Workbook

Sheet ODHAV 
A1: NUTAN NAGARIK SAHAKARI BANK LTD (GUJARAT BRANCHES & HEAD OFFICE)
A3: BRANCH NAME : ODHAV BRANCH
A4: BRANCH CODE: 21
A5: SUMMARY OF INCOME FOR THE MONTH OF SEP 2026
A7: CODE NO. | B7: PARTICULARS | D7: GGST | E7: CGST | F7: IGST
A8: PL
A9: 3303 | B9: DD CANCEL CHARGES | D9: =+C9*9% | E9: =+D9 | F9: =IF(D9>0," ",C9*18%)
A10: 3200 | B10: COMMISION ON BILLS | D10: =+C10*9% | E10: =+D10 | F10: =IF(D10>0," ",C10*18%)
A11: 3215 | B11: COMMISION ON PAYORDER | D11: =+C11*9% | E11: =+D11 | F11: =IF(D11>0," ",C11*18%)
A12: 3220 | B12: COMMISION ON U.B.D. | D12: =+C12*9% | E12: =+D12 | F12: =IF(D12>0," ",C12*18%)
A13: 3225 | B13: COMMISION I.B.C. | D13: =+C13*9% | E13: =+D13 | F13: =IF(D13>0," ",C13*18%)
A14: 3230 | B14: COMMISION ON GUARANTEE | D14: =+C14*9% | E14: =+D14 | F14: 0
A15: 3235 | B15: COMMISION ON DEMAND DRAFT | D15: =+C15*9% | E15: =+D15 | F15: =IF(D15>0," ",C15*18%)
A16: 3240 | B16: COMMISION ON U.B.C. | D16: =+C16*9% | E16: =+D16 | F16: =IF(D16>0," ",C16*18%)
A17: 3245 | B17: COMMISION ON L.C. | D17: =+C17*9% | E17: =+D17 | F17: =IF(D17>0," ",C17*18%)
A18: 3250 | B18: COMMISSION ON GUARANTEE | D18: =+C18*9% | E18: =+D18 | F18: =IF(D18>0," ",C18*18%)
A19: 3270 | B19: PROCESSING CHARGE | D19: =+C19*9% | E19: =+D19 | J19: =+G19*9%
A20: 3271 | B20: RENEWAL FEES | D20: =+C20*9% | E20: =+D20 | F20: =IF(D20>0," ",C20*18%)
A21: 3274 | B21: INCOME FROM E-STAMPING
A22: 3276 | B22: COMMISION ON PAN | D22: =+C22*9% | E22: =+D22 | F22: =IF(D22>0," ",C22*18%)
A23: 3280 | B23: INSURANCE PREMIUM | D23: =+C23*9% | E23: =+D23 | F23: =IF(D23>0," ",C23*18%)
A24: 3281 | B24: ATM CHARGES | D24: =+C24*9% | E24: =+D24 | F24: 0
A25: 3285 | B25: COMMISION ON RTGS | D25: =+C25*9% | E25: =+D25 | F25: =IF(D25>0," ",C25*18%)
A26: 3286 | B26: COMMISION ON PMJJBY LIC | D26: =+C26*9% | E26: =+D26 | F26: =IF(D26>0," ",C26*18%)
A27: 3287 | B27: COMM. ON PMSBY NEW INDIA ASSURANCE | D27: =+C27*9% | E27: =+D27 | F27: =IF(D27>0," ",C27*18%)
A28: 3291 | B28: CIBIL CHARGES | D28: =+C28*9% | E28: =+D28 | F28: =IF(D28>0," ",C28*18%)
A29: 3296 | B29: RTGS/NEFT MANUAL CHARGES | D29: =+C29*9% | E29: =+D29 | F29: =IF(D29>0," ",C29*18%)
A30: 3297 | B30: ASBA FORM PRINT CHARGES | D30: =+C30*9% | E30: =+D30 | F30: =IF(D30>0," ",C30*18%)
A31: 3298 | B31: MANDATE HANDLING CHARGES | D31: =+C31*9% | E31: =+D31 | F31: =IF(D31>0," ",C31*18%)
A32: 3299 | B32: SI EXECUTION FAILED CHARGES | D32: =+C32*9% | E32: =+D32 | F32: =IF(D32>0," ",C32*18%)
A33: 3300 | B33: INCIDENTAL CHARGES | D33: =+C33*9% | E33: =+D33 | F33: =IF(D33>0," ",C33*18%)
A34: 3301 | B34: INOPERATIVE CHARGES | D34: =+C34*9% | E34: =+D34 | F34: =IF(D34>0," ",C34*18%)
A35: 3302 | B35: PO CANCEL CHARGES | D35: =+C35*9% | E35: =+D35 | F35: =IF(D35>0," ",C35*18%)
A36: 3305 | B36: A/C SHARE TRANSFER FEES | D36: =+C36*9% | E36: =+D36 | F36: =IF(D36>0," ",C36*18%)
A37: 3309 | B37: MIS. INCOME WITH GST | D37: =+C37*9% | E37: =+D37 | F37: =IF(D37>0," ",C37*18%)
A38: 3310 | B38: MIS. INCOME | D38: =+C38*9% | E38: =+D38 | F38: =IF(D38>0," ",C38*18%)
A39: 3311 | B39: I/W CHQ. RET. CHARGES | D39: =+C39*9% | E39: =+D39 | F39: =IF(D39>0," ",C39*18%)
A40: 3312 | B40: O/W CHQ. RET. CHARGES | D40: =+C40*9% | E40: =+D40 | F40: =IF(D40>0," ",C40*18%)
A41: 3313 | B41: ECS RETD. CHARGES | D41: =+C41*9% | E41: =+D41 | F41: =IF(D41>0," ",C41*18%) | J41: =3000*9%
A42: 3314 | B42: CHQ. BOOK ISSUE CHARGES | D42: =+C42*9% | E42: =+D42 | F42: =IF(D42>0," ",C42*18%) | K42: =9000*9%
A43: 3315 | B43: CHARGES ON GODOWNS | D43: =+C43*9% | E43: =+D43 | F43: =IF(D43>0," ",C43*18%)
A44: 3316 | B44: CASH CHARGES | D44: =+C44*9% | E44: =+D44 | F44: =IF(D44>0," ",C44*18%)
A45: 3317 | B45: THE P&T CHARGES FOR LC/BG | D45: =+C45*9% | E45: =+D45 | F45: =IF(D45>0," ",C45*18%)
A46: 3318 | B46: OBC POSTAGE CHARGES | D46: =+C46*9% | E46: =+D46 | F46: =IF(D46>0," ",C46*18%)
A47: 3320 | B47: RENT ON LOCKER | D47: =+C47*9% | E47: =+D47 | F47: =IF(D47>0," ",C47*18%) | J47: =26800-4679
A48: 3321 | B48: ADHOC LIMIT CHARGES | D48: =+C48*9% | E48: =+D48 | F48: =IF(D48>0," ",C48*18%)
A49: 3322 | B49: INCOME FROM SALE OF OLD NEWS PAPERS | D49: =+C49*9% | E49: =+D49 | F49: =IF(D49>0," ",C49*18%)
A50: 3324 | B50: PENALTY ON OVERDUE RENT ON LOCKER | D50: =+C50*9% | E50: =+D50 | F50: =IF(D50>0," ",C50*18%)
A51: 3325 | B51: MICR CHARGES | D51: =+C51*2.5% | E51: =+D51 | F51: =IF(D51>0," ",C51*18%)
A52: 3391 | B52: SMS CHARGES INCOME RECEIVED | D52: =+C52*9% | E52: =+D52 | F52: =IF(D52>0," ",C52*18%)
A53: 3359 | B53: COMMITTMENT CHARGES | D53: =+C53*9% | E53: =+D53 | F53: 0
A54: 3825 | B54: EXTERNAL AUDIT FEES | D54: =+C54*9% | E54: =+D54 | F54: =IF(D54>0," ",C54*18%)
A55: 3362 | B55: FORECLOSURE CHARGES | D55: =+C55*9% | E55: =+D55 | F55: =IF(D55>0," ",C55*18%)
A56: 3340 | B56: LOAN PROCESSING FEES | D56: =+C56*9% | E56: =+D56 | F56: =IF(D56>0," ",C56*18%)
A57: GL | D57: =+C57*9% | E57: =+D57 | F57: =IF(D57>0," ",C57*18%)
A58: 1720 | B58: COMM. RECD. BUT NOT ACCRUED | D58: =+C58*9% | E58: =+D58 | F58: 0
A59: 1836 | B59: RENT ON LOCKER RECEIVED BUT | D59: =+C59*9% | E59: =+D59 | F59: =IF(D59>0," ",C59*18%) | I59: =+G59*0.09
B60: NOT ACCRUED | D60: =+C60*9% | E60: =+D60 | F60: =IF(D60>0," ",C60*18%)
B61: SALE OF ASSET ( CASH COUNTING MACHINE) | D61: =+C61*9% | E61: =+D61 | F61: 0
B62: TOTAL : | C62: =SUM(C9:C61) | D62: =SUM(D9:D61) | E62: =SUM(E9:E61) | F62: =SUM(F9:F61) | G62: =+SUM(G9:G60) | H62: =SUM(H9:H60)
A63: RCM
A64: PL 3750 | B64: LAW CHARGES (EXCLUSIVE) | D64: =+C64*9% | E64: =+D64 | F64: =IF(D64>0," ",C64*18%)
A65: PL 3751 | B65: INCIDENTAL LAW CHARGES (EXCLUSIVE) | C65: 0 | D65: =+C65*9% | E65: =+D65 | F65: =IF(D65>0," ",C65*18%) | G65: =+C62*0.09
A66: SUMMARY
H67: 0
A68: (1) INCOME
A69: PARTICULARS | D69: GGST | E69: CGST | F69: IGST
A71: (1) INCOME AS PER LEDGERWISE CALCULATION | D71: =+D62 | E71: =+E62 | F71: =+F62
A72: (2) REFUND GIVEN BUT GST REFUND NOT GIVEN | C72: =+G62 | D72: =C72*0.09 | E72: =+C72*0.09 | F72: 0
D73: =+D71+D72 | E73: =+E71+E72 | F73: =SUM(F71:F72)
A74: (3) PAYABLE AS PER LEDGER | D74: 14387.8 | E74: =+D74 | F74: 0
A75: DIFFERENCE | D75: =+D73-D74 | E75: =+E73-E74 | F75: =+F74-F71 | G75: =+D75/9*100
A77: (2) INPUT TAX CREDIT
A78: PARTICULARS | D78: GL 8546 GGST | E78: GL 8547 CGST | F78: GL 8548 IGST
A81: CURRENT MONTH INPUT TAX CREDIT AVAILABLE | D81: 2672.55 | E81: =+D81 | F81: 0 | G81: =+D81/2 | H81: =+E81/2 | I81: =+F81/2
A82: LESS : CREDIT CANNOT BE UTILISED (BCUZ GST NO NOT AVAILABLE IN BILL) | D82: =+C96 | E82: =+D82 | F82: =+E96 | G82: =+D82/2 | H82: =+E82/2 | I82: =+F82/2
A83: ELIGIBLE CREDIT | D83: =+D81-D82 | E83: =+E81-E82 | F83: =+F81-F82 | G83: =+D83/2 | H83: =+E83/2 | I83: =+F83/2
B85: OUR GST NO. NOT REFLECTED ON CENVAT BILLS & BLOCKED CREDIT
B86: PARTY NAME | C86: GGST | D86: CGST | E86: IGST
B87: BSNL | D87: =+C87 | E87: 0
B88: BSNL | C88: 0 | D88: =+C88 | E88: 0
B89: BSNL | C89: 0 | D89: =+C89 | E89: 0
B90: BSNL | C90: 0 | D90: =+C90 | E90: 0
B91: BSNL | C91: 0 | D91: =+C91 | E91: 0
B92: BSNL | C92: 0 | D92: =+C92 | E92: 0
B93: BSNL | C93: 0 | D93: =+C93 | E93: 0
B94: ROHAN Agency | C94: 0 | D94: =+C94 | E94: 0
B95: MAA BEVERAGES | C95: 0 | D95: =+C95 | E95: 0
C96: =SUM(C87:C95) | D96: =SUM(D87:D95) | E96: =SUM(E87:E95)

Sheet RAKHIAL
A1: NUTAN NAGARIK SAHAKARI BANK LTD (GUJARAT BRANCHES & HEAD OFFICE)
A3: BRANCH NAME : RAKHIAL BRANCH
A4: BRANCH CODE: 06
A5: =+'ODHAV '!A5
A7: CODE NO. | B7: PARTICULARS | D7: GGST | E7: CGST | F7: IGST
A8: PL
A9: 3303 | B9: DD CANCEL CHARGES | D9: =+C9*9% | E9: =+D9 | F9: =IF(D9>0," ",C9*18%)
A10: 3200 | B10: COMMISION ON BILLS | D10: =+C10*9% | E10: =+D10 | F10: =IF(D10>0," ",C10*18%)
A11: 3215 | B11: COMMISION ON PAYORDER | D11: =+C11*9% | E11: =+D11 | F11: =IF(D11>0," ",C11*18%)
A12: 3220 | B12: COMMISION ON U.B.D. | D12: =+C12*9% | E12: =+D12 | F12: =IF(D12>0," ",C12*18%)
A13: 3225 | B13: COMMISION I.B.C. | D13: =+C13*9% | E13: =+D13 | F13: =IF(D13>0," ",C13*18%)
A14: 3230 | B14: COMMISION ON GUARANTEE | D14: =+C14*9% | E14: =+D14 | F14: 0
A15: 3235 | B15: COMMISION ON DEMAND DRAFT | D15: =+C15*9% | E15: =+D15 | F15: =IF(D15>0," ",C15*18%)
A16: 3240 | B16: COMMISION ON U.B.C. | D16: =+C16*9% | E16: =+D16 | F16: =IF(D16>0," ",C16*18%)
A17: 3245 | B17: COMMISION ON L.C. | D17: =+C17*9% | E17: =+D17 | F17: =IF(D17>0," ",C17*18%)
A18: 3250 | B18: COMMISSION ON GUARANTEE | D18: =+C18*9% | E18: =+D18 | F18: =IF(D18>0," ",C18*18%)
A19: 3270 | B19: PROCESSING CHARGE | D19: =+C19*9% | E19: =+D19 | F19: =IF(D19>0," ",C19*18%)
A20: 3271 | B20: RENEWAL FEES | D20: =+C20*9% | E20: =+D20
A21: 3274 | B21: INCOME FROM E-STAMPING | D21: =+C21*9% | E21: =+D21 | F21: =IF(D21>0," ",C21*18%)
A22: 3276 | B22: COMMISION ON PAN | D22: =+C22*9% | E22: =+D22 | F22: =IF(D22>0," ",C22*18%)
A23: 3280 | B23: INSURANCE PREMIUM | D23: =+C23*9% | E23: =+D23 | F23: =IF(D23>0," ",C23*18%)
A24: 3281 | B24: ATM CHARGES | D24: =+C24*9% | E24: =+D24 | F24: =IF(D24>0," ",C24*18%)
A25: 3285 | B25: COMMISION ON RTGS | D25: =+C25*9% | E25: =+D25 | F25: =IF(D25>0," ",C25*18%)
A26: 3286 | B26: COMMISION ON PMJJBY LIC | D26: =+C26*9% | E26: =+D26 | F26: =IF(D26>0," ",C26*18%)
A27: 3287 | B27: COMM. ON PMSBY NEW INDIA ASSURANCE | D27: =+C27*9% | E27: =+D27 | F27: =IF(D27>0," ",C27*18%)
A28: 3291 | B28: CIBIL CHARGES | D28: =+C28*9% | E28: =+D28 | F28: =IF(D28>0," ",C28*18%)
A29: 3296 | B29: RTGS/NEFT MANUAL CHARGES | D29: =+C29*9% | E29: =+D29 | F29: =IF(D29>0," ",C29*18%)
A30: 3297 | B30: ASBA FORM PRINT CHARGES | D30: =+C30*9% | E30: =+D30 | F30: =IF(D30>0," ",C30*18%)
A31: 3298 | B31: MANDATE HANDLING CHARGES | D31: =+C31*9% | E31: =+D31 | F31: =IF(D31>0," ",C31*18%)
A32: 3299 | B32: SI EXECUTION FAILED CHARGES | D32: =+C32*9% | E32: =+D32 | F32: =IF(D32>0," ",C32*18%)
A33: 3300 | B33: INCIDENTAL CHARGES | D33: =+C33*9% | E33: =+D33 | F33: 0
A34: 3301 | B34: INOPERATIVE CHARGES | D34: =+C34*9% | E34: =+D34 | F34: =IF(D34>0," ",C34*18%)
A35: 3302 | B35: PO CANCEL CHARGES | D35: =+C35*9% | E35: =+D35 | F35: =IF(D35>0," ",C35*18%)
A36: 3305 | B36: A/C SHARE TRANSFER FEES | D36: =+C36*9% | E36: =+D36 | F36: =IF(D36>0," ",C36*18%)
A37: 3309 | B37: MIS. INCOME WITH GST | D37: =+C37*9% | E37: =+D37 | F37: =IF(D37>0," ",C37*18%)
A38: 3310 | B38: MIS. INCOME | D38: =+C38*9% | E38: =+D38 | F38: =IF(D38>0," ",C38*18%)
A39: 3311 | B39: I/W CHQ. RET. CHARGES | D39: =+C39*9% | E39: =+D39 | F39: =IF(D39>0," ",C39*18%)
A40: 3312 | B40: O/W CHQ. RET. CHARGES | D40: =+C40*9% | E40: =+D40 | F40: =IF(D40>0," ",C40*18%)
A41: 3313 | B41: ECS RETD. CHARGES | D41: =+C41*9% | E41: =+D41 | F41: =IF(D41>0," ",C41*18%)
A42: 3314 | B42: CHQ. BOOK ISSUE CHARGES | D42: =+C42*9% | E42: =+D42 | F42: =IF(D42>0," ",C42*18%)
A43: 3315 | B43: CHARGES ON GODOWNS | D43: =+C43*9% | E43: =+D43 | F43: =IF(D43>0," ",C43*18%)
A44: 3316 | B44: CASH CHARGES | D44: =+C44*9% | E44: =+D44 | F44: =IF(D44>0," ",C44*18%)
A45: 3317 | B45: THE P&T CHARGES FOR LC/BG | D45: =+C45*9% | E45: =+D45 | F45: 0
A46: 3318 | B46: OBC POSTAGE CHARGES | D46: =+C46*9% | E46: =+D46 | F46: =IF(D46>0," ",C46*18%)
A47: 3320 | B47: RENT ON LOCKER | D47: =+C47*9% | E47: =+D47 | F47: 0
A48: 3321 | B48: ADHOC LIMIT CHARGES | D48: =+C48*9% | E48: =+D48 | F48: =IF(D48>0," ",C48*18%)
A49: 3322 | B49: INCOME FROM SALE OF OLD NEWS PAPERS | D49: =+C49*9% | E49: =+D49 | F49: =IF(D49>0," ",C49*18%)
A50: 3324 | B50: PENALTY ON OVERDUE LOCKER RENT | D50: =+C50*9% | E50: =+D50 | F50: =IF(D50>0," ",C50*18%)
A51: 3325 | B51: MICR CHARGES | D51: =+C51*2.5% | E51: =+D51 | F51: =IF(D51>0," ",C51*18%)
A52: 3391 | B52: SMS CHARGES INCOME RECEIVED | D52: =+C52*9% | E52: =+D52 | F52: =IF(D52>0," ",C52*18%)
A53: 3359 | B53: COMMITMENT CHARGES | D53: =+C53*9% | E53: =+D53
A54: 3825 | B54: EXTERNAL AUDIT FEES | D54: =+C54*9% | E54: =+D54
A55: 3362 | B55: FORECLOSURE CHARGES | D55: =+C55*9% | E55: =+D55
A56: 3340 | B56: LOAN PROCESSING FEES | D56: =+C56*9% | E56: =+D56
A57: GL | D57: =+C57*9% | E57: =+D57
A58: 1720 | B58: COMM. RECD. BUT NOT ACCRUED | D58: =+C58*9% | E58: =+D58 | F58: 0
A59: 1836 | B59: RENT ON LOCKER RECEIVED BUT | D59: =+C59*9% | E59: =+D59 | F59: =IF(D59>0," ",C59*18%)
B60: NOT ACCRUED
B61: SALE OF ASSET ( CASH COUNTING MACHINE) | D61: =+C61*9% | E61: =+D61
B62: TOTAL : | C62: =SUM(C9:C61) | D62: =SUM(D9:D61) | E62: =SUM(E9:E61) | F62: =SUM(F9:F61) | G62: =+SUM(G9:G60) | H62: =+SUM(H9:H60)
A63: RCM
A64: PL 3750 | B64: LAW CHARGES (EXCLUSIVE) | C64: 0 | D64: =+C64*9% | E64: =+D64 | F64: =IF(D64>0," ",C64*18%)
A65: PL 3751 | B65: INCIDENTAL LAW CHARGES (EXCLUSIVE) | C65: 0 | D65: =+C65*9% | E65: =+D65 | F65: =IF(D65>0," ",C65*18%) | G65: =+C62*9%
A66: SUMMARY
A68: (1) INCOME
A69: PARTICULARS | D69: GGST | E69: CGST | F69: IGST
A71: (1) INCOME AS PER LEDGERWISE CALCULATION | D71: =+D62 | E71: =+E62 | F71: =+F62
A72: (2) REFUND GIVEN BUT GST REFUND NOT GIVEN | C72: =+G62 | D72: =C72*0.09 | E72: =+C72*0.09 | F72: 0
D73: =+D71+D72 | E73: =+E71+E72 | F73: 0
A74: (3) PAYABLE AS PER LEDGER | D74: 18891.48 | E74: =+D74 | F74: 0
A75: DIFFERENCE | D75: =+D73-D74 | E75: =+E73-E74 | F75: =IF(F71>F74,F71,F74) | G75: =+E75/0.09
A77: (2) INPUT TAX CREDIT
A78: PARTICULARS | D78: GL 8546 GGST | E78: GL 8547 CGST | F78: GL 8548 IGST
A81: CURRENT MONTH INPUT TAX CREDIT AVAILABLE | D81: 1575 | E81: =+D81 | F81: 0 | G81: =+D81/2 | H81: =+E81/2 | I81: =+F81/2
A82: LESS : CREDIT CANNOT BE UTILISED (BCUZ GST NO NOT AVAILABLE IN BILL) | D82: =C92 | E82: =+D92 | F82: =+E92 | G82: =+D82/2 | H82: =+E82/2 | I82: =+F82/2
A83: ELIGIBLE CREDIT | D83: =+D81-D82 | E83: =+E81-E82 | F83: =+F81-F82 | G83: =+D83/2 | H83: =+E83/2 | I83: =+F83/2
B86: OUR GST NO. NOT REFLECTED ON CENVAT BILLS
B87: PARTY NAME | C87: GGST | D87: CGST | E87: IGST
B88: ROHAN AGENCY | C88: 0 | D88: =+C88 | E88: 0
B89: ROHAN AGENCY | C89: 0 | D89: =+C89 | E89: 0
C90: 0 | D90: =+C90 | E90: 0
C91: 0 | D91: 0
C92: =SUM(C88:C91) | D92: =SUM(D88:D91) | E92: =SUM(E88:E90)

Sheet NEW SHARDA
A1: NUTAN NAGARIK SAHAKARI BANK LTD (GUJARAT BRANCHES & HEAD OFFICE) | L1: 6357077131
A3: BRANCH NAME : NEW SHARDA MANDIR BRANCH
A4: BRANCH CODE: 16
A5: =+CHANGODAR!A5
A7: CODE NO. | B7: PARTICULARS | D7: GGST | E7: CGST | F7: IGST | I7: LOCKER CLOSED
A8: PL
A9: 3303 | B9: DD CANCEL CHARGES | D9: =+C9*9% | E9: =+D9 | F9: =IF(D9>0," ",C9*18%)
A10: 3200 | B10: COMMISION ON BILLS | D10: =+C10*9% | E10: =+D10 | F10: =IF(D10>0," ",C10*18%)
A11: 3215 | B11: COMMISION ON PAYORDER | D11: =+C11*9% | E11: =+D11 | F11: =IF(D11>0," ",C11*18%)
A12: 3220 | B12: COMMISION ON U.B.D. | D12: =+C12*9% | E12: =+D12 | F12: =IF(D12>0," ",C12*18%)
A13: 3225 | B13: COMMISION I.B.C. | D13: =+C13*9% | E13: =+D13 | F13: =IF(D13>0," ",C13*18%)
A14: 3230 | B14: COMMISION ON GUARANTEE | D14: =+C14*9% | E14: =+D14 | F14: =IF(D14>0," ",C14*18%)
A15: 3235 | B15: COMMISION ON DEMAND DRAFT | D15: =+C15*9% | E15: =+D15 | F15: =IF(D15>0," ",C15*18%)
A16: 3240 | B16: COMMISION ON U.B.C. | D16: =+C16*9% | E16: =+D16 | F16: =IF(D16>0," ",C16*18%)
A17: 3245 | B17: COMMISION ON L.C. | D17: =+C17*9% | E17: =+D17 | F17: =IF(D17>0," ",C17*18%)
A18: 3250 | B18: COMMISSION ON GUARANTEE | D18: =+C18*9% | E18: =+D18 | F18: =IF(D18>0," ",C18*18%)
A19: 3270 | B19: PROCESSING CHARGE | D19: =+C19*9% | E19: =+D19 | F19: =IF(D19>0," ",C19*18%)
A20: 3271 | B20: RENEWAL FEES | D20: =+C20*9% | E20: =+D20 | F20: =IF(D20>0," ",C20*18%)
A21: 3274 | B21: INCOME FROM E-STAMPING
A22: 3276 | B22: COMMISION ON PAN | D22: =+C22*9% | E22: =+D22 | F22: =IF(D22>0," ",C22*18%)
A23: 3280 | B23: INSURANCE PREMIUM | D23: =+C23*9% | E23: =+D23 | F23: =IF(D23>0," ",C23*18%)
A24: 3281 | B24: ATM CHARGES | D24: =+C24*9% | E24: =+D24 | F24: 0
A25: 3285 | B25: COMMISION ON RTGS | D25: =+C25*9% | E25: =+D25 | F25: =IF(D25>0," ",C25*18%)
A26: 3286 | B26: COMMISION ON PMJJBY LIC | D26: =+C26*9% | E26: =+D26 | F26: =IF(D26>0," ",C26*18%)
A27: 3287 | B27: COMM. ON PMSBY NEW INDIA ASSURANCE | D27: =+C27*9% | E27: =+D27 | F27: =IF(D27>0," ",C27*18%)
A28: 3291 | B28: CIBIL CHARGES | D28: =+C28*9% | E28: =+D28 | F28: =IF(D28>0," ",C28*18%)
A29: 3296 | B29: RTGS/NEFT MANUAL CHARGES | D29: =+C29*9% | E29: =+D29 | F29: =IF(D29>0," ",C29*18%)
A30: 3297 | B30: ASBA FORM PRINT CHARGES | D30: =+C30*9% | E30: =+D30 | F30: =IF(D30>0," ",C30*18%)
A31: 3298 | B31: MANDATE HANDLING CHARGES | D31: =+C31*9% | E31: =+D31 | F31: =IF(D31>0," ",C31*18%)
A32: 3299 | B32: SI EXECUTION FAILED CHARGES | D32: =+C32*9% | E32: =+D32 | F32: =IF(D32>0," ",C32*18%)
A33: 3300 | B33: INCIDENTAL CHARGES | D33: =+C33*9% | E33: =+D33 | F33: 0
A34: 3301 | B34: INOPERATIVE CHARGES | D34: =+C34*9% | E34: =+D34 | F34: =IF(D34>0," ",C34*18%)
A35: 3302 | B35: PO CANCEL CHARGES | D35: =+C35*9% | E35: =+D35 | F35: =IF(D35>0," ",C35*18%)
A36: 3305 | B36: A/C SHARE TRANSFER FEES | D36: =+C36*9% | E36: =+D36 | F36: =IF(D36>0," ",C36*18%)
A37: 3309 | B37: MIS. INCOME WITH GST | D37: =+C37*9% | E37: =+D37 | F37: =IF(D37>0," ",C37*18%)
A38: 3310 | B38: MIS. INCOME | D38: =+C38*9% | E38: =+D38 | F38: 0
A39: 3311 | B39: I/W CHQ. RET. CHARGES | D39: =+C39*9% | E39: =+D39 | F39: =IF(D39>0," ",C39*18%)
A40: 3312 | B40: O/W CHQ. RET. CHARGES | D40: =+C40*9% | E40: =+D40 | F40: 0
A41: 3313 | B41: ECS RETD. CHARGES | D41: =+C41*9% | E41: =+D41 | F41: =IF(D41>0," ",C41*18%)
A42: 3314 | B42: CHQ. BOOK ISSUE CHARGES | D42: =+C42*9% | E42: =+D42 | F42: =IF(D42>0," ",C42*18%)
A43: 3315 | B43: CHARGES ON GODOWNS | D43: =+C43*9% | E43: =+D43 | F43: =IF(D43>0," ",C43*18%)
A44: 3316 | B44: CASH CHARGES | D44: =+C44*9% | E44: =+D44 | F44: =IF(D44>0," ",C44*18%)
A45: 3317 | B45: THE P&T CHARGES FOR LC/BG | D45: =+C45*9% | E45: =+D45 | F45: =IF(D45>0," ",C45*18%)
A46: 3318 | B46: OBC POSTAGE CHARGES | D46: =+C46*9% | E46: =+D46 | F46: =IF(D46>0," ",C46*18%)
A47: 3320 | B47: RENT ON LOCKER | D47: =+C47*9% | E47: =+D47 | F47: =IF(D47>0," ",C47*18%)
A48: 3321 | B48: ADHOC LIMIT CHARGES | D48: =+C48*9% | E48: =+D48 | F48: =IF(D48>0," ",C48*18%)
A49: 3322 | B49: INCOME FROM SALE OF OLD NEWS PAPERS | D49: =+C49*9% | E49: =+D49
A50: 3324 | B50: PENALTY ON OVERDUE LOCKER RENT | D50: =+C50*0.09 | E50: =+D50
A51: 3325 | B51: MICR CHARGES | D51: =+C51*2.5% | E51: =+D51 | F51: =IF(D51>0," ",C51*18%)
A52: 3391 | B52: SMS CHARGES INCOME RECEIVED | D52: =+C52*9% | E52: =+D52 | F52: =IF(D52>0," ",C52*18%)
A53: 3359 | B53: COMMITMENT CHARGES | D53: =+C53*9% | E53: =+D53
A54: 3825 | B54: EXTERNAL AUDIT FEES | D54: =+C54*9% | E54: =+D54
A55: 3362 | B55: FORECLOSURE CHARGES
A56: 3340 | B56: LOAN PROCESSING FEES | D56: =+C56*9% | E56: =+D56
A57: GL
A58: 1720 | B58: COMM. RECD. BUT NOT ACCRUED | D58: =+C58*9% | E58: =+D58 | F58: =IF(D58>0," ",C58*18%)
A59: 1836 | B59: RENT ON LOCKER RECEIVED BUT | D59: =+C59*9% | E59: =+D59 | F59: =IF(D59>0," ",C59*18%) | I59: 0
B60: NOT ACCRUED
B61: SALE OF ASSET ( CASH COUNTING MACHINE) | D61: =+C61*0.09 | E61: =+D61
B62: TOTAL : | C62: =SUM(C9:C61) | D62: =SUM(D9:D61) | E62: =SUM(E9:E61) | F62: =SUM(F9:F61) | G62: =SUM(G9:G59) | H62: =SUM(H9:H59) | I62: =SUM(I9:I59)
A63: RCM
A64: PL 3750 | B64: LAW CHARGES (EXCLUSIVE) | C64: 0 | D64: =+C64*9% | E64: =+D64 | F64: =IF(D64>0," ",C64*18%)
A65: PL 3751 | B65: INCIDENTAL LAW CHARGES (EXCLUSIVE) | C65: 0 | D65: =+C65*9% | E65: =+D65 | F65: =IF(D65>0," ",C65*18%) | G65: =+C62*0.09
A66: SUMMARY
A68: (1) INCOME
A69: PARTICULARS | D69: GGST | E69: CGST | F69: IGST
A71: (1) INCOME AS PER LEDGERWISE CALCULATION | D71: =+D62 | E71: =+E62 | F71: =+F62
A72: (2) REFUND GIVEN BUT GST REFUND NOT GIVEN | C72: =G62 | D72: =+C72*0.09 | E72: =+C72*0.09 | F72: 0
D73: =SUM(D71:D72) | E73: =+D73 | F73: 0
A74: (3) PAYABLE AS PER LEDGER | E74: =+D74 | F74: 0
A75: DIFFERENCE | D75: =+D73-D74 | E75: =+E73-E74 | F75: =IF(F71>F74,F71,F74) | G75: =D75/9%
A77: (2) INPUT TAX CREDIT
A78: PARTICULARS | D78: GL 8546 GGST | E78: GL 8547 CGST | F78: GL 8548 IGST
A81: CURRENT MONTH INPUT TAX CREDIT AVAILABLE | E81: =+D81 | F81: 0 | G81: =+D81/2 | H81: =+E81/2 | I81: =+F81/2
A82: LESS : CREDIT CANNOT BE UTILISED (BCUZ GST NO NOT AVAILABLE IN BILL) | D82: =+C93 | E82: =+D82 | F82: 0 | G82: =+D82/2 | H82: =+E82/2 | I82: =+F82/2
A83: ELIGIBLE CREDIT | D83: =+D81-D82 | E83: =+E81-E82 | F83: =+F81-F82 | G83: =+D83/2 | H83: =+E83/2 | I83: =+F83/2
B86: INELIGIBLE CREDIT
B87: PARTY NAME | C87: GGST | D87: CGST | E87: IGST
B88: BSNL | D88: =+C88
B89: BSNL | D89: =+C89
A90: BLOCK CREDIT | B90: ROHAN AGENCY | D90: =+C90
A91: BLOCK CREDIT | B91: HRPL RESTAURANTS PVT LTD | D91: =+C91
B92: BSNL | C92: 0 | D92: =+C92
B93: TOTAL | C93: =SUM(C88:C92) | D93: =SUM(D88:D92)

Sheet CHANGODAR
A1: NUTAN NAGARIK SAHAKARI BANK LTD (GUJARAT BRANCHES & HEAD OFFICE)
A3: BRANCH NAME : CHANGODAR BRANCH
A4: BRANCH CODE: 20
A5: =+RAKHIAL!A5
A7: CODE NO. | B7: PARTICULARS | D7: GGST | E7: CGST | F7: IGST
A8: PL
A9: 3303 | B9: DD CANCEL CHARGES | D9: =+C9*9% | E9: =+D9 | F9: =IF(D9>0," ",C9*18%)
A10: 3200 | B10: COMMISION ON BILLS | D10: =+C10*9% | E10: =+D10 | F10: 0
A11: 3215 | B11: COMMISION ON PAYORDER | D11: =+C11*9% | E11: =+D11 | F11: 0
A12: 3220 | B12: COMMISION ON U.B.D. | D12: =+C12*9% | E12: =+D12 | F12: =IF(D12>0," ",C12*18%)
A13: 3225 | B13: COMMISION I.B.C. | D13: =+C13*9% | E13: =+D13 | F13: =IF(D13>0," ",C13*18%)
A14: 3230 | B14: COMMISION ON GUARANTEE | D14: =+C14*9% | E14: =+D14 | F14: =IF(D14>0," ",C14*18%)
A15: 3235 | B15: COMMISION ON DEMAND DRAFT | D15: =+C15*9% | E15: =+D15 | F15: 0
A16: 3240 | B16: COMMISION ON U.B.C. | D16: =+C16*9% | E16: =+D16 | F16: =IF(D16>0," ",C16*18%)
A17: 3245 | B17: COMMISION ON L.C. | D17: =+C17*9% | E17: =+D17 | F17: 0
A18: 3250 | B18: COMMISSION ON GUARANTEE | D18: =+C18*9% | E18: =+D18 | F18: =IF(D18>0," ",C18*18%)
A19: 3270 | B19: PROCESSING CHARGE | D19: =+C19*9% | E19: =+D19 | F19: 0
A20: 3271 | B20: RENEWAL FEES | D20: =+C20*9% | E20: =+D20
A21: 3274 | B21: INCOME FROM E-STAMPING
A22: 3276 | B22: COMMISION ON PAN | D22: =+C22*9% | E22: =+D22 | F22: =IF(D22>0," ",C22*18%)
A23: 3280 | B23: INSURANCE PREMIUM | D23: =+C23*9% | E23: =+D23 | F23: =IF(D23>0," ",C23*18%)
A24: 3281 | B24: ATM CHARGES | D24: =+C24*9% | E24: =+D24 | F24: 0
A25: 3285 | B25: COMMISION ON RTGS | D25: =+C25*9% | E25: =+D25
A26: 3286 | B26: COMMISION ON PMJJBY LIC | D26: =+C26*9% | E26: =+D26 | F26: =IF(D26>0," ",C26*18%)
A27: 3287 | B27: COMM. ON PMSBY NEW INDIA ASSURANCE | D27: =+C27*9% | E27: =+D27 | F27: =IF(D27>0," ",C27*18%)
A28: 3291 | B28: CIBIL CHARGES | D28: =+C28*9% | E28: =+D28 | F28: =IF(D28>0," ",C28*18%)
A29: 3296 | B29: RTGS/NEFT MANUAL CHARGES | D29: =+C29*9% | E29: =+D29 | F29: =IF(D29>0," ",C29*18%)
A30: 3297 | B30: ASBA FORM PRINT CHARGES | D30: =+C30*9% | E30: =+D30 | F30: 0
A31: 3298 | B31: MANDATE HANDLING CHARGES | D31: =+C31*9% | E31: =+D31 | F31: =IF(D31>0," ",C31*18%)
A32: 3299 | B32: SI EXECUTION FAILED CHARGES | D32: =+C32*9% | E32: =+D32 | F32: =IF(D32>0," ",C32*18%)
A33: 3300 | B33: INCIDENTAL CHARGES | D33: =+C33*9% | E33: =+D33 | F33: 0
A34: 3301 | B34: INOPERATIVE CHARGES | D34: =+C34*9% | E34: =+D34 | F34: =IF(D34>0," ",C34*18%)
A35: 3302 | B35: PO CANCEL CHARGES | D35: =+C35*9% | E35: =+D35 | F35: =IF(D35>0," ",C35*18%)
A36: 3305 | B36: A/C SHARE TRANSFER FEES | D36: =+C36*9% | E36: =+D36 | F36: =IF(D36>0," ",C36*18%)
A37: 3309 | B37: MIS. INCOME WITH GST | D37: =+C37*9% | E37: =+D37 | F37: =IF(D37>0," ",C37*18%)
A38: 3310 | B38: MIS. INCOME | D38: =+C38*9% | E38: =+D38 | F38: 0
A39: 3311 | B39: I/W CHQ. RET. CHARGES | D39: =+C39*9% | E39: =+D39 | F39: 0
A40: 3312 | B40: O/W CHQ. RET. CHARGES | D40: =+C40*9% | E40: =+D40 | F40: 0
A41: 3313 | B41: ECS RETD. CHARGES | D41: =+C41*9% | E41: =+D41 | F41: 0
A42: 3314 | B42: CHQ. BOOK ISSUE CHARGES | D42: =+C42*9% | E42: =+D42 | F42: 0
A43: 3315 | B43: CHARGES ON GODOWNS | D43: =+C43*9% | E43: =+D43 | F43: 0
A44: 3316 | B44: CASH CHARGES | D44: =+C44*9% | E44: =+D44 | F44: 0
A45: 3317 | B45: THE P&T CHARGES FOR LC/BG | D45: =+C45*9% | E45: =+D45 | F45: 0
A46: 3318 | B46: OBC POSTAGE CHARGES | D46: =+C46*9% | E46: =+D46 | F46: =IF(D46>0," ",C46*18%)
A47: 3320 | B47: RENT ON LOCKER | D47: =+C47*9% | E47: =+D47 | F47: =IF(D47>0," ",C47*18%)
A48: 3321 | B48: ADHOC LIMIT CHARGES | D48: =+C48*9% | E48: =+D48 | F48: =IF(D48>0," ",C48*18%)
A49: 3322 | B49: INCOME FROM SALE OF OLD NEWS PAPERS | D49: =+C49*9% | E49: =+D49
A50: 3324 | B50: PENALTY ON OVERDUE LOCKER RENT | D50: =+C50*9% | E50: =+D50 | F50: =IF(D50>0," ",C50*18%)
A51: 3325 | B51: MICR CHARGES | D51: =+C51*2.5% | E51: =+D51 | F51: =IF(D51>0," ",C51*18%)
A52: 3391 | B52: SMS CHARGES INCOME RECEIVED | D52: =+C52*9% | E52: =+D52 | F52: =IF(D52>0," ",C52*18%)
A53: 3359 | B53: COMMITMENT CHARGES | D53: =+C53*9% | E53: =+D53
A54: 3380 | B54: STATMENT CHARGES | D54: =+C54*9% | E54: =+D54 | F54: =IF(D54>0," ",C54*18%)
A55: 3825 | B55: EXTERNAL AUDIT FEES
A56: 3362 | B56: FORECLOSURE CHARGES
A57: 3340 | B57: LOAN PROCESSING FEES | D57: =+C57*9% | E57: =+D57
A58: GL
A59: 1720 | B59: COMM. RECD. BUT NOT ACCRUED | D59: =+C59*9% | E59: =+D59 | F59: 0
A60: 1836 | B60: RENT ON LOCKER RECEIVED BUT | D60: =+C60*9% | E60: =+D60 | F60: =IF(D60>0," ",C60*18%)
B61: NOT ACCRUED
B62: SALE OF ASSET ( CASH COUNTING MACHINE) | D62: =+C62*9% | E62: =+D62
B63: TOTAL : | C63: =SUM(C9:C62) | D63: =SUM(D9:D62) | E63: =SUM(E9:E62) | F63: =SUM(F9:F62) | G63: =SUM(G9:G62) | H63: =SUM(H9:H62)
A64: RCM | G64: .
A65: PL 3750 | B65: LAW CHARGES (EXCLUSIVE) | C65: 0 | D65: =+C65*9% | E65: =+D65 | F65: =IF(D65>0," ",C65*18%)
A66: PL 3751 | B66: INCIDENTAL LAW CHARGES (EXCLUSIVE) | C66: 0 | D66: =+C66*9% | E66: =+D66 | F66: =IF(D66>0," ",C66*18%) | G66: =+C63*0.09
A67: SUMMARY
A68: (1) INCOME
A69: PARTICULARS | D69: GGST | E69: CGST | F69: IGST
A71: (1) INCOME AS PER LEDGERWISE CALCULATION | D71: =+D63 | E71: =+E63 | F71: =+F63
A72: (2) REFUND GIVEN BUT GST REFUND NOT GIVEN | C72: =+G63 | D72: =+C72*0.09 | E72: =+C72*0.09 | F72: 0
D73: =+D71+D72 | E73: =+E71+E72 | F73: 0
A74: (3) PAYABLE AS PER LEDGER | D74: 4599.89 | E74: =+D74 | F74: 0
A75: DIFFERENCE | D75: =+D73-D74 | E75: =+E73-E74 | F75: =IF(F71>F74,F71,F74) | G75: =+D75/9%
A77: (2) INPUT TAX CREDIT
A78: PARTICULARS | D78: GL 8546 GGST | E78: GL 8547 CGST | F78: GL 8548 IGST
A81: CURRENT MONTH INPUT TAX CREDIT AVAILABLE | D81: 3174.75 | E81: =+D81 | F81: 0 | G81: =+D81/2 | H81: =+E81/2 | I81: =+F81/2
A82: LESS : CREDIT CANNOT BE UTILISED (BCUZ GST NO NOT AVAILABLE IN BILL) | D82: =+C91 | E82: =+D82 | F82: 0 | G82: =+D82/2 | H82: =+E82/2 | I82: =+F82/2
A83: ELIGIBLE CREDIT | D83: =+D81-D82 | E83: =+E81-E82 | F83: =+F81-F82 | G83: =+D83/2 | H83: =+E83/2 | I83: =+F83/2
B87: OUR GST NO. NOT REFLECTED ON CENVAT BILLS
B88: PARTY NAME | C88: CGST | D88: SGST
B89: ROHAN AGENCY | C89: 0 | D89: =+C89
B90: ROHAN AGENCY | C90: 0 | D90: =+C90
C91: =+SUM(C89:C90) | D91: =+SUM(D89:D90)

Sheet ISANPUR
A1: NUTAN NAGARIK SAHAKARI BANK LTD (GUJARAT BRANCHES & HEAD OFFICE)
A3: BRANCH NAME : ISANPUR BRANCH
A4: BRANCH CODE: 13
A5: =+'NEW SHARDA'!A5:F5
A7: CODE NO. | B7: PARTICULARS | D7: GGST | E7: CGST | F7: IGST | I7: LOCKER CLOSED CREDIT
A8: PL
A9: 3303 | B9: PENAL INEREST ON CASH CREDIT | D9: =+C9*9% | E9: =+D9 | F9: =IF(D9>0," ",C9*18%)
A10: 3200 | B10: COMMISION ON BILLS | D10: =+C10*9% | E10: =+D10 | F10: =IF(D10>0," ",C10*18%) | O10: d | P10: 580 | R10: =+P10
A11: 3215 | B11: COMMISION ON PAYORDER | D11: =+C11*9% | E11: =+D11 | F11: =IF(D11>0," ",C11*18%) | O11: d | P11: 146 | R11: =+P11
A12: 3220 | B12: COMMISION ON U.B.D. | D12: =+C12*9% | E12: =+D12 | F12: =IF(D12>0," ",C12*18%) | O12: d | P12: 91700 | R12: =+P12
A13: 3225 | B13: COMMISION I.B.C. | D13: =+C13*9% | E13: =+D13 | F13: =IF(D13>0," ",C13*18%) | O13: d | P13: 2040 | R13: =+P13
A14: 3230 | B14: COMMISION ON GUARANTEE | D14: =+C14*9% | E14: =+D14 | F14: 0 | O14: d | P14: 330 | R14: =+P14
A15: 3235 | B15: COMMISION ON DEMAND DRAFT | D15: =+C15*9% | E15: =+D15 | F15: =IF(D15>0," ",C15*18%) | O15: d | P15: 1250 | R15: =+P15
A16: 3240 | B16: COMMISION ON U.B.C. | D16: =+C16*9% | E16: =+D16 | F16: =IF(D16>0," ",C16*18%) | O16: d | P16: 2973.9 | R16: =+P16
A17: 3245 | B17: COMMISION ON L.C. | D17: =+C17*9% | E17: =+D17 | F17: =IF(D17>0," ",C17*18%) | O17: d | P17: 7834.15 | R17: =+P17
A18: 3250 | B18: COMMISSION ON GUARANTEE | D18: =+C18*9% | E18: =+D18 | F18: =IF(D18>0," ",C18*18%) | O18: d | P18: 6850 | R18: =+P18
A19: 3270 | B19: PROCESSING CHARGE | D19: =+C19*9% | E19: =+D19 | F19: 0 | O19: d | P19: 3900 | R19: =+P19
A20: 3271 | B20: RENEWAL FEES | D20: =+C20*9% | E20: =+D20 | O20: d | P20: 36518.56 | R20: =+P20
A21: 3274 | B21: INCOME FROM E-STAMPING | O21: d | P21: 7410 | R21: =+P21
A22: 3276 | B22: COMMISION ON PAN | D22: =+C22*9% | E22: =+D22 | F22: =IF(D22>0," ",C22*18%) | O22: d | P22: 3986 | R22: =+P22
A23: 3280 | B23: INSURANCE PREMIUM | D23: =+C23*9% | E23: =+D23 | F23: =IF(D23>0," ",C23*18%) | O23: d | P23: 8698 | Q23: 6393 | R23: =+P23-Q26
A24: 3281 | B24: ATM CHARGES | D24: =+C24*9% | E24: =+D24 | O24: d | P24: 25305 | R24: =+P24
A25: 3285 | B25: COMMISION ON RTGS | D25: =+C25*9% | E25: =+D25 | F25: =IF(D25>0," ",C25*18%) | P25: 366 | R25: =+P25
A26: 3286 | B26: COMMISION ON PMJJBY LIC | D26: =+C26*9% | E26: =+D26 | F26: =IF(D26>0," ",C26*18%) | P26: 57300 | Q26: 8698 | R26: =+P26-Q23
A27: 3287 | B27: COMM. ON PMSBY NEW INDIA ASSURANCE | D27: =+C27*9% | E27: =+D27 | F27: =IF(D27>0," ",C27*18%) | P27: =SUM(P10:P26) | Q27: =SUM(Q23:Q26) | R27: =SUM(R10:R26)
A28: 3291 | B28: CIBIL CHARGES | D28: =+C28*9% | E28: =+D28 | F28: =IF(D28>0," ",C28*18%) | R28: =R27*9%
A29: 3296 | B29: RTGS/NEFT MANUAL CHARGES | D29: =+C29*9% | E29: =+D29 | F29: =IF(D29>0," ",C29*18%)
A30: 3297 | B30: ASBA FORM PRINT CHARGES | D30: =+C30*9% | E30: =+D30 | F30: =IF(D30>0," ",C30*18%)
A31: 3298 | B31: MANDATE HANDLING CHARGES | D31: =+C31*9% | E31: =+D31 | F31: =IF(D31>0," ",C31*18%)
A32: 3299 | B32: SI EXECUTION FAILED CHARGES | D32: =+C32*9% | E32: =+D32 | F32: =IF(D32>0," ",C32*18%)
A33: 3300 | B33: INCIDENTAL CHARGES | D33: =+C33*9% | E33: =+D33 | F33: 0
A34: 3301 | B34: INOPERATIVE CHARGES | D34: =+C34*9% | E34: =+D34 | F34: =IF(D34>0," ",C34*18%)
A35: 3302 | B35: PO CANCEL CHARGES | D35: =+C35*9% | E35: =+D35 | F35: =IF(D35>0," ",C35*18%)
A36: 3305 | B36: A/C SHARE TRANSFER FEES | D36: =+C36*9% | E36: =+D36 | F36: =IF(D36>0," ",C36*18%)
A37: 3309 | B37: MIS. INCOME WITH GST | D37: =+C37*9% | E37: =+D37 | F37: =IF(D37>0," ",C37*18%)
A38: 3310 | B38: MIS. INCOME | D38: =+C38*9% | E38: =+D38 | F38: =IF(D38>0," ",C38*18%)
A39: 3311 | B39: I/W CHQ. RET. CHARGES | D39: =+C39*9% | E39: =+D39 | F39: =IF(D39>0," ",C39*18%)
A40: 3312 | B40: O/W CHQ. RET. CHARGES | D40: =+C40*9% | E40: =+D40 | F40: =IF(D40>0," ",C40*18%)
A41: 3313 | B41: ECS RETD. CHARGES | D41: =+C41*9% | E41: =+D41 | F41: =IF(D41>0," ",C41*18%)
A42: 3314 | B42: CHQ. BOOK ISSUE CHARGES | D42: =+C42*9% | E42: =+D42 | F42: =IF(D42>0," ",C42*18%)
A43: 3315 | B43: CHARGES ON GODOWNS | D43: =+C43*9% | E43: =+D43 | F43: 0
A44: 3316 | B44: CASH CHARGES | D44: =+C44*9% | E44: =+D44 | F44: =IF(D44>0," ",C44*18%)
A45: 3317 | B45: THE P&T CHARGES FOR LC/BG | D45: =+C45*9% | E45: =+D45 | F45: =IF(D45>0," ",C45*18%)
A46: 3318 | B46: OBC POSTAGE CHARGES | D46: =+C46*9% | E46: =+D46 | F46: =IF(D46>0," ",C46*18%)
A47: 3320 | B47: RENT ON LOCKER | D47: =+C47*9% | E47: =+D47 | F47: 0
A48: 3321 | B48: ADHOC LIMIT CHARGES | D48: =+C48*9% | E48: =+D48 | F48: =IF(D48>0," ",C48*18%)
A49: 3322 | B49: INCOME FROM SALE OF OLD NEWS PAPERS | D49: =+C49*5% | E49: =+D49
A50: 3324 | B50: PENALTY ON OVERDUE LOCKER RENT | D50: =+C50*9% | E50: =+D50
A51: 3325 | B51: MICR CHARGES | D51: =+C51*2.5% | E51: =+D51 | F51: =IF(D51>0," ",C51*18%)
A52: 3391 | B52: SMS CHARGES INCOME RECEIVED | D52: =+C52*9% | E52: =+D52 | F52: =IF(D52>0," ",C52*18%)
A53: 3359 | B53: COMMITMENT CHARGES | D53: =+C53*9% | E53: =+D53 | F53: 0
A54: 3825 | B54: EXTERNAL AUDIT FEES | D54: =+C54*9% | E54: =+D54 | F54: =IF(D54>0," ",C54*18%)
A55: 3362 | B55: FORECLOSURE CHARGES
A56: 3340 | B56: LOAN PROCESSING FEES | D56: =+C56*9% | E56: =+D56 | F56: =IF(D56>0," ",C56*18%)
A57: GL
A58: 1720 | B58: COMM. RECD. BUT NOT ACCRUED | D58: =+C58*9% | E58: =+D58 | F58: 0
A59: 1836 | B59: RENT ON LOCKER RECEIVED BUT | D59: =+C59*9% | E59: =+D59 | F59: =IF(D59>0," ",C59*18%)
B60: NOT ACCRUED | D60: =+C60*9% | E60: =+D60
B61: SALE OF ASSET ( CASH COUNTING MACHINE) | D61: =+C61*9% | E61: =+D61
B62: TOTAL : | C62: =+SUM(C9:C61) | D62: =+SUM(D9:D61) | E62: =+SUM(E9:E61) | F62: =SUM(F9:F59) | G62: =SUM(G9:G60) | H62: =SUM(H9:H59)
A63: RCM
A64: PL 3750 | B64: LAW CHARGES (EXCLUSIVE) | C64: 0 | D64: =+C64*9% | E64: =+D64 | F64: =IF(D64>0," ",C64*18%)
A65: PL 3751 | B65: INCIDENTAL LAW CHARGES (EXCLUSIVE) | C65: 0 | D65: =+C65*9% | E65: =+D65 | F65: =IF(D65>0," ",C65*18%) | G65: =+C62*0.09
A66: SUMMARY
A68: (1) INCOME
A69: PARTICULARS | D69: GGST | E69: CGST | F69: IGST
A71: (1) INCOME AS PER LEDGERWISE CALCULATION | D71: =+D62 | E71: =+E62 | F71: =+F62
A72: (2) REFUND GIVEN BUT GST REFUND NOT GIVEN | C72: =+G62 | D72: =+C72*0.09 | E72: =+C72*0.09 | F72: 0
D73: =+D71+D72 | E73: =+E71+E72 | F73: 0
A74: (3) PAYABLE AS PER LEDGER | E74: =+D74 | F74: 0
A75: DIFFERENCE | D75: =+D73-D74 | E75: =+E73-E74 | F75: =IF(F71>F74,F71,F74) | G75: =+D75/0.09
A77: (2) INPUT TAX CREDIT
A78: PARTICULARS | D78: GL 8546 GGST | E78: GL 8547 CGST | F78: GL 8548 IGST
A81: CURRENT MONTH INPUT TAX CREDIT AVAILABLE | E81: =+D81 | F81: 0 | G81: =+D81/2 | H81: =+E81/2 | I81: =+F81/2
A82: LESS : CREDIT CANNOT BE UTILISED (BCUZ GST NO NOT AVAILABLE IN BILL) | D82: =+C92 | E82: =+D82 | F82: 0 | G82: =+D82/2 | H82: =+E82/2 | I82: =+F82/2
A83: ELIGIBLE CREDIT | D83: =+D81-D82 | E83: =+E81-E82 | F83: =+F81-F82 | G83: =+D83/2 | H83: =+E83/2 | I83: =+F83/2
B86: OUR GST NO. NOT REFLECTED ON CENVAT BILLS
B87: PARTY NAME | C87: GGST | D87: CGST
B88: BSNL | C88: 0 | D88: =C88
B89: BSNL | C89: 0 | D89: =+C89
B90: ROHAN AGENCY | D90: =C90
B91: BSNL | D91: =+C91
B92: Total | C92: =+SUM(C88:C91) | D92: =+SUM(D88:D91) | G92: =+C92/2

Sheet MANINAGAR
A1: NUTAN NAGARIK SAHAKARI BANK LTD (GUJARAT BRANCHES & HEAD OFFICE)
A3: BRANCH NAME : MANINAGAR BRANCH
A4: BRANCH CODE: 19
A5: =+ISANPUR!A5
A7: CODE NO. | B7: PARTICULARS | D7: GGST | E7: CGST | F7: IGST | I7: LOCKER CLOSED CREDIT
A8: PL
A9: 3303 | B9: DD CANCEL CHARGES | D9: =+C9*9% | E9: =+D9 | F9: =IF(D9>0," ",C9*18%)
A10: 3200 | B10: COMMISION ON BILLS | D10: =+C10*9% | E10: =+D10 | F10: =IF(D10>0," ",C10*18%)
A11: 3215 | B11: COMMISION ON PAYORDER | D11: =+C11*9% | E11: =+D11 | F11: =IF(D11>0," ",C11*18%)
A12: 3220 | B12: COMMISION ON U.B.D. | D12: =+C12*9% | E12: =+D12 | F12: =IF(D12>0," ",C12*18%)
A13: 3225 | B13: COMMISION I.B.C. | D13: =+C13*9% | E13: =+D13 | F13: =IF(D13>0," ",C13*18%)
A14: 3230 | B14: COMMISION ON GUARANTEE | D14: =+C14*9% | E14: =+D14 | F14: =IF(D14>0," ",C14*18%)
A15: 3235 | B15: COMMISION ON DEMAND DRAFT | D15: =+C15*9% | E15: =+D15 | F15: =IF(D15>0," ",C15*18%)
A16: 3240 | B16: COMMISION ON U.B.C. | D16: =+C16*9% | E16: =+D16 | F16: =IF(D16>0," ",C16*18%)
A17: 3245 | B17: COMMISION ON L.C. | D17: =+C17*9% | E17: =+D17 | F17: =IF(D17>0," ",C17*18%)
A18: 3250 | B18: COMMISSION ON GUARANTEE | D18: =+C18*9% | E18: =+D18 | F18: =IF(D18>0," ",C18*18%)
A19: 3270 | B19: PROCESSING CHARGE | D19: =+C19*9% | E19: =+D19 | F19: =IF(D19>0," ",C19*18%)
A20: 3271 | B20: RENEWAL FEES | D20: =+C20*9% | E20: =+D20 | F20: =IF(D20>0," ",C20*18%)
A21: 3274 | B21: INCOME FROM E-STAMPING | D21: =+C21*9% | E21: =+D21 | F21: =IF(D21>0," ",C21*18%)
A22: 3276 | B22: COMMISION ON PAN | D22: =+C22*9% | E22: =+D22 | F22: =IF(D22>0," ",C22*18%)
A23: 3280 | B23: INSURANCE PREMIUM | D23: =+C23*9% | E23: =+D23 | F23: =IF(D23>0," ",C23*18%)
A24: 3281 | B24: ATM CHARGES | D24: =+C24*9% | E24: =+D24 | F24: =IF(D24>0," ",C24*18%)
A25: 3285 | B25: COMMISION ON RTGS | D25: =+C25*9% | E25: =+D25 | F25: =IF(D25>0," ",C25*18%)
A26: 3286 | B26: COMMISION ON PMJJBY LIC | D26: =+C26*9% | E26: =+D26 | F26: =IF(D26>0," ",C26*18%)
A27: 3287 | B27: COMM. ON PMSBY NEW INDIA ASSURANCE | D27: =+C27*9% | E27: =+D27 | F27: =IF(D27>0," ",C27*18%)
A28: 3291 | B28: CIBIL CHARGES | D28: =+C28*9% | E28: =+D28 | F28: =IF(D28>0," ",C28*18%)
A29: 3296 | B29: RTGS/NEFT MANUAL CHARGES | D29: =+C29*9% | E29: =+D29 | F29: =IF(D29>0," ",C29*18%)
A30: 3297 | B30: ASBA FORM PRINT CHARGES | D30: =+C30*9% | E30: =+D30 | F30: =IF(D30>0," ",C30*18%)
A31: 3298 | B31: MANDATE HANDLING CHARGES | D31: =+C31*9% | E31: =+D31 | F31: =IF(D31>0," ",C31*18%)
A32: 3299 | B32: SI EXECUTION FAILED CHARGES | D32: =+C32*9% | E32: =+D32 | F32: =IF(D32>0," ",C32*18%)
A33: 3300 | B33: INCIDENTAL CHARGES | D33: =+C33*9% | E33: =+D33 | F33: =IF(D33>0," ",C33*18%)
A34: 3301 | B34: INOPERATIVE CHARGES | D34: =+C34*9% | E34: =+D34 | F34: =IF(D34>0," ",C34*18%)
A35: 3302 | B35: PO CANCEL CHARGES | D35: =+C35*9% | E35: =+D35 | F35: =IF(D35>0," ",C35*18%)
A36: 3305 | B36: A/C SHARE TRANSFER FEES | D36: =+C36*9% | E36: =+D36 | F36: =IF(D36>0," ",C36*18%)
A37: 3309 | B37: MIS. INCOME WITH GST | D37: =+C37*9% | E37: =+D37 | F37: =IF(D37>0," ",C37*18%)
A38: 3310 | B38: MIS. INCOME | D38: =+C38*9% | E38: =+D38 | F38: =IF(D38>0," ",C38*18%) | J38: =+C39-J39
A39: 3311 | B39: I/W CHQ. RET. CHARGES | D39: =+C39*9% | E39: =+D39 | F39: =IF(D39>0," ",C39*18%) | J39: 7150
A40: 3312 | B40: O/W CHQ. RET. CHARGES | D40: =+C40*9% | E40: =+D40 | F40: =IF(D40>0," ",C40*18%)
A41: 3313 | B41: ECS RETD. CHARGES | D41: =+C41*9% | E41: =+D41 | F41: =IF(D41>0," ",C41*18%)
A42: 3314 | B42: CHQ. BOOK ISSUE CHARGES | D42: =+C42*9% | E42: =+D42 | F42: =IF(D42>0," ",C42*18%)
A43: 3315 | B43: CHARGES ON GODOWNS | D43: =+C43*9% | E43: =+D43 | F43: =IF(D43>0," ",C43*18%)
A44: 3316 | B44: CASH CHARGES | D44: =+C44*9% | E44: =+D44 | F44: =IF(D44>0," ",C44*18%)
A45: 3317 | B45: THE P&T CHARGES FOR LC/BG | D45: =+C45*9% | E45: =+D45 | F45: =IF(D45>0," ",C45*18%)
A46: 3318 | B46: OBC POSTAGE CHARGES | D46: =+C46*9% | E46: =+D46 | F46: =IF(D46>0," ",C46*18%)
A47: 3320 | B47: RENT ON LOCKER | D47: =+C47*9% | E47: =+D47 | F47: 0
A48: 3321 | B48: ADHOC LIMIT CHARGES | D48: =+C48*9% | E48: =+D48 | F48: =IF(D48>0," ",C48*18%)
A49: 3322 | B49: INCOME FROM SALE OF OLD NEWS PAPERS | D49: =+C49*2.5% | E49: =+D49
A50: 3324 | B50: PENALTY ON OVERDUE LOCKER RENT | D50: =C50*9% | E50: =+D50 | F50: 0
A51: 3325 | B51: MICR CHARGES | D51: =+C51*2.5% | E51: =+D51 | F51: =IF(D51>0," ",C51*18%)
A52: 3391 | B52: SMS CHARGES INCOME RECEIVED | D52: =+C52*9% | E52: =+D52 | F52: =IF(D52>0," ",C52*18%)
A53: 3359 | B53: COMMITMENT CHARGES | D53: =+C53*9% | E53: =+D53
A54: 3825 | B54: EXTERNAL AUDIT FEES | D54: =+C54*9% | E54: =+D54
A55: 3362 | B55: FORECLOSURE CHARGES
A56: 3340 | B56: LOAN PROCESSING FEES | D56: =+C56*9% | E56: =+D56 | F56: =IF(D56>0," ",C56*18%)
A57: GL
A58: 1720 | B58: COMM. RECD. BUT NOT ACCRUED | D58: =+C58*9% | E58: =+D58 | F58: =IF(D58>0," ",C58*18%)
A59: 1836 | B59: RENT ON LOCKER RECEIVED BUT | D59: =+C59*9% | E59: =+D59 | F59: =IF(D59>0," ",C59*18%)
B60: NOT ACCRUED
B61: SALE OF ASSET ( CASH COUNTING MACHINE)
B62: TOTAL : | C62: =SUM(C9:C61) | D62: =SUM(D9:D61) | E62: =SUM(E9:E61) | F62: =SUM(F9:F61) | G62: =+SUM(G9:G61) | H62: =SUM(H9:H59)
A63: RCM
A64: PL 3750 | B64: LAW CHARGES (EXCLUSIVE) | D64: =+C64*9% | E64: =+D64 | F64: =IF(D64>0," ",C64*18%)
A65: PL 3751 | B65: INCIDENTAL LAW CHARGES (EXCLUSIVE) | C65: 0 | D65: =+C65*9% | E65: =+D65 | F65: =IF(D65>0," ",C65*18%) | G65: =+C62*0.09
A66: SUMMARY
A68: (1) INCOME
A69: PARTICULARS | D69: GGST | E69: CGST | F69: IGST
A71: (1) INCOME AS PER LEDGERWISE CALCULATION | D71: =+D62 | E71: =+E62 | F71: =+F62
A72: (2) REFUND GIVEN BUT GST REFUND NOT GIVEN | C72: =G62 | D72: =+C72*0.09 | E72: =+C72*0.09 | F72: 0
D73: =+D71+D72 | E73: =+E71+E72 | F73: 0
A74: (3) PAYABLE AS PER LEDGER | D74: 37918.81 | E74: =+D74 | F74: 0
A75: DIFFERENCE | D75: =+D73-D74 | E75: =+E73-E74 | F75: =IF(F71>F74,F71,F74) | G75: =-D75/9*100 | H75: =+G75*9%
A77: (2) INPUT TAX CREDIT
A78: PARTICULARS | D78: GL 8546 GGST | E78: GL 8547 CGST | F78: GL 8548 IGST
A81: CURRENT MONTH INPUT TAX CREDIT AVAILABLE | D81: 5841 | E81: =+D81 | F81: 0 | G81: =+D81/2 | H81: =+E81/2 | I81: =+F81/2
A82: LESS : CREDIT CANNOT BE UTILISED (BCUZ GST NO NOT AVAILABLE IN BILL) | D82: =+C91 | E82: =+D91 | F82: =+E91 | G82: =+D82/2 | H82: =+E82/2 | I82: =+F82/2
A83: ELIGIBLE CREDIT | D83: =+D81-D82 | E83: =+E81-E82 | F83: =+F81-F82 | G83: =+D83/2 | H83: =+E83/2 | I83: =+F83/2
B86: INELIBILBLE CREDIT
B87: PARTY NAME | C87: SGST | D87: CGST | E87: IGST
B88: BSNL | C88: 0 | D88: =+C88
B89: ROHAN AGENCY | C89: 0 | D89: =+C89
B91: TOTAL | C91: =SUM(C88:C90) | D91: =SUM(D88:D90) | E91: =SUM(E90:E90)
A94: Note-1: The difference of Rs. 2128.50/- which is shown the GL 1878 & 1879. There is 50% SETOFF 08/26 TRF EXP on 29/09/2026.

Sheet SHANTI COMM
A1: NUTAN NAGARIK SAHAKARI BANK LTD (GUJARAT BRANCHES & HEAD OFFICE)
A3: BRANCH NAME : SHANTI COMMERCIAL BRANCH
A4: BRANCH CODE: 04
A5: =+MANINAGAR!A5
A7: CODE NO. | B7: PARTICULARS | D7: GGST | E7: CGST | F7: IGST | I7: LOCKER CLOSED CREDIT
A8: PL
A9: 3303 | B9: DD CANCEL CHARGES | D9: =+C9*9% | E9: =+D9 | F9: =IF(D9>0," ",C9*18%)
A10: 3200 | B10: COMMISION ON BILLS | D10: =+C10*9% | E10: =+D10 | F10: =IF(D10>0," ",C10*18%)
A11: 3215 | B11: COMMISION ON PAYORDER | D11: =+C11*9% | E11: =+D11 | F11: =IF(D11>0," ",C11*18%)
A12: 3220 | B12: COMMISION ON U.B.D. | D12: =+C12*9% | E12: =+D12 | F12: =IF(D12>0," ",C12*18%)
A13: 3225 | B13: COMMISION I.B.C. | D13: =+C13*9% | E13: =+D13 | F13: =IF(D13>0," ",C13*18%)
A14: 3230 | B14: COMMISION ON GUARANTEE | D14: =+C14*9% | E14: =+D14 | F14: 0
A15: 3235 | B15: COMMISION ON DEMAND DRAFT | D15: =+C15*9% | E15: =+D15 | F15: =IF(D15>0," ",C15*18%)
A16: 3240 | B16: COMMISION ON U.B.C. | D16: =+C16*9% | E16: =+D16 | F16: =IF(D16>0," ",C16*18%)
A17: 3245 | B17: COMMISION ON L.C. | D17: =+C17*9% | E17: =+D17 | F17: =IF(D17>0," ",C17*18%)
A18: 3250 | B18: COMMISSION ON GUARANTEE | D18: =+C18*9% | E18: =+D18 | F18: =IF(D18>0," ",C18*18%)
A19: 3270 | B19: PROCESSING CHARGE | D19: =+C19*9% | E19: =+D19 | F19: =IF(D19>0," ",C19*18%)
A20: 3271 | B20: RENEWAL FEES | D20: =+C20*9% | E20: =+D20 | F20: =IF(D20>0," ",C20*18%)
A21: 3274 | B21: INCOME FROM E-STAMPING | D21: =+C21*9% | E21: =+D21 | F21: =IF(D21>0," ",C21*18%)
A22: 3276 | B22: COMMISION ON PAN | D22: =+C22*9% | E22: =+D22 | F22: =IF(D22>0," ",C22*18%)
A23: 3280 | B23: INSURANCE PREMIUM | D23: =+C23*9% | E23: =+D23 | F23: =IF(D23>0," ",C23*18%)
A24: 3281 | B24: ATM CHARGES | D24: =+C24*9% | E24: =+D24 | F24: 0
A25: 3285 | B25: COMMISION ON RTGS | D25: =+C25*9% | E25: =+D25 | F25: =IF(D25>0," ",C25*18%)
A26: 3286 | B26: COMMISION ON PMJJBY LIC | D26: =+C26*9% | E26: =+D26 | F26: =IF(D26>0," ",C26*18%)
A27: 3287 | B27: COMM. ON PMSBY NEW INDIA ASSURANCE | D27: =+C27*9% | E27: =+D27 | F27: =IF(D27>0," ",C27*18%)
A28: 3291 | B28: CIBIL CHARGES | D28: =+C28*9% | E28: =+D28 | F28: =IF(D28>0," ",C28*18%)
A29: 3296 | B29: RTGS/NEFT MANUAL CHARGES | D29: =+C29*9% | E29: =+D29 | F29: =IF(D29>0," ",C29*18%)
A30: 3297 | B30: ASBA FORM PRINT CHARGES | D30: =+C30*9% | E30: =+D30 | F30: =IF(D30>0," ",C30*18%)
A31: 3298 | B31: MANDATE HANDLING CHARGES | D31: =+C31*9% | E31: =+D31 | F31: =IF(D31>0," ",C31*18%)
A32: 3299 | B32: SI EXECUTION FAILED CHARGES | D32: =+C32*9% | E32: =+D32 | F32: =IF(D32>0," ",C32*18%)
A33: 3300 | B33: INCIDENTAL CHARGES | D33: =+C33*9% | E33: =+D33 | F33: 0
A34: 3301 | B34: INOPERATIVE CHARGES | D34: =+C34*9% | E34: =+D34 | F34: =IF(D34>0," ",C34*18%)
A35: 3302 | B35: PO CANCEL CHARGES | D35: =+C35*9% | E35: =+D35 | F35: =IF(D35>0," ",C35*18%)
A36: 3305 | B36: A/C SHARE TRANSFER FEES | D36: =+C36*9% | E36: =+D36 | F36: =IF(D36>0," ",C36*18%)
A37: 3309 | B37: MIS. INCOME WITH GST | D37: =+C37*9% | E37: =+D37 | F37: =IF(D37>0," ",C37*18%)
A38: 3310 | B38: MIS. INCOME | D38: =+C38*9% | E38: =+D38 | F38: =IF(D38>0," ",C38*18%)
A39: 3311 | B39: I/W CHQ. RET. CHARGES | D39: =+C39*9% | E39: =+D39 | F39: =IF(D39>0," ",C39*18%)
A40: 3312 | B40: O/W CHQ. RET. CHARGES | D40: =+C40*9% | E40: =+D40 | F40: =IF(D40>0," ",C40*18%)
A41: 3313 | B41: ECS RETD. CHARGES | D41: =+C41*9% | E41: =+D41 | F41: =IF(D41>0," ",C41*18%)
A42: 3314 | B42: CHQ. BOOK ISSUE CHARGES | D42: =+C42*9% | E42: =+D42 | F42: =IF(D42>0," ",C42*18%)
A43: 3315 | B43: CHARGES ON GODOWNS | D43: =+C43*9% | E43: =+D43 | F43: =IF(D43>0," ",C43*18%)
A44: 3316 | B44: CASH CHARGES | D44: =+C44*9% | E44: =+D44 | F44: =IF(D44>0," ",C44*18%)
A45: 3317 | B45: THE P&T CHARGES FOR LC/BG | D45: =+C45*9% | E45: =+D45 | F45: =IF(D45>0," ",C45*18%)
A46: 3318 | B46: OBC POSTAGE CHARGES | D46: =+C46*9% | E46: =+D46 | F46: =IF(D46>0," ",C46*18%)
A47: 3320 | B47: RENT ON LOCKER | D47: =+C47*9% | E47: =+D47 | F47: =IF(D47>0," ",C47*18%)
A48: 3321 | B48: ADHOC LIMIT CHARGES | D48: =+C48*9% | E48: =+D48 | F48: =IF(D48>0," ",C48*18%)
A49: 3322 | B49: INCOME FROM SALE OF OLD NEWS PAPERS | D49: =+C49*5% | E49: =+D49
A50: 3324 | B50: PENALTY ON OVERDUE LOCKER RENT | D50: =+C50*5% | E50: =+D50
A51: 3325 | B51: MICR CHARGES | D51: =+C51*2.5% | E51: =+D51 | F51: =IF(D51>0," ",C51*18%)
A52: 3391 | B52: SMS CHARGES INCOME RECEIVED | D52: =+C52*9% | E52: =+D52 | F52: =IF(D52>0," ",C52*18%)
A53: 3359 | B53: COMMITMENT CHARGES | D53: =+C53*9% | E53: =+D53
A54: 3825 | B54: EXTERNAL AUDIT FEES
A55: 3362 | B55: FORECLOSURE CHARGES
A56: 3340 | B56: LOAN PROCESSING FEES | D56: =+C56*9% | E56: =+D56 | F56: =IF(D56>0," ",C56*18%)
A57: GL
A58: 1720 | B58: COMM. RECD. BUT NOT ACCRUED | D58: =+C58*9% | E58: =+D58 | F58: 0
A59: 1836 | B59: RENT ON LOCKER RECEIVED BUT | D59: =+C59*9% | E59: =+D59 | F59: =IF(D59>0," ",C59*18%)
B60: NOT ACCRUED
B61: SALE OF ASSET (CASH COUNTING MACHINE) | D61: =+C61*0.09 | E61: =+D61
B62: TOTAL : | C62: =SUM(C9:C61) | D62: =SUM(D9:D61) | E62: =SUM(E9:E61) | F62: =SUM(F9:F61) | G62: =+SUM(G9:G60) | H62: =+SUM(H9:H60) | I62: =+SUM(I9:I60)
A63: RCM
A64: PL 3750 | B64: LAW CHARGES (EXCLUSIVE) | C64: 0 | D64: =+C64*9% | E64: =+D64 | F64: =IF(D64>0," ",C64*18%)
A65: PL 3751 | B65: INCIDENTAL LAW CHARGES (EXCLUSIVE) | C65: 0 | D65: =+C65*9% | E65: =+D65 | F65: =IF(D65>0," ",C65*18%) | G65: =+C62*0.09
A66: SUMMARY
A68: (1) INCOME
A69: PARTICULARS | D69: GGST | E69: CGST | F69: IGST
A71: (1) INCOME AS PER LEDGERWISE CALCULATION | D71: =+D62 | E71: =+E62 | F71: =+F62
A72: (2) REFUND GIVEN BUT GST REFUND NOT GIVEN | C72: =+G62 | D72: =+C72*0.09 | E72: =+C72*0.09 | F72: 0
D73: =+D71+D72 | E73: =+E71+E72 | F73: =+F71+F72
A74: (3) PAYABLE AS PER LEDGER | E74: =+D74 | F74: 0
A75: DIFFERENCE | D75: =+D73-D74 | E75: =+E73-E74 | F75: =+F73-F74 | G75: =+D75/9*100
A77: (2) INPUT TAX CREDIT
A78: PARTICULARS | D78: GL 8546 GGST | E78: GL 8547 CGST | F78: GL 8548 IGST
A81: CURRENT MONTH INPUT TAX CREDIT AVAILABLE | E81: =+D81 | F81: 0 | G81: =+D81/2 | H81: =+E81/2 | I81: =+F81/2
A82: LESS : CREDIT CANNOT BE UTILISED (BCUZ GST NO NOT AVAILABLE IN BILL) | D82: =+C91 | E82: =+D82 | F82: 0 | G82: =+D82/2 | H82: =+E82/2 | I82: =+F82/2
A83: ELIGIBLE CREDIT | D83: =+D81-D82 | E83: =+E81-E82 | F83: =+F81-F82 | G83: =+D83/2 | H83: =+E83/2 | I83: =+F83/2
B86: PARTY NAME | C86: GGST | D86: CGST | E86: IGST
B87: BSNL | C87: 0 | D87: =+C87 | E87: 0
B88: ROHAN AGENCY | C88: 0 | D88: =+C88
B89: BSNL | D89: =+C89 | E89: 0
B90: BSNL | D90: =+C90 | E90: 0
B91: TOTAL | C91: =+SUM(C87:C90) | D91: =+SUM(D87:D90) | E91: =+SUM(E87:E90)

Sheet MASKATI
A1: NUTAN NAGARIK SAHAKARI BANK LTD (GUJARAT BRANCHES & HEAD OFFICE)
A3: BRANCH NAME :MASKATI BRANCH
A4: BRANCH CODE:2
A5: =+'SHANTI COMM'!A5:F5
A7: CODE NO. | B7: PARTICULARS | D7: GGST | E7: CGST | F7: IGST | I7: LOCKER CLOSED CREDIT
A8: PL
A9: 3303 | B9: DD CANCEL CHARGES | D9: =+C9*9% | E9: =+D9 | F9: =IF(D9>0," ",C9*18%)
A10: 3200 | B10: COMMISION ON BILLS | D10: =+C10*9% | E10: =+D10 | F10: =IF(D10>0," ",C10*18%)
A11: 3215 | B11: COMMISION ON PAYORDER | D11: =+C11*9% | E11: =+D11 | F11: =IF(D11>0," ",C11*18%)
A12: 3220 | B12: COMMISION ON U.B.D. | D12: =+C12*9% | E12: =+D12 | F12: =IF(D12>0," ",C12*18%)
A13: 3225 | B13: COMMISION I.B.C. | D13: =+C13*9% | E13: =+D13 | F13: =IF(D13>0," ",C13*18%)
A14: 3230 | B14: COMMISION ON GUARANTEE | D14: =+C14*9% | E14: =+D14 | F14: 0
A15: 3235 | B15: COMMISION ON DEMAND DRAFT | D15: =+C15*9% | E15: =+D15 | F15: =IF(D15>0," ",C15*18%)
A16: 3240 | B16: COMMISION ON U.B.C. | D16: =+C16*9% | E16: =+D16 | F16: =IF(D16>0," ",C16*18%)
A17: 3245 | B17: COMMISION ON L.C. | D17: =+C17*9% | E17: =+D17 | F17: =IF(D17>0," ",C17*18%)
A18: 3250 | B18: COMMISSION ON GUARANTEE | D18: =+C18*9% | E18: =+D18 | F18: =IF(D18>0," ",C18*18%)
A19: 3270 | B19: PROCESSING CHARGE | D19: =+C19*9% | E19: =+D19 | F19: 0
A20: 3271 | B20: RENEWAL FEES | D20: =+C20*9% | E20: =+D20 | F20: 0
A21: 3274 | B21: INCOME FROM E-STAMPING
A22: 3276 | B22: COMMISION ON PAN | D22: =+C22*9% | E22: =+D22 | F22: =IF(D22>0," ",C22*18%)
A23: 3280 | B23: INSURANCE PREMIUM | D23: =+C23*9% | E23: =+D23 | F23: =IF(D23>0," ",C23*18%) | N23: 26113
A24: 3281 | B24: ATM CHARGES | D24: =+C24*9% | E24: =+D24 | F24: =IF(D24>0," ",C24*18%)
A25: 3285 | B25: COMMISION ON RTGS | D25: =+C25*9% | E25: =+D25 | F25: 0
A26: 3286 | B26: COMMISION ON PMJJBY LIC | D26: =+C26*9% | E26: =+D26 | F26: =IF(D26>0," ",C26*18%)
A27: 3287 | B27: COMM. ON PMSBY NEW INDIA ASSURANCE | D27: =+C27*9% | E27: =+D27 | F27: =IF(D27>0," ",C27*18%)
A28: 3291 | B28: CIBIL CHARGES | D28: =+C28*9% | E28: =+D28 | F28: =IF(D28>0," ",C28*18%)
A29: 3296 | B29: RTGS/NEFT MANUAL CHARGES | D29: =+C29*9% | E29: =+D29 | F29: =IF(D29>0," ",C29*18%)
A30: 3297 | B30: ASBA FORM PRINT CHARGES | D30: =+C30*9% | E30: =+D30 | F30: =IF(D30>0," ",C30*18%)
A31: 3298 | B31: MANDATE HANDLING CHARGES | D31: =+C31*9% | E31: =+D31 | F31: =IF(D31>0," ",C31*18%)
A32: 3299 | B32: SI EXECUTION FAILED CHARGES | D32: =+C32*9% | E32: =+D32 | F32: =IF(D32>0," ",C32*18%)
A33: 3300 | B33: INCIDENTAL CHARGES | D33: =+C33*9% | E33: =+D33 | F33: 0
A34: 3301 | B34: INOPERATIVE CHARGES | D34: =+C34*9% | E34: =+D34 | F34: =IF(D34>0," ",C34*18%)
A35: 3302 | B35: PO CANCEL CHRAGES | D35: =+C35*9% | E35: =+D35 | F35: =IF(D35>0," ",C35*18%)
A36: 3305 | B36: A/C SHARE TRANSFER FEES | D36: =+C36*9% | E36: =+D36 | F36: =IF(D36>0," ",C36*18%)
A37: 3309 | B37: MIS. INCOME WITH GST | D37: =+C37*9% | E37: =+D37 | F37: =IF(D37>0," ",C37*18%)
A38: 3310 | B38: MIS. INCOME | D38: =+C38*9% | E38: =+D38 | F38: =IF(D38>0," ",C38*18%)
A39: 3311 | B39: I/W CHQ. RET. CHARGES | D39: =+C39*9% | E39: =+D39 | F39: =IF(D39>0," ",C39*18%)
A40: 3312 | B40: O/W CHQ. RET. CHARGES | D40: =+C40*9% | E40: =+D40 | F40: =IF(D40>0," ",C40*18%)
A41: 3313 | B41: ECS RETD. CHARGES | D41: =+C41*9% | E41: =+D41 | F41: =IF(D41>0," ",C41*18%)
A42: 3314 | B42: CHQ. BOOK ISSUE CHARGES | D42: =+C42*9% | E42: =+D42 | F42: =IF(D42>0," ",C42*18%)
A43: 3315 | B43: CHARGES ON GODOWNS | D43: =+C43*9% | E43: =+D43 | F43: =IF(D43>0," ",C43*18%)
A44: 3316 | B44: CASH CHARGES | D44: =+C44*9% | E44: =+D44 | F44: =IF(D44>0," ",C44*18%)
A45: 3317 | B45: THE P&T CHARGES FOR LC/BG | D45: =+C45*9% | E45: =+D45 | F45: =IF(D45>0," ",C45*18%)
A46: 3318 | B46: OBC POSTAGE CHARGES | D46: =+C46*9% | E46: =+D46 | F46: =IF(D46>0," ",C46*18%)
A47: 3320 | B47: RENT ON LOCKER | D47: =+C47*9% | E47: =+D47 | F47: =IF(D47>0," ",C47*18%)
A48: 3321 | B48: ADHOC LIMIT CHARGES | D48: =+C48*9% | E48: =+D48 | F48: =IF(D48>0," ",C48*18%)
A49: 3322 | B49: INCOME FROM SALE OF OLD NEWS PAPERS | D49: =+C49*5% | E49: =+D49
A50: 3324 | B50: PENALTY ON OVERDUE LOCKER RENT | D50: =+C50*5% | E50: =+D50
A51: 3325 | B51: MICR CHARGES | D51: =+C51*2.5% | E51: =+D51 | F51: =IF(D51>0," ",C51*18%)
A52: 3391 | B52: SMS CHARGES INCOME RECEIVED | D52: =+C52*9% | E52: =+D52 | F52: =IF(D52>0," ",C52*18%)
A53: 3359 | B53: COMMITMENT CHARGES | D53: =+C53*9% | E53: =+D53
A54: 3825 | B54: EXTERNAL AUDIT FEES | D54: =+C54*9% | E54: =+D54
A55: 3362 | B55: FORECLOSURE CHARGES
A56: 3340 | B56: LOAN PROCESSING FEES | D56: =+C56*9% | E56: =+D56 | F56: =IF(D56>0," ",C56*18%)
A57: GL
A58: 1720 | B58: COMM. RECD. BUT NOT ACCRUED | D58: =+C58*9% | E58: =+D58 | F58: 0
A59: 1836 | B59: RENT ON LOCKER RECEIVED BUT | D59: =+C59*9% | E59: =+D59 | F59: =IF(D59>0," ",C59*18%)
B60: NOT ACCRUED
B61: SALE OF ASSET ( Air Conditioner) | D61: =+C61*9% | E61: =+D61
B62: TOTAL : | C62: =SUM(C9:C61) | D62: =SUM(D9:D61) | E62: =SUM(E9:E61) | F62: =SUM(F9:F61) | G62: =SUM(G9:G59) | H62: =SUM(H9:H59)
A63: RCM
A64: PL 3750 | B64: LAW CHARGES (EXCLUSIVE) | C64: 0 | D64: =+C64*9% | E64: =+D64 | F64: =IF(D64>0," ",C64*18%)
A65: PL 3751 | B65: INCIDENTAL LAW CHARGES (EXCLUSIVE) | C65: 0 | D65: =+C65*9% | E65: =+D65 | F65: =IF(D65>0," ",C65*18%)
A66: SUMMARY
A68: (1) INCOME
A69: PARTICULARS | D69: GGST | E69: CGST | F69: IGST
A71: (1) INCOME AS PER LEDGERWISE CALCULATION | D71: =+D62 | E71: =+E62 | F71: =+F62
A72: (2) REFUND GIVEN BUT GST REFUND NOT GIVEN | C72: =G62 | D72: =+C72*0.09 | E72: =+C72*0.09 | F72: 0
D73: =+D71+D72 | E73: =+E71+E72 | F73: 0
A74: (3) PAYABLE AS PER LEDGER | D74: 52486.98 | E74: =+D74 | F74: 0
A75: DIFFERENCE | D75: =+D73-D74 | E75: =+E73-E74 | F75: =IF(F71>F74,F71,F74) | G75: =+D75/9*100
A77: (2) INPUT TAX CREDIT
A78: PARTICULARS | D78: GL 8546 GGST | E78: GL 8547 CGST | F78: GL 8548 IGST
A81: CURRENT MONTH INPUT TAX CREDIT AVAILABLE | D81: 1753.22 | E81: =D81 | F81: 15093.54 | G81: =+D81/2 | H81: =+E81/2 | I81: =+F81/2
A82: LESS : CREDIT CANNOT BE UTILISED (BCUZ GST NO NOT AVAILABLE IN BILL) | D82: =+C99 | E82: =+D82 | F82: =+E99 | G82: =+D82/2 | H82: =+E82/2 | I82: =+F82/2
A83: ELIGIBLE CREDIT | D83: =+D81-D82 | E83: =+E81-E82 | F83: =SUM(F81:F82) | G83: =+G81-G82 | H83: =+H81-H82 | I83: =+I81-I82
B85: INELLIGEBLE CREDIT
B86: PARTY NAME | C86: CGST | D86: SGST | E86: IGST
B87: ROHAN AGENCY | C87: 0 | D87: =+C87
B88: ROHAN AGENCY | C88: 0 | D88: =+C88
B89: JET LIFTS PVT. LTD. | C89: 0 | D89: =+C89
B90: INSTANT MARKETING INC. | C90: 0 | D90: =+C90
B91: INSTANT MARKETING INC. | C91: 0 | D91: =+C91
B92: BSNL | D92: =+C92
B93: BSNL | D93: =+C93
B94: BSNL | C94: 0 | D94: =+C94
B95: BSNL | C95: 0 | D95: =+C95
B96: BSNL | C96: 0 | D96: =+C96
B97: INTEL AIR TECHNOLOGIES | C97: 0 | D97: =+C97
B99: TOTAL | C99: =SUM(C87:C98) | D99: =SUM(D87:D98) | E99: 0

Sheet VEJALPUR
A1: NUTAN NAGARIK SAHAKARI BANK LTD (GUJARAT BRANCHES & HEAD OFFICE)
A3: BRANCH NAME : VEJALPUR BRANCH
A4: BRANCH CODE: 17
A5: =+MASKATI!A5
A7: CODE NO. | B7: PARTICULARS | D7: GGST | E7: CGST | F7: IGST | I7: LOCKER CLOSED CREDIT
A8: PL
A9: 3303 | B9: DD CANCEL CHARGES | D9: =+C9*9% | E9: =+D9 | F9: =IF(D9>0," ",C9*18%)
A10: 3200 | B10: COMMISION ON BILLS | D10: =+C10*9% | E10: =+D10 | F10: =IF(D10>0," ",C10*18%)
A11: 3215 | B11: COMMISION ON PAYORDER | D11: =+C11*9% | E11: =+D11 | F11: =IF(D11>0," ",C11*18%)
A12: 3220 | B12: COMMISION ON U.B.D. | D12: =+C12*9% | E12: =+D12 | F12: =IF(D12>0," ",C12*18%)
A13: 3225 | B13: COMMISION I.B.C. | D13: =+C13*9% | E13: =+D13 | F13: =IF(D13>0," ",C13*18%)
A14: 3230 | B14: COMMISION ON GUARANTEE | D14: =+C14*9% | E14: =+D14 | F14: =IF(D14>0," ",C14*18%)
A15: 3235 | B15: COMMISION ON DEMAND DRAFT | D15: =+C15*9% | E15: =+D15 | F15: =IF(D15>0," ",C15*18%)
A16: 3240 | B16: COMMISION ON U.B.C. | D16: =+C16*9% | E16: =+D16 | F16: =IF(D16>0," ",C16*18%)
A17: 3245 | B17: COMMISION ON L.C. | D17: =+C17*9% | E17: =+D17 | F17: =IF(D17>0," ",C17*18%)
A18: 3250 | B18: COMMISSION ON GUARANTEE | D18: =+C18*9% | E18: =+D18 | F18: =IF(D18>0," ",C18*18%)
A19: 3270 | B19: PROCESSING CHARGE | D19: =+C19*9% | E19: =+D19
A20: 3271 | B20: RENEWAL FEES | D20: =+C20*9% | E20: =+D20
A21: 3274 | B21: INCOME FROM E-STAMPING
A22: 3276 | B22: COMMISION ON PAN | D22: =+C22*9% | E22: =+D22
A23: 3280 | B23: INSURANCE PREMIUM | D23: =+C23*9% | E23: =+D23 | F23: =IF(D23>0," ",C23*18%)
A24: 3281 | B24: ATM CHARGES | D24: =+C24*9% | E24: =+D24 | F24: =IF(D24>0," ",C24*18%)
A25: 3285 | B25: COMMISION ON RTGS | D25: =+C25*9% | E25: =+D25 | F25: =IF(D25>0," ",C25*18%)
A26: 3286 | B26: COMMISION ON PMJJBY LIC | D26: =+C26*9% | E26: =+D26 | F26: =IF(D26>0," ",C26*18%)
A27: 3287 | B27: COMM. ON PMSBY NEW INDIA ASSURANCE | D27: =+C27*9% | E27: =+D27 | F27: =IF(D27>0," ",C27*18%)
A28: 3291 | B28: CIBIL CHARGES | D28: =+C28*9% | E28: =+D28 | F28: =IF(D28>0," ",C28*18%)
A29: 3296 | B29: RTGS/NEFT MANUAL CHARGES | D29: =+C29*9% | E29: =+D29 | F29: =IF(D29>0," ",C29*18%)
A30: 3297 | B30: ASBA FORM PRINT CHARGES | D30: =+C30*9% | E30: =+D30 | F30: =IF(D30>0," ",C30*18%)
A31: 3298 | B31: MANDATE HANDLING CHARGES | D31: =+C31*9% | E31: =+D31 | F31: =IF(D31>0," ",C31*18%)
A32: 3299 | B32: SI EXECUTION FAILED CHARGES | D32: =+C32*9% | E32: =+D32 | F32: =IF(D32>0," ",C32*18%)
A33: 3300 | B33: INCIDENTAL CHARGES | D33: =+C33*9% | E33: =+D33 | F33: =IF(D33>0," ",C33*18%)
A34: 3301 | B34: INOPERATIVE CHARGES | D34: =+C34*9% | E34: =+D34 | F34: =IF(D34>0," ",C34*18%)
A35: 3302 | B35: PO CANCEL CHRAGES | D35: =+C35*9% | E35: =+D35 | F35: =IF(D35>0," ",C35*18%)
A36: 3305 | B36: A/C SHARE TRANSFER FEES | D36: =+C36*9% | E36: =+D36 | F36: =IF(D36>0," ",C36*18%)
A37: 3309 | B37: MIS. INCOME WITH GST | D37: =+C37*9% | E37: =+D37 | F37: =IF(D37>0," ",C37*18%)
A38: 3310 | B38: MIS. INCOME | D38: =+C38*9% | E38: =+D38 | F38: =IF(D38>0," ",C38*18%)
A39: 3311 | B39: I/W CHQ. RET. CHARGES | D39: =+C39*9% | E39: =+D39 | F39: =IF(D39>0," ",C39*18%)
A40: 3312 | B40: O/W CHQ. RET. CHARGES | D40: =+C40*9% | E40: =+D40 | F40: =IF(D40>0," ",C40*18%)
A41: 3313 | B41: ECS RETD. CHARGES | D41: =+C41*9% | E41: =+D41 | F41: =IF(D41>0," ",C41*18%)
A42: 3314 | B42: CHQ. BOOK ISSUE CHARGES | D42: =+C42*9% | E42: =+D42 | F42: =IF(D42>0," ",C42*18%)
A43: 3315 | B43: CHARGES ON GODOWNS | D43: =+C43*9% | E43: =+D43 | F43: =IF(D43>0," ",C43*18%)
A44: 3316 | B44: CASH CHARGES | D44: =+C44*9% | E44: =+D44 | F44: =IF(D44>0," ",C44*18%)
A45: 3317 | B45: THE P&T CHARGES FOR LC/BG | D45: =+C45*9% | E45: =+D45 | F45: =IF(D45>0," ",C45*18%)
A46: 3318 | B46: OBC POSTAGE CHARGES | D46: =+C46*9% | E46: =+D46 | F46: =IF(D46>0," ",C46*18%)
A47: 3320 | B47: RENT ON LOCKER | D47: =+C47*9% | E47: =+D47
A48: 3321 | B48: ADHOC LIMIT CHARGES | D48: =+C48*9% | E48: =+D48 | F48: =IF(D48>0," ",C48*18%)
A49: 3322 | B49: INCOME FROM SALE OF OLD NEWS PAPERS | D49: =+C49*2.5% | E49: =+D49
A50: 3324 | B50: PENALTY ON OVERDUE LOCKER RENT | D50: =+C50*9% | E50: =+D50
A51: 3325 | B51: MICR CHARGES | D51: =+C51*2.5% | E51: =+D51 | F51: =IF(D51>0," ",C51*18%)
A52: 3391 | B52: SMS CHARGES INCOME RECEIVED | D52: =+C52*9% | E52: =+D52
A53: 3359 | B53: COMMITMENT CHARGES | D53: =+C53*9% | E53: =+D53
A54: 3825 | B54: EXTERNAL AUDIT FEES | D54: =+C54*9% | E54: =+D54
A55: 3362 | B55: FORECLOSURE CHARGES
A56: 3340 | B56: LOAN PROCESSING FEES | D56: =+C56*9% | E56: =+D56 | F56: =IF(D56>0," ",C56*18%)
A57: GL
A58: 1720 | B58: COMM. RECD. BUT NOT ACCRUED | D58: =+C58*9% | E58: =+D58 | F58: =IF(D58>0," ",C58*18%)
A59: 1836 | B59: RENT ON LOCKER RECEIVED BUT | D59: =+C59*9% | E59: =+D59 | F59: =IF(D59>0," ",C59*18%)
B60: NOT ACCRUED
B61: SALE OF ASSET ( CASH COUNTING MACHINE) | D61: =+C61*9% | E61: =+D61
B62: TOTAL : | C62: =+SUM(C9:C61) | D62: =+SUM(D9:D61) | E62: =+SUM(E9:E61) | F62: =+SUM(F9:F61) | G62: =+SUM(G9:G61) | H62: =SUM(H9:H59)
A63: RCM
A64: PL 3750 | B64: LAW CHARGES (EXCLUSIVE) | C64: 0 | D64: =+C64*9% | E64: =+D64 | F64: 0 | G64: =+C62*18% | H64: =+D62+E62 | I64: =+G64-H64
A65: PL 3751 | B65: INCIDENTAL LAW CHARGES (EXCLUSIVE) | C65: 0 | D65: =+C65*9% | E65: =+D65 | F65: =IF(D65>0," ",C65*18%) | G65: =+C62*0.09
A66: SUMMARY
A68: (1) INCOME
A69: PARTICULARS | D69: GGST | E69: CGST | F69: IGST
A71: (1) INCOME AS PER LEDGERWISE CALCULATION | D71: =+D62 | E71: =+E62 | F71: =+F62
A72: (2) REFUND GIVEN BUT GST REFUND NOT GIVEN | C72: =G62 | D72: =+C72*0.09 | E72: =+C72*0.09 | F72: 0
D73: =+D71+D72 | E73: =+E71+E72 | F73: 0 | G73: =+C62+C72+H62 | H73: =+G73*0.18
A74: (3) PAYABLE AS PER LEDGER | E74: =+D74 | F74: 0
A75: DIFFERENCE | D75: =+D73-D74 | E75: =+E73-E74 | F75: =IF(F71>F74,F71,F74) | G75: =+D75/9% | H75: 0
A77: (2) INPUT TAX CREDIT
A78: PARTICULARS | D78: GL 8546 GGST | E78: GL 8547 CGST | F78: GL 8548 IGST
A81: CURRENT MONTH INPUT TAX CREDIT AVAILABLE | E81: =+D81 | F81: 0 | G81: =+D81/2 | H81: =+E81/2 | I81: =+F81/2
A82: LESS : CREDIT CANNOT BE UTILISED (BCUZ GST NO NOT AVAILABLE IN BILL) | D82: =+C92 | E82: =+D82 | F82: 0 | G82: =+D82/2 | H82: =+E82/2 | I82: =+F82/2
A83: ELIGIBLE CREDIT | D83: =+D81-D82 | E83: =+E81-E82 | F83: =+F81-F82 | G83: =+D83/2 | H83: =+E83/2 | I83: =+F83/2
B86: OUR GST NO. NOT REFLECTED ON CENVAT BILLS
B87: PARTY | C87: CGST | D87: SGST | E87: IGST
B88: BSNL | C88: 0 | D88: =+C88 | E88: 0
B89: PRIME DINE | C89: 0 | D89: =+C89
B90: ROHAN AGENCY | C90: 0 | D90: =+C90
B91: BSNL | C91: 0 | D91: =+C91 | E91: 0
C92: =+SUM(C88:C91) | D92: =+SUM(D88:D91) | E92: =+SUM(E88:E88) | G92: =+C92/2

Sheet JODHPUR-SATELLITE
A1: NUTAN NAGARIK SAHAKARI BANK LTD (GUJARAT BRANCHES & HEAD OFFICE)
A3: BRANCH NAME : JODHPUR BRANCH
A4: BRANCH CODE: 11
A5: =+VEJALPUR!A5
A7: CODE NO. | B7: PARTICULARS | D7: GGST | E7: CGST | F7: IGST | I7: LCOKER CLOSED CREDIT
A8: PL
A9: 3303 | B9: DD CANCEL CHARGES | D9: =+C9*9% | E9: =+D9 | F9: =IF(D9>0," ",C9*18%)
A10: 3200 | B10: COMMISION ON BILLS | D10: =+C10*9% | E10: =+D10 | F10: =IF(D10>0," ",C10*18%)
A11: 3215 | B11: COMMISION ON PAYORDER | D11: =+C11*9% | E11: =+D11 | F11: =IF(D11>0," ",C11*18%)
A12: 3220 | B12: COMMISION ON U.B.D. | D12: =+C12*9% | E12: =+D12 | F12: =IF(D12>0," ",C12*18%)
A13: 3225 | B13: COMMISION I.B.C. | D13: =+C13*9% | E13: =+D13 | F13: =IF(D13>0," ",C13*18%)
A14: 3230 | B14: COMMISION ON GUARANTEE | D14: =+C14*9% | E14: =+D14 | F14: =IF(D14>0," ",C14*18%)
A15: 3235 | B15: COMMISION ON DEMAND DRAFT | D15: =+C15*9% | E15: =+D15 | F15: =IF(D15>0," ",C15*18%)
A16: 3240 | B16: COMMISION ON U.B.C. | D16: =+C16*9% | E16: =+D16 | F16: =IF(D16>0," ",C16*18%)
A17: 3245 | B17: COMMISION ON L.C. | D17: =+C17*9% | E17: =+D17 | F17: =IF(D17>0," ",C17*18%)
A18: 3250 | B18: COMMISSION ON GUARANTEE | D18: =+C18*9% | E18: =+D18 | F18: =IF(D18>0," ",C18*18%)
A19: 3270 | B19: PROCESSING CHARGE | D19: =+C19*9% | E19: =+D19 | F19: =IF(D19>0," ",C19*18%)
A20: 3271 | B20: RENEWAL FEES | D20: =+C20*9% | E20: =+D20 | F20: =IF(D20>0," ",C20*18%)
A21: 3274 | B21: INCOME FROM E-STAMPING
A22: 3276 | B22: COMMISION ON PAN | D22: =+C22*9% | E22: =+D22 | F22: =IF(D22>0," ",C22*18%)
A23: 3280 | B23: INSURANCE PREMIUM | D23: =+C23*9% | E23: =+D23 | F23: =IF(D23>0," ",C23*18%)
A24: 3281 | B24: ATM CHARGES | D24: =+C24*9% | E24: =+D24 | F24: =IF(D24>0," ",C24*18%)
A25: 3285 | B25: COMMISION ON RTGS | D25: =+C25*9% | E25: =+D25 | F25: =IF(D25>0," ",C25*18%)
A26: 3286 | B26: COMMISION ON PMJJBY LIC | D26: =+C26*9% | E26: =+D26 | F26: =IF(D26>0," ",C26*18%)
A27: 3287 | B27: COMM. ON PMSBY NEW INDIA ASSURANCE | D27: =+C27*9% | E27: =+D27 | F27: =IF(D27>0," ",C27*18%)
A28: 3291 | B28: CIBIL CHARGES | D28: =+C28*9% | E28: =+D28 | F28: =IF(D28>0," ",C28*18%)
A29: 3296 | B29: RTGS/NEFT MANUAL CHARGES | D29: =+C29*9% | E29: =+D29 | F29: =IF(D29>0," ",C29*18%)
A30: 3297 | B30: ASBA FORM PRINT CHARGES | D30: =+C30*9% | E30: =+D30 | F30: =IF(D30>0," ",C30*18%)
A31: 3298 | B31: MANDATE HANDLING CHARGES | D31: =+C31*9% | E31: =+D31 | F31: =IF(D31>0," ",C31*18%)
A32: 3299 | B32: SI EXECUTION FAILED CHARGES | D32: =+C32*9% | E32: =+D32 | F32: =IF(D32>0," ",C32*18%)
A33: 3300 | B33: INCIDENTAL CHARGES | D33: =+C33*9% | E33: =+D33 | F33: 0
A34: 3301 | B34: INOPERATIVE CHARGES | D34: =+C34*9% | E34: =+D34 | F34: =IF(D34>0," ",C34*18%)
A35: 3302 | B35: PO CANCEL CHRAGES | D35: =+C35*9% | E35: =+D35 | F35: =IF(D35>0," ",C35*18%)
A36: 3305 | B36: A/C SHARE TRANSFER FEES | D36: =+C36*9% | E36: =+D36 | F36: =IF(D36>0," ",C36*18%)
A37: 3309 | B37: MIS. INCOME WITH GST | D37: =+C37*9% | E37: =+D37 | F37: =IF(D37>0," ",C37*18%)
A38: 3310 | B38: MIS. INCOME | D38: =+C38*9% | E38: =+D38 | F38: =IF(D38>0," ",C38*18%)
A39: 3311 | B39: I/W CHQ. RET. CHARGES | D39: =+C39*9% | E39: =+D39 | F39: =IF(D39>0," ",C39*18%)
A40: 3312 | B40: O/W CHQ. RET. CHARGES | D40: =+C40*9% | E40: =+D40 | F40: =IF(D40>0," ",C40*18%)
A41: 3313 | B41: ECS RETD. CHARGES | D41: =+C41*9% | E41: =+D41 | F41: =IF(D41>0," ",C41*18%)
A42: 3314 | B42: CHQ. BOOK ISSUE CHARGES | D42: =+C42*9% | E42: =+D42 | F42: =IF(D42>0," ",C42*18%)
A43: 3315 | B43: CHARGES ON GODOWNS | D43: =+C43*9% | E43: =+D43 | F43: =IF(D43>0," ",C43*18%)
A44: 3316 | B44: CASH CHARGES | D44: =+C44*9% | E44: =+D44 | F44: =IF(D44>0," ",C44*18%)
A45: 3317 | B45: THE P&T CHARGES FOR LC/BG | D45: =+C45*9% | E45: =+D45 | F45: =IF(D45>0," ",C45*18%)
A46: 3318 | B46: OBC POSTAGE CHARGES | D46: =+C46*9% | E46: =+D46 | F46: =IF(D46>0," ",C46*18%)
A47: 3320 | B47: RENT ON LOCKER | D47: =+C47*9% | E47: =+D47 | F47: 0
A48: 3321 | B48: ADHOC LIMIT CHARGES | D48: =+C48*9% | E48: =+D48 | F48: =IF(D48>0," ",C48*18%)
A49: 3322 | B49: INCOME FROM SALE OF OLD NEWS PAPERS | D49: =+C49*5% | E49: =+D49
A50: 3324 | B50: PENALTY ON OVERDUE LOCKER RENT | D50: =+C50*9% | E50: =+D50
A51: 3325 | B51: MICR CHARGES | D51: =+C51*2.5% | E51: =+D51 | F51: =IF(D51>0," ",C51*18%)
A52: 3391 | B52: SMS CHARGES INCOME RECEIVED | D52: =+C52*9% | E52: =+D52 | F52: =IF(D52>0," ",C52*18%)
A53: 3359 | B53: COMMITMENT CHARGES | D53: =+C53*9% | E53: =+D53
A54: 3825 | B54: EXTERNAL AUDIT FEES | D54: =+C54*9% | E54: =+D54
A55: 3362 | B55: FORECLOSURE CHARGES
A56: 3340 | B56: LOAN PROCESSING FEES | D56: =+C56*9% | E56: =+D56 | F56: =IF(D56>0," ",C56*18%)
A57: GL
A58: 1720 | B58: COMM. RECD. BUT NOT ACCRUED | D58: =+C58*9% | E58: =+D58 | F58: 0
A59: 1836 | B59: RENT ON LOCKER RECEIVED BUT | D59: =+C59*9% | E59: =+D59 | F59: 0
B60: NOT ACCRUED | D60: =+C60*9% | E60: =+D60
B61: SALE OF ASSET ( CASH COUNTING MACHINE) | D61: =+C61*0.09 | E61: =+D61
B62: TOTAL : | C62: =SUM(C9:C61) | D62: =SUM(D9:D61) | E62: =SUM(E9:E61) | F62: =SUM(F9:F61) | G62: =SUM(G9:G59) | H62: =SUM(H9:H59)
A63: RCM
A64: PL 3750 | B64: LAW CHARGES (EXCLUSIVE) | D64: =+C64*9% | E64: =+D64 | F64: =IF(D64>0," ",C64*18%)
A65: PL 3751 | B65: INCIDENTAL LAW CHARGES (EXCLUSIVE) | C65: 0 | D65: =+C65*9% | E65: =+D65 | F65: =IF(D65>0," ",C65*18%) | G65: =+D62/C62
A66: SUMMARY
A68: (1) INCOME
A69: PARTICULARS | D69: GGST | E69: CGST | F69: IGST | H69: =337.5+192.42+815.4+121.14+57.69+133.38+145.35 | I69: =+H69/9%
A71: (1) INCOME AS PER LEDGERWISE CALCULATION | D71: =+D62 | E71: =+E62 | F71: =+F62 | H71: =16.2/9%
A72: (2) REFUND GIVEN BUT GST REFUND NOT GIVEN | C72: =+G62 | D72: =+C72*0.09 | E72: =+C72*0.09 | F72: 0 | H72: =13.5/9% | O72: =+M72-N72
D73: =+D71+D72 | E73: =+E71+E72 | F73: 0
A74: (3) PAYABLE AS PER LEDGER | E74: =+D74 | F74: 0
A75: DIFFERENCE | D75: =+D73-D74 | E75: =+E73-E74 | F75: =IF(F71>F74,F71,F74) | G75: =D75/9%
A77: (2) INPUT TAX CREDIT
A78: PARTICULARS | D78: GL 8546 GGST | E78: GL 8547 CGST | F78: GL 8548 IGST
A81: CURRENT MONTH INPUT TAX CREDIT AVAILABLE | E81: =+D81 | F81: 0 | G81: =+E81/2 | H81: =+E81/2 | I81: =+F81/2
A82: LESS : CREDIT CANNOT BE UTILISED (BCUZ GST NO NOT AVAILABLE IN BILL) | D82: =+C92 | E82: =+D82 | F82: 0 | G82: =+D82/2 | H82: =+E82/2 | I82: =+F82/2
A83: ELIGIBLE CREDIT | D83: =+D81-D82 | E83: =+E81-E82 | F83: =+F81-F82 | G83: =+E83/2 | H83: =+E83/2 | I83: =+F83/2
B87: INELLIGBLE CREDIT
B88: PARTY NAME | C88: GGST | D88: CGST | E88: IGST
B89: BSNL | C89: 0 | D89: =+C89 | E89: 0
B90: ROHAN AGENCY | C90: 0 | D90: =+C90
B91: BSNL | C91: 0 | D91: =+C91
B92: TOTAL | C92: =+SUM(C89:C91) | D92: =+SUM(D89:D91) | E92: =SUM(E89:E89)

Sheet PANJRAPOLE
A1: NUTAN NAGARIK SAHAKARI BANK LTD (GUJARAT BRANCHES & HEAD OFFICE)
A3: BRANCH NAME : PANJRAPOLE BRANCH
A4: BRANCH CODE:10
A5: =+'JODHPUR-SATELLITE'!A5
A7: CODE NO. | B7: PARTICULARS | D7: GGST | E7: CGST | F7: IGST | I7: LOCKER CLOSED
A8: PL
A9: 3303 | B9: DD CANCEL CHARGES | D9: =+C9*9% | E9: =+D9 | F9: =IF(D9>0," ",C9*18%) | I9: 0
A10: 3200 | B10: COMMISION ON BILLS | D10: =+C10*9% | E10: =+D10 | F10: =IF(D10>0," ",C10*18%) | I10: 0
A11: 3215 | B11: COMMISION ON PAYORDER | D11: =+C11*9% | E11: =+D11 | F11: =IF(D11>0," ",C11*18%) | I11: 0
A12: 3220 | B12: COMMISION ON U.B.D. | D12: =+C12*9% | E12: =+D12 | F12: =IF(D12>0," ",C12*18%) | I12: 0
A13: 3225 | B13: COMMISION I.B.C. | D13: =+C13*9% | E13: =+D13 | F13: =IF(D13>0," ",C13*18%) | I13: 0
A14: 3230 | B14: COMMISION ON GUARANTEE | D14: =+C14*9% | E14: =+D14 | F14: 0 | I14: 0
A15: 3235 | B15: COMMISION ON DEMAND DRAFT | D15: =+C15*9% | E15: =+D15 | F15: =IF(D15>0," ",C15*18%) | I15: 0
A16: 3240 | B16: COMMISION ON U.B.C. | D16: =+C16*9% | E16: =+D16 | F16: =IF(D16>0," ",C16*18%) | I16: 0
A17: 3245 | B17: COMMISION ON L.C. | D17: =+C17*9% | E17: =+D17 | F17: =IF(D17>0," ",C17*18%) | I17: 0
A18: 3250 | B18: COMMISSION ON GUARANTEE | D18: =+C18*9% | E18: =+D18 | F18: =IF(D18>0," ",C18*18%) | I18: 0
A19: 3270 | B19: PROCESSING CHARGE | D19: =+C19*9% | E19: =+D19 | F19: =IF(D19>0," ",C19*18%) | I19: 0
A20: 3271 | B20: RENEWAL FEES | D20: =+C20*9% | E20: =+D20 | F20: =IF(D20>0," ",C20*18%) | I20: 0
A21: 3274 | B21: INCOME FROM E-STAMPING | I21: 0
A22: 3276 | B22: COMMISION ON PAN | D22: =+C22*9% | E22: =+D22 | F22: 0 | I22: 0
A23: 3280 | B23: INSURANCE PREMIUM | D23: =+C23*9% | E23: =+D23 | F23: =IF(D23>0," ",C23*18%) | I23: 0
A24: 3281 | B24: ATM CHARGES | D24: =+C24*9% | E24: =+D24 | I24: 0
A25: 3285 | B25: COMMISION ON RTGS | D25: =+C25*9% | E25: =+D25 | F25: =IF(D25>0," ",C25*18%) | I25: 0
A26: 3286 | B26: COMMISION ON PMJJBY LIC | D26: =+C26*9% | E26: =+D26 | F26: =IF(D26>0," ",C26*18%) | I26: 0
A27: 3287 | B27: COMM. ON PMSBY NEW INDIA ASSURANCE | D27: =+C27*9% | E27: =+D27 | F27: =IF(D27>0," ",C27*18%) | I27: 0
A28: 3291 | B28: CIBIL CHARGES | D28: =+C28*9% | E28: =+D28 | F28: =IF(D28>0," ",C28*18%) | I28: 0
A29: 3296 | B29: RTGS/NEFT MANUAL CHARGES | D29: =+C29*9% | E29: =+D29 | F29: =IF(D29>0," ",C29*18%) | I29: 0
A30: 3297 | B30: ASBA FORM PRINT CHARGES | D30: =+C30*9% | E30: =+D30 | F30: =IF(D30>0," ",C30*18%) | I30: 0
A31: 3298 | B31: MANDATE HANDLING CHARGES | D31: =+C31*9% | E31: =+D31 | F31: =IF(D31>0," ",C31*18%) | I31: 0
A32: 3299 | B32: SI EXECUTION FAILED CHARGES | D32: =+C32*9% | E32: =+D32 | F32: =IF(D32>0," ",C32*18%) | I32: 0
A33: 3300 | B33: INCIDENTAL CHARGES | D33: =+C33*9% | E33: =+D33 | F33: 0 | I33: 0
A34: 3301 | B34: INOPERATIVE CHARGES | D34: =+C34*9% | E34: =+D34 | F34: =IF(D34>0," ",C34*18%) | I34: 0
A35: 3302 | B35: PO CANCEL CHARGES | D35: =+C35*9% | E35: =+D35 | F35: =IF(D35>0," ",C35*18%) | I35: 0
A36: 3305 | B36: A/C SHARE TRANSFER FEES | D36: =+C36*9% | E36: =+D36 | F36: =IF(D36>0," ",C36*18%) | I36: 0
A37: 3309 | B37: MIS. INCOME WITH GST | D37: =+C37*9% | E37: =+D37 | F37: =IF(D37>0," ",C37*18%) | I37: 0
A38: 3310 | B38: MIS. INCOME | D38: =+C38*9% | E38: =+D38 | F38: 0 | I38: 0
A39: 3311 | B39: I/W CHQ. RET. CHARGES | D39: =+C39*9% | E39: =+D39 | F39: =IF(D39>0," ",C39*18%) | I39: 0
A40: 3312 | B40: O/W CHQ. RET. CHARGES | D40: =+C40*9% | E40: =+D40 | F40: =IF(D40>0," ",C40*18%) | I40: 0
A41: 3313 | B41: ECS RETD. CHARGES | D41: =+C41*9% | E41: =+D41 | F41: =IF(D41>0," ",C41*18%) | I41: 0
A42: 3314 | B42: CHQ. BOOK ISSUE CHARGES | D42: =+C42*9% | E42: =+D42 | F42: =IF(D42>0," ",C42*18%) | I42: 0
A43: 3315 | B43: CHARGES ON GODOWNS | D43: =+C43*9% | E43: =+D43 | F43: =IF(D43>0," ",C43*18%) | I43: 0
A44: 3316 | B44: CASH CHARGES | D44: =+C44*9% | E44: =+D44 | F44: =IF(D44>0," ",C44*18%) | I44: 0
A45: 3317 | B45: THE P&T CHARGES FOR LC/BG | D45: =+C45*9% | E45: =+D45 | F45: =IF(D45>0," ",C45*18%) | I45: 0
A46: 3318 | B46: OBC POSTAGE CHARGES | D46: =+C46*9% | E46: =+D46 | F46: =IF(D46>0," ",C46*18%) | I46: 0
A47: 3320 | B47: RENT ON LOCKER | D47: =+C47*9% | E47: =+D47 | I47: 0
A48: 3321 | B48: ADHOC LIMIT CHARGES | D48: =+C48*9% | E48: =+D48 | F48: =IF(D48>0," ",C48*18%) | I48: 0
A49: 3322 | B49: INCOME FROM SALE OF OLD NEWS PAPERS | D49: =+C49*2.5% | E49: =+D49 | I49: 0 | J49: =+C50-J50
A50: 3324 | B50: PENALTY ON OVERDUE LOCKER RENT | D50: =+C50*9% | E50: =+D50 | I50: 0 | J50: 10941
A51: 3325 | B51: MICR CHARGES | D51: =+C51*2.5% | E51: =+D51 | F51: =IF(D51>0," ",C51*18%) | I51: 0
A52: 3391 | B52: SMS CHARGES INCOME RECEIVED | D52: =+C52*9% | E52: =+D52 | F52: =IF(D52>0," ",C52*18%) | I52: 0
A53: 3359 | B53: COMMITMENT CHARGES | D53: =+C53*9% | E53: =+D53 | F53: =IF(D53>0," ",C53*18%) | I53: 0
A54: 3825 | B54: EXTERNAL AUDIT FEES | D54: =+C54*9% | E54: =+D54 | F54: =IF(D54>0," ",C54*18%) | I54: 0
A55: 3362 | B55: FORECLOSURE CHARGES | D55: =+C55*9% | E55: =+D55 | I55: 0
A56: 3340 | B56: LOAN PROCESSING FEES | D56: =+C56*9% | E56: =+D56 | F56: =IF(D56>0," ",C56*18%) | I56: 0
A57: GL | D57: =+C57*9% | E57: =+D57 | I57: 0
A58: 1720 | B58: COMM. RECD. BUT NOT ACCRUED | D58: =+C58*9% | E58: =+D58 | F58: 0 | I58: 0
A59: 1836 | B59: RENT ON LOCKER RECEIVED BUT | D59: =+C59*9% | E59: =+D59 | F59: 0 | I59: 0
B60: NOT ACCRUED | I60: 0
B61: SALE OF ASSET ( CASH COUNTING MACHINE) | D61: =+C61*0.09 | E61: =+D61 | I61: 0
B62: TOTAL : | C62: =SUM(C9:C61) | D62: =SUM(D9:D61) | E62: =SUM(E9:E61) | F62: =SUM(F9:F59) | G62: =SUM(G9:G60) | H62: =SUM(H9:H59) | I62: =SUM(I9:I59)
A63: RCM
A64: PL 3750 | B64: LAW CHARGES (EXCLUSIVE) | C64: 0 | D64: =+C64*9% | E64: =+D64
A65: PL 3751 | B65: INCIDENTAL LAW CHARGES (EXCLUSIVE) | C65: 0 | D65: =+C65*9% | E65: =+D65 | F65: =IF(D65>0," ",C65*18%) | G65: =+C62*0.09
A66: SUMMARY | H66: =+C62+G62
H67: =+H66*0.09
A68: (1) INCOME
A69: PARTICULARS | D69: GGST | E69: CGST | F69: IGST
A71: (1) INCOME AS PER LEDGERWISE CALCULATION | D71: =+D62 | E71: =+E62 | F71: =+F62
A72: (2) REFUND GIVEN BUT GST REFUND NOT GIVEN | C72: =+G62 | D72: =+C72*0.09 | E72: =+C72*0.09 | F72: 0
D73: =+D71+D72 | E73: =+E71+E72 | F73: 0
A74: (3) PAYABLE AS PER LEDGER | E74: =+D74 | F74: 0
A75: DIFFERENCE | D75: =+D73-D74 | E75: =+E73-E74 | F75: =IF(F71>F74,F71,F74) | G75: =+E75/9%
A77: (2) INPUT TAX CREDIT
A78: PARTICULARS | D78: GL 8546 GGST | E78: GL 8547 CGST | F78: GL 8548 IGST
A81: CURRENT MONTH INPUT TAX CREDIT AVAILABLE | E81: =+D81 | F81: 0 | G81: =+D81/2 | H81: =+E81/2 | I81: =+F81/2
A82: LESS : CREDIT CANNOT BE UTILISED (BCUZ GST NO NOT AVAILABLE IN BILL) | D82: =+C91 | E82: =+D91 | F82: 0 | G82: =+D82/2 | H82: =+E82/2 | I82: =+F82/2
A83: ELIGIBLE CREDIT | D83: =+D81-D82 | E83: =+E81-E82 | F83: =+F81-F82 | G83: =+D83/2 | H83: =+E83/2 | I83: =+F83/2
B85: OUR GST NO. NOT REFLECTED ON CENVAT BILLS
B86: PARTY NAME | C86: SGST | D86: CGST | E86: IGST
B87: BSNL | D87: =+C87 | E87: 0
B88: BSNL | C88: 0 | D88: =+C88 | E88: 0
B89: BSNL | D89: =+C89 | E89: 0
B90: ROHAN AGENCY | D90: 0 | E90: 0 | G90: =+C91/2 | H90: =+D91/2 | I90: =+E91/2
B91: TOTAL | C91: =+SUM(C87:C90) | D91: =+SUM(D87:D90) | E91: =+SUM(E87:E90)

Sheet ASHRAM ROAD
A1: NUTAN NAGARIK SAHAKARI BANK LTD (GUJARAT BRANCHES & HEAD OFFICE)
A3: BRANCH NAME : ASHRAM ROAD BRANCH
A4: BRANCH CODE: 05
A5: =+PANJRAPOLE!A5
A7: CODE NO. | B7: PARTICULARS | D7: GGST | E7: CGST | F7: IGST | I7: LOCKER CLOSED CREDIT
A8: PL
A9: 3303 | B9: DD CANCEL CHARGES | D9: =+C9*9% | E9: =+D9 | F9: =IF(D9>0," ",C9*18%) | I9: 0
A10: 3200 | B10: COMMISION ON BILLS | D10: =+C10*9% | E10: =+D10 | F10: =IF(D10>0," ",C10*18%) | I10: 0
A11: 3215 | B11: COMMISION ON PAYORDER | D11: =+C11*9% | E11: =+D11 | F11: =IF(D11>0," ",C11*18%) | I11: 0
A12: 3220 | B12: COMMISION ON U.B.D. | D12: =+C12*9% | E12: =+D12 | F12: =IF(D12>0," ",C12*18%) | I12: 0
A13: 3225 | B13: COMMISION I.B.C. | D13: =+C13*9% | E13: =+D13 | F13: =IF(D13>0," ",C13*18%) | I13: 0
A14: 3230 | B14: COMMISION ON GUARANTEE | D14: =+C14*9% | E14: =+D14 | F14: 0 | I14: 0 | K14: 0 | L14: 0 | M14: 0 | N14: 0
A15: 3235 | B15: COMMISION ON DEMAND DRAFT | D15: =+C15*9% | E15: =+D15 | F15: =IF(D15>0," ",C15*18%) | I15: 0
A16: 3240 | B16: COMMISION ON U.B.C. | D16: =+C16*9% | E16: =+D16 | F16: =IF(D16>0," ",C16*18%) | I16: 0
A17: 3245 | B17: COMMISION ON L.C. | D17: =+C17*9% | E17: =+D17 | F17: =IF(D17>0," ",C17*18%) | I17: 0
A18: 3250 | B18: COMMISSION ON GUARANTEE | D18: =+C18*9% | E18: =+D18 | F18: =IF(D18>0," ",C18*18%) | I18: 0
A19: 3270 | B19: PROCESSING CHARGE | D19: =+C19*9% | E19: =+D19 | I19: 0
A20: 3271 | B20: RENEWAL FEES | D20: =+C20*9% | E20: =+D20 | I20: 0
A21: 3274 | B21: INCOME FROM E-STAMPING | I21: 0
A22: 3276 | B22: COMMISION ON PAN | D22: =+C22*9% | E22: =+D22 | F22: =IF(D22>0," ",C22*18%) | I22: 0
A23: 3280 | B23: INSURANCE PREMIUM | D23: =+C23*9% | E23: =+D23 | F23: =IF(D23>0," ",C23*18%) | I23: 0
A24: 3281 | B24: ATM CHARGES | D24: =+C24*9% | E24: =+D24 | I24: 0
A25: 3285 | B25: COMMISION ON RTGS | D25: =+C25*9% | E25: =+D25 | F25: =IF(D25>0," ",C25*18%) | I25: 0
A26: 3286 | B26: COMMISION ON PMJJBY LIC | D26: =+C26*9% | E26: =+D26 | F26: =IF(D26>0," ",C26*18%) | I26: 0
A27: 3287 | B27: COMM. ON PMSBY NEW INDIA ASSURANCE | D27: =+C27*9% | E27: =+D27 | F27: =IF(D27>0," ",C27*18%) | I27: 0
A28: 3291 | B28: CIBIL CHARGES | D28: =+C28*9% | E28: =+D28 | F28: =IF(D28>0," ",C28*18%) | I28: 0
A29: 3296 | B29: RTGS/NEFT MANUAL CHARGES | D29: =+C29*9% | E29: =+D29 | F29: =IF(D29>0," ",C29*18%) | I29: 0
A30: 3297 | B30: ASBA FORM PRINT CHARGES | D30: =+C30*9% | E30: =+D30 | F30: =IF(D30>0," ",C30*18%) | I30: 0
A31: 3298 | B31: MANDATE HANDLING CHARGES | D31: =+C31*9% | E31: =+D31 | F31: =IF(D31>0," ",C31*18%) | I31: 0
A32: 3299 | B32: SI EXECUTION FAILED CHARGES | D32: =+C32*9% | E32: =+D32 | F32: =IF(D32>0," ",C32*18%) | I32: 0
A33: 3300 | B33: INCIDENTAL CHARGES | D33: =+C33*9% | E33: =+D33 | F33: =IF(D33>0," ",C33*18%) | I33: 0
A34: 3301 | B34: INOPERATIVE CHARGES | D34: =+C34*9% | E34: =+D34 | F34: =IF(D34>0," ",C34*18%) | I34: 0
A35: 3302 | B35: PO CANCEL CHARGES | D35: =+C35*9% | E35: =+D35 | F35: =IF(D35>0," ",C35*18%) | I35: 0
A36: 3305 | B36: A/C SHARE TRANSFER FEES | D36: =+C36*9% | E36: =+D36 | F36: =IF(D36>0," ",C36*18%) | I36: 0
A37: 3309 | B37: MIS. INCOME WITH GST | D37: =+C37*9% | E37: =+D37 | F37: =IF(D37>0," ",C37*18%) | I37: 0
A38: 3310 | B38: MIS. INCOME | D38: =+C38*9% | E38: =+D38 | F38: 0 | I38: 0
A39: 3311 | B39: I/W CHQ. RET. CHARGES | D39: =+C39*9% | E39: =+D39 | F39: 0 | I39: 0 | M39: =3884-4463
A40: 3312 | B40: O/W CHQ. RET. CHARGES | D40: =+C40*9% | E40: =+D40 | F40: =IF(D40>0," ",C40*18%) | I40: 0
A41: 3313 | B41: ECS RETD. CHARGES | D41: =+C41*9% | E41: =+D41 | F41: =IF(D41>0," ",C41*18%) | I41: 0
A42: 3314 | B42: CHQ. BOOK ISSUE CHARGES | D42: =+C42*9% | E42: =+D42 | F42: =IF(D42>0," ",C42*18%) | I42: 0
A43: 3315 | B43: CHARGES ON GODOWNS | D43: =+C43*9% | E43: =+D43 | F43: =IF(D43>0," ",C43*18%) | I43: 0
A44: 3316 | B44: CASH CHARGES | D44: =+C44*9% | E44: =+D44 | F44: =IF(D44>0," ",C44*18%) | I44: 0
A45: 3317 | B45: THE P&T CHARGES FOR LC/BG | D45: =+C45*9% | E45: =+D45 | F45: 0 | I45: 0
A46: 3318 | B46: OBC POSTAGE CHARGES | D46: =+C46*9% | E46: =+D46 | F46: =IF(D46>0," ",C46*18%) | I46: 0
A47: 3320 | B47: RENT ON LOCKER | D47: =+C47*9% | E47: =+D47 | F47: =IF(D47>0," ",C47*18%) | I47: 0
A48: 3321 | B48: ADHOC LIMIT CHARGES | D48: =+C48*9% | E48: =+D48 | F48: =IF(D48>0," ",C48*18%) | I48: 0
A49: 3322 | B49: INCOME FROM SALE OF OLD NEWS PAPERS | D49: =+C49*9% | E49: =+D49 | I49: 0
A50: 3324 | B50: PENALTY ON OVERDUE LOCKER RENT | D50: =+C50*9% | E50: =+D50 | I50: 0
A51: 3325 | B51: MICR CHARGES | D51: =+C51*2.5% | E51: =+D51 | F51: =IF(D51>0," ",C51*18%) | I51: 0
A52: 3391 | B52: SMS CHARGES INCOME RECEIVED | D52: =+C52*9% | E52: =+D52 | F52: =IF(D52>0," ",C52*18%) | I52: 0
A53: 3359 | B53: COMMITMENT CHARGES | D53: =+C53*9% | E53: =+D53 | F53: =IF(D53>0," ",C53*18%) | I53: 0
A54: 3825 | B54: EXTERNAL AUDIT FEES | D54: =+C54*9% | E54: =+D54 | F54: =IF(D54>0," ",C54*18%) | I54: 0
A55: 3362 | B55: FORECLOSURE CHARGES | I55: 0
A56: 3340 | B56: LOAN PROCESSING FEES | D56: =+C56*9% | E56: =+D56 | F56: =IF(D56>0," ",C56*18%) | I56: 0
A57: GL | D57: =+C57*9% | E57: =+D57 | I57: 0
A58: 1720 | B58: COMM. RECD. BUT NOT ACCRUED | D58: =+C58*9% | E58: =+D58 | F58: 0 | I58: 0
A59: 1836 | B59: RENT ON LOCKER RECEIVED BUT | D59: =+C59*9% | E59: =+D59 | F59: =IF(D59>0," ",C59*18%) | I59: 0
B60: NOT ACCRUED | I60: 0
B61: SALE OF ASSET ( CASH COUNTING MACHINE) | D61: =+C61*0.09 | E61: =+D61 | I61: 0
B62: TOTAL : | C62: =SUM(C9:C61) | D62: =SUM(D9:D61) | E62: =SUM(E9:E61) | F62: =SUM(F9:F61) | G62: =SUM(G9:G59) | H62: =SUM(H9:H59) | I62: =SUM(I9:I59)
A63: RCM
A64: PL 3750 | B64: LAW CHARGES (EXCLUSIVE) | C64: 0 | D64: =+C64*9% | E64: =+D64 | F64: =IF(D64>0," ",C64*18%)
A65: PL 3751 | B65: INCIDENTAL LAW CHARGES (EXCLUSIVE) | C65: 0 | D65: =+C65*9% | E65: =+D65 | F65: =IF(D65>0," ",C65*18%) | G65: =+C62*0.09
A68: (1) INCOME
A69: PARTICULARS | D69: GGST | E69: CGST | F69: IGST
A71: (1) INCOME AS PER LEDGERWISE CALCULATION | D71: =+D62 | E71: =+E62 | F71: =+F62
A72: (2) REFUND GIVEN BUT GST REFUND NOT GIVEN | C72: =G62 | D72: =+C72*0.09 | E72: =+C72*0.09 | F72: 0
D73: =+D71+D72 | E73: =+E71+E72 | F73: 0 | G73: 0
A74: (3) PAYABLE AS PER LEDGER | D74: 22500.65 | E74: =+D74 | F74: 0 | J74: 1368
A75: DIFFERENCE | D75: =+D73-D74 | E75: =+E73-E74 | F75: =IF(F71>F74,F71,F74) | G75: =+D75/9% | J75: 104
J76: =J74-J75
A77: (2) INPUT TAX CREDIT
A78: PARTICULARS | D78: GL 8546 GGST | E78: GL 8547 CGST | F78: GL 8548 IGST
A81: CURRENT MONTH INPUT TAX CREDIT AVAILABLE | D81: 2534.22 | E81: =+D81 | F81: 0 | G81: =+D81/2 | H81: =+E81/2 | I81: =+F81/2 | L81: 0
A82: LESS : CREDIT CANNOT BE UTILISED (BCUZ GST NO NOT AVAILABLE IN BILL) | D82: =+C90 | E82: =D82 | F82: =+E90 | G82: =+D82/2 | H82: =+E82/2 | I82: =+F82/2
A83: ELIGIBLE CREDIT | D83: =+D81-D82 | E83: =+E81-E82 | F83: =+F81-F82 | G83: =+D83/2 | H83: =+E83/2 | I83: =+F83/2
B86: OUR GST NO. NOT REFLECTED ON GST BILLS
B87: PARTY NAME | C87: GGST | D87: CGST | E87: IGST
B88: BSNL | D88: =+C88
B89: BSNL | D89: =+C89
B90: TOTAL | C90: =SUM(C88:C88) | D90: =SUM(D88:D88) | E90: =SUM(E88:E88)

Sheet NARAYANNAGAR
A1: NUTAN NAGARIK SAHAKARI BANK LTD (GUJARAT BRANCHES & HEAD OFFICE)
A3: BRANCH NAME :NARAYANNAGAR ROAD BRANCH
A4: BRANCH CODE: 15
A5: =+'ODHAV '!$A$5
A7: CODE NO. | B7: PARTICULARS | D7: GGST | E7: CGST | F7: IGST | I7: LOCKER CLOSED CREDIT
A8: PL
A9: 3303 | B9: DD CANCEL CHARGES | D9: =+C9*9% | E9: =+D9 | F9: =IF(D9>0," ",C9*18%) | I9: 0
A10: 3200 | B10: COMMISION ON BILLS | D10: =+C10*9% | E10: =+D10 | F10: =IF(D10>0," ",C10*18%) | I10: 0
A11: 3215 | B11: COMMISION ON PAYORDER | D11: =+C11*9% | E11: =+D11 | F11: =IF(D11>0," ",C11*18%) | I11: 0
A12: 3220 | B12: COMMISION ON U.B.D. | D12: =+C12*9% | E12: =+D12 | F12: =IF(D12>0," ",C12*18%) | I12: 0
A13: 3225 | B13: COMMISION I.B.C. | D13: =+C13*9% | E13: =+D13 | F13: =IF(D13>0," ",C13*18%) | I13: 0
A14: 3230 | B14: COMMISION ON GUARANTEE | D14: =+C14*9% | E14: =+D14 | F14: =IF(D14>0," ",C14*18%) | I14: 0
A15: 3235 | B15: COMMISION ON DEMAND DRAFT | D15: =+C15*9% | E15: =+D15 | F15: =IF(D15>0," ",C15*18%) | I15: 0
A16: 3240 | B16: COMMISION ON U.B.C. | D16: =+C16*9% | E16: =+D16 | F16: =IF(D16>0," ",C16*18%) | I16: 0
A17: 3245 | B17: COMMISION ON L.C. | D17: =+C17*9% | E17: =+D17 | F17: =IF(D17>0," ",C17*18%) | I17: 0
A18: 3250 | B18: COMMISSION ON GUARANTEE | D18: =+C18*9% | E18: =+D18 | F18: =IF(D18>0," ",C18*18%) | I18: 0
A19: 3270 | B19: PROCESSING CHARGE | D19: =+C19*9% | E19: =+D19 | F19: =IF(D19>0," ",C19*18%) | I19: 0
A20: 3271 | B20: RENEWAL FEES | D20: =+C20*9% | E20: =+D20 | F20: =IF(D20>0," ",C20*18%) | I20: 0
A21: 3274 | B21: INCOME FROM E-STAMPING | F21: =IF(D21>0," ",C21*18%) | I21: 0
A22: 3276 | B22: COMMISION ON PAN | D22: =+C22*9% | E22: =+D22 | F22: =IF(D22>0," ",C22*18%) | I22: 0
A23: 3280 | B23: INSURANCE PREMIUM | D23: =+C23*9% | E23: =+D23 | F23: =IF(D23>0," ",C23*18%) | I23: 0
A24: 3281 | B24: ATM CHARGES | D24: =+C24*9% | E24: =+D24 | F24: =IF(D24>0," ",C24*18%) | I24: 0
A25: 3285 | B25: COMMISION ON RTGS | D25: =+C25*9% | E25: =+D25 | F25: =IF(D25>0," ",C25*18%) | I25: 0
A26: 3286 | B26: COMMISION ON PMJJBY LIC | D26: =+C26*9% | E26: =+D26 | F26: =IF(D26>0," ",C26*18%) | I26: 0
A27: 3287 | B27: COMM. ON PMSBY NEW INDIA ASSURANCE | D27: =+C27*9% | E27: =+D27 | F27: =IF(D27>0," ",C27*18%) | I27: 0
A28: 3291 | B28: CIBIL CHARGES | D28: =+C28*9% | E28: =+D28 | F28: =IF(D28>0," ",C28*18%) | I28: 0
A29: 3296 | B29: RTGS/NEFT MANUAL CHARGES | D29: =+C29*0.09 | E29: =+D29 | F29: =IF(D29>0," ",C29*18%) | I29: 0
A30: 3297 | B30: ASBA FORM PRINT CHARGES | D30: =+C30*9% | E30: =+D30 | F30: =IF(D30>0," ",C30*18%) | I30: 0
A31: 3298 | B31: MANDATE HANDLING CHARGES | D31: =+C31*9% | E31: =+D31 | F31: =IF(D31>0," ",C31*18%) | I31: 0
A32: 3299 | B32: SI EXECUTION FAILED CHARGES | D32: =+C32*9% | E32: =+D32 | F32: =IF(D32>0," ",C32*18%) | I32: 0 | J32: =+C33-J33
A33: 3300 | B33: INCIDENTAL CHARGES | D33: =+C33*9% | E33: =+D33 | F33: =IF(D33>0," ",C33*18%) | I33: 0 | J33: 163981
A34: 3301 | B34: INOPERATIVE CHARGES | D34: =+C34*9% | E34: =+D34 | F34: =IF(D34>0," ",C34*18%) | I34: 0
A35: 3302 | B35: PO CANCEL CHARGES | D35: =+C35*9% | E35: =+D35 | F35: =IF(D35>0," ",C35*18%) | I35: 0
A36: 3305 | B36: A/C SHARE TRANSFER FEES | D36: =+C36*9% | E36: =+D36 | F36: =IF(D36>0," ",C36*18%) | I36: 0
A37: 3309 | B37: MIS. INCOME WITH GST | D37: =+C37*9% | E37: =+D37 | F37: =IF(D37>0," ",C37*18%) | I37: 0
A38: 3310 | B38: MIS. INCOME | D38: =+C38*9% | E38: =+D38 | F38: =IF(D38>0," ",C38*18%) | I38: 0
A39: 3311 | B39: I/W CHQ. RET. CHARGES | D39: =+C39*9% | E39: =+D39 | F39: =IF(D39>0," ",C39*18%) | I39: 0
A40: 3312 | B40: O/W CHQ. RET. CHARGES | D40: =+C40*9% | E40: =+D40 | F40: =IF(D40>0," ",C40*18%) | I40: 0
A41: 3313 | B41: ECS RETD. CHARGES | D41: =+C41*9% | E41: =+D41 | F41: =IF(D41>0," ",C41*18%) | I41: 0
A42: 3314 | B42: CHQ. BOOK ISSUE CHARGES | D42: =+C42*9% | E42: =+D42 | F42: =IF(D42>0," ",C42*18%) | I42: 0 | J42: =6150-C42
A43: 3315 | B43: CHARGES ON GODOWNS | D43: =+C43*9% | E43: =+D43 | F43: =IF(D43>0," ",C43*18%) | I43: 0
A44: 3316 | B44: CASH CHARGES | D44: =+C44*9% | E44: =+D44 | F44: =IF(D44>0," ",C44*18%) | I44: 0
A45: 3317 | B45: THE P&T CHARGES FOR LC/BG | D45: =+C45*9% | E45: =+D45 | F45: =IF(D45>0," ",C45*18%) | I45: 0
A46: 3318 | B46: OBC POSTAGE CHARGES | D46: =+C46*9% | E46: =+D46 | F46: =IF(D46>0," ",C46*18%) | I46: 0
A47: 3320 | B47: RENT ON LOCKER | D47: =+C47*9% | E47: =+D47 | F47: =IF(D47>0," ",C47*18%) | I47: 0
A48: 3321 | B48: ADHOC LIMIT CHARGES | D48: =+C48*9% | E48: =+D48 | F48: =IF(D48>0," ",C48*18%) | I48: 0
A49: 3322 | B49: INCOME FROM SALE OF OLD NEWS PAPERS | D49: =+C49*5% | E49: =+D49 | F49: =IF(D49>0," ",C49*18%) | I49: 0
A50: 3324 | B50: PENALTY ON OVERDUE LOCKER RENT | D50: =+C50*9% | E50: =+D50 | F50: =IF(D50>0," ",C50*18%) | I50: 0
A51: 3325 | B51: MICR CHARGES | D51: =+C51*2.5% | E51: =+D51 | F51: =IF(D51>0," ",C51*18%) | I51: 0
A52: 3391 | B52: SMS CHARGES INCOME RECEIVED | D52: =+C52*9% | E52: =+D52 | F52: =IF(D52>0," ",C52*18%) | I52: 0
A53: 3359 | B53: COMMITMENT CHARGES | D53: =+C53*9% | E53: =+D53 | F53: =IF(D53>0," ",C53*18%) | I53: 0
A54: 3825 | B54: EXTERNAL AUDIT FEES | D54: =+C54*9% | E54: =+D54 | F54: =IF(D54>0," ",C54*18%) | I54: 0
A55: 3362 | B55: FORECLOSURE CHARGES | F55: =IF(D55>0," ",C55*18%) | I55: 0
A56: 3340 | B56: LOAN PROCESSING FEES | D56: =+C56*9% | E56: =+D56 | F56: =IF(D56>0," ",C56*18%) | I56: 0
A57: GL | I57: 0
A58: 1720 | B58: COMM. RECD. BUT NOT ACCRUED | D58: =+C58*9% | E58: =+D58 | F58: 0 | I58: 0
A59: 1836 | B59: RENT ON LOCKER RECEIVED BUT | D59: =+C59*9% | E59: =+D59 | F59: =IF(D59>0," ",C59*18%) | I59: 0
B60: NOT ACCRUED | I60: 0
B61: SALE OF ASSET ( CASH COUNTING MACHINE) | D61: =+C61*0.09 | E61: =+D61 | F61: 0 | I61: 0
B62: TOTAL : | C62: =SUM(C9:C61) | D62: =SUM(D9:D61) | E62: =SUM(E9:E61) | F62: =SUM(F9:F61) | G62: =SUM(G9:G59) | H62: =SUM(H9:H59) | I62: =SUM(I9:I59)
A63: RCM
A64: PL 3750 | B64: LAW CHARGES (EXCLUSIVE) | C64: 0 | D64: =+C64*9% | E64: =+D64 | F64: =IF(D64>0," ",C64*18%)
A65: PL 3751 | B65: INCIDENTAL LAW CHARGES (EXCLUSIVE) | C65: 0 | D65: =+C65*9% | E65: =+D65 | F65: =IF(D65>0," ",C65*18%) | G65: =+C62*0.09
A66: SUMMARY
A68: (1) INCOME
A69: PARTICULARS | D69: GGST | E69: CGST | F69: IGST
A71: (1) INCOME AS PER LEDGERWISE CALCULATION | D71: =+D62 | E71: =+E62 | F71: 0 | G71: 13870 | H71: 33.03 | I71: =+H71/9*100
A72: (2) REFUND GIVEN BUT GST REFUND NOT GIVEN | C72: =G62 | D72: =+C72*0.09 | E72: =+C72*0.09 | F72: 0 | H72: 180 | I72: =+H72/9*100
D73: =+D71+D72 | E73: =+E71+E72 | F73: =+F71+F72
A74: (3) PAYABLE AS PER LEDGER | D74: 35698.38 | E74: =+D74 | F74: 0
A75: DIFFERENCE | D75: =+D73-D74 | E75: =+E73-E74 | F75: =IF(F71>F74,F71,F74) | G75: =+D75/9%
A78: (2) INPUT TAX CREDIT
A79: PARTICULARS | D79: GL 8546 GGST | E79: GL 8547 CGST | F79: GL 8548 IGST
A82: CURRENT MONTH INPUT TAX CREDIT AVAILABLE | D82: 4003.3 | E82: =+D82 | F82: 0 | G82: =+D82/2 | H82: =+E82/2 | I82: =+F82/2
A83: LESS : CREDIT CANNOT BE UTILISED (BCUZ GST NO NOT AVAILABLE IN BILL) | D83: =C93 | E83: =+D93 | F83: 0 | G83: =+D83/2 | H83: =+E83/2 | I83: =+F83/2
A84: ELIGIBLE CREDIT | D84: =+D82-D83 | E84: =+E82-E83 | F84: =+F82-F83 | G84: =+D84/2 | H84: =+E84/2 | I84: =+F84/2
B87: PARTY NAME | C87: CGST | D87: SGST | E87: IGST
B88: BSNL | D88: =+C88 | E88: 0
B89: ROHAN AGENCY | D89: =+C89 | F89: BLOCK CREDIT
B90: BSNL | D90: =+C90
B91: BSNL | C91: 0 | D91: =+C91
B92: BSNL | C92: 0 | D92: =+C92 | E92: 0
C93: =+SUM(C88:C92) | D93: =+SUM(D88:D92) | E93: =+SUM(E88:E92) | G93: =+C93/2

Sheet NARANPURA
A1: NUTAN NAGARIK SAHAKARI BANK LTD (GUJARAT BRANCHES & HEAD OFFICE)
A3: BRANCH NAME :NARANPURA BRANCH
A4: BRANCH CODE: 14
A5: =+'ODHAV '!$A$5
A7: CODE NO. | B7: PARTICULARS | D7: GGST | E7: CGST | F7: IGST | I7: LOCKER CLOSED CREDIT
A8: PL
A9: 3110 | B9: OVER DRAFT | D9: =+C9*9% | E9: =+D9 | F9: =IF(D9>0," ",C9*18%) | I9: 0
A10: 3200 | B10: COMMISION ON BILLS | D10: =+C10*9% | E10: =+D10 | F10: =IF(D10>0," ",C10*18%) | I10: 0
A11: 3215 | B11: COMMISION ON PAYORDER | D11: =+C11*9% | E11: =+D11 | F11: =IF(D11>0," ",C11*18%) | I11: 0
A12: 3220 | B12: COMMISION ON U.B.D. | D12: =+C12*9% | E12: =+D12 | F12: =IF(D12>0," ",C12*18%) | I12: 0
A13: 3225 | B13: COMMISION I.B.C. | D13: =+C13*9% | E13: =+D13 | F13: =IF(D13>0," ",C13*18%) | I13: 0
A14: 3230 | B14: COMMISION ON GUARANTEE | D14: =+C14*9% | E14: =+D14 | F14: =IF(D14>0," ",C14*18%) | I14: 0
A15: 3235 | B15: COMMISION ON DEMAND DRAFT | D15: =+C15*9% | E15: =+D15 | F15: =IF(D15>0," ",C15*18%) | I15: 0
A16: 3240 | B16: COMMISION ON U.B.C. | D16: =+C16*9% | E16: =+D16 | F16: =IF(D16>0," ",C16*18%) | I16: 0
A17: 3245 | B17: COMMISION ON L.C. | D17: =+C17*9% | E17: =+D17 | F17: =IF(D17>0," ",C17*18%) | I17: 0
A18: 3250 | B18: COMMISSION ON GUARANTEE | D18: =+C18*9% | E18: =+D18 | F18: =IF(D18>0," ",C18*18%) | I18: 0
A19: 3270 | B19: PROCESSING CHARGE | D19: =+C19*9% | E19: =+D19 | F19: =IF(D19>0," ",C19*18%) | I19: 0
A20: 3271 | B20: RENEWAL FEES | D20: =+C20*9% | E20: =+D20 | F20: =IF(D20>0," ",C20*18%) | I20: 0
A21: 3274 | B21: INCOME FROM E-STAMPING | D21: =+C21*9% | E21: =+D21 | F21: =IF(D21>0," ",C21*18%) | I21: 0
A22: 3276 | B22: COMMISION ON PAN | D22: =+C22*9% | E22: =+D22 | F22: =IF(D22>0," ",C22*18%) | I22: 0
A23: 3280 | B23: INSURANCE PREMIUM | D23: =+C23*9% | E23: =+D23 | F23: =IF(D23>0," ",C23*18%) | I23: 0
A24: 3281 | B24: ATM CHARGES | D24: =+C24*9% | E24: =+D24 | F24: =IF(D24>0," ",C24*18%) | I24: 0
A25: 3285 | B25: COMMISION ON RTGS | D25: =+C25*9% | E25: =+D25 | F25: =IF(D25>0," ",C25*18%) | I25: 0
A26: 3286 | B26: COMMISION ON PMJJBY LIC | D26: =+C26*9% | E26: =+D26 | F26: =IF(D26>0," ",C26*18%) | I26: 0
A27: 3287 | B27: COMM. ON PMSBY NEW INDIA ASSURANCE | D27: =+C27*9% | E27: =+D27 | F27: =IF(D27>0," ",C27*18%) | I27: 0
A28: 3291 | B28: CIBIL CHARGES | D28: =+C28*9% | E28: =+D28 | F28: =IF(D28>0," ",C28*18%) | I28: 0
A29: 3296 | B29: RTGS/NEFT MANUAL CHARGES | D29: =+C29*9% | E29: =+D29 | F29: =IF(D29>0," ",C29*18%) | I29: 0
A30: 3297 | B30: ASBA FORM PRINT CHARGES | D30: =+C30*9% | E30: =+D30 | F30: =IF(D30>0," ",C30*18%) | I30: 0
A31: 3298 | B31: MANDATE HANDLING CHARGES | D31: =+C31*9% | E31: =+D31 | F31: =IF(D31>0," ",C31*18%) | I31: 0
A32: 3299 | B32: SI EXECUTION FAILED CHARGES | D32: =+C32*9% | E32: =+D32 | F32: =IF(D32>0," ",C32*18%) | I32: 0
A33: 3300 | B33: INCIDENTAL CHARGES | D33: =+C33*9% | E33: =+D33 | F33: =IF(D33>0," ",C33*18%) | I33: 0
A34: 3301 | B34: INOPERATIVE CHARGES | D34: =+C34*9% | E34: =+D34 | F34: =IF(D34>0," ",C34*18%) | I34: 0
A35: 3302 | B35: PO CANCEL CHARGES | D35: =+C35*9% | E35: =+D35 | F35: =IF(D35>0," ",C35*18%) | I35: 0
A36: 3305 | B36: A/C SHARE TRANSFER FEES | D36: =+C36*9% | E36: =+D36 | F36: =IF(D36>0," ",C36*18%) | I36: 0
A37: 3309 | B37: MIS. INCOME WITH GST | D37: =+C37*9% | E37: =+D37 | F37: =IF(D37>0," ",C37*18%) | I37: 0
A38: 3310 | B38: MIS. INCOME | D38: =+C38*9% | E38: =+D38 | F38: 0 | I38: 0
A39: 3311 | B39: I/W CHQ. RET. CHARGES | D39: =+C39*9% | E39: =+D39 | F39: 0 | I39: 0
A40: 3312 | B40: O/W CHQ. RET. CHARGES | D40: =+C40*9% | E40: =+D40 | F40: =IF(D40>0," ",C40*18%) | I40: 0
A41: 3313 | B41: ECS RETD. CHARGES | D41: =+C41*9% | E41: =+D41 | F41: =IF(D41>0," ",C41*18%) | I41: 0
A42: 3314 | B42: CHQ. BOOK ISSUE CHARGES | D42: =+C42*9% | E42: =+D42 | F42: =IF(D42>0," ",C42*18%) | I42: 0
A43: 3315 | B43: CHARGES ON GODOWNS | D43: =+C43*9% | E43: =+D43 | F43: =IF(D43>0," ",C43*18%) | I43: 0
A44: 3316 | B44: CASH CHARGES | D44: =+C44*9% | E44: =+D44 | F44: =IF(D44>0," ",C44*18%) | I44: 0
A45: 3317 | B45: THE P&T CHARGES FOR LC/BG | D45: =+C45*9% | E45: =+D45 | F45: =IF(D45>0," ",C45*18%) | I45: 0
A46: 3318 | B46: OBC POSTAGE CHARGES | D46: =+C46*9% | E46: =+D46 | F46: =IF(D46>0," ",C46*18%) | I46: 0
A47: 3320 | B47: RENT ON LOCKER | D47: =+C47*9% | E47: =+D47 | F47: 0 | I47: 0
A48: 3321 | B48: ADHOC LIMIT CHARGES | D48: =+C48*9% | E48: =+D48 | F48: =IF(D48>0," ",C48*18%) | I48: 0
A49: 3322 | B49: INCOME FROM SALE OF OLD NEWS PAPERS | D49: =+C49*9% | E49: =+D49 | F49: =IF(D49>0," ",C49*18%) | I49: 0
A50: 3324 | B50: PENALTY ON OVERDUE LOCKER RENT | D50: =+C50*9% | E50: =+D50 | F50: =IF(D50>0," ",C50*18%) | I50: 0
A51: 3325 | B51: MICR CHARGES | D51: =+C51*2.5% | E51: =+D51 | F51: =IF(D51>0," ",C51*18%) | I51: 0
A52: 3391 | B52: SMS CHARGES INCOME RECEIVED | D52: =+C52*9% | E52: =+D52 | F52: =IF(D52>0," ",C52*18%) | I52: 0
A53: 3359 | B53: COMMITMENT CHARGES | D53: =+C53*9% | E53: =+D53 | F53: =IF(D53>0," ",C53*18%) | I53: 0
A54: 3825 | B54: EXTERNAL AUDIT FEES | F54: =IF(D54>0," ",C54*18%) | I54: 0
A55: 3362 | B55: FORECLOSURE CHARGES | F55: =IF(D55>0," ",C55*18%) | I55: 0
A56: 3340 | B56: LOAN PROCESSING FEES | D56: =+C56*9% | E56: =+D56 | F56: =IF(D56>0," ",C56*18%) | I56: 0
A57: GL | D57: =+C57*9% | E57: =+D57 | I57: 0
A58: 1720 | B58: COMM. RECD. BUT NOT ACCRUED | D58: =+C58*9% | E58: =+D58 | F58: 0 | I58: 0
A59: 1836 | B59: RENT ON LOCKER RECEIVED BUT | D59: =+C59*9% | E59: =+D59 | F59: 0 | I59: 0
B60: NOT ACCRUED | D60: =+C60*9% | E60: =+D60 | I60: 0
B61: SALE OF ASSET ( CASH COUNTING MACHINE) | I61: 0
B62: TOTAL : | C62: =SUM(C9:C61) | D62: =SUM(D9:D61) | E62: =SUM(E9:E61) | F62: =SUM(F9:F61) | G62: =SUM(G9:G61) | H62: =SUM(H9:H59) | I62: =SUM(I9:I59)
A63: RCM
A64: PL 3750 | B64: LAW CHARGES (EXCLUSIVE) | C64: 0 | D64: =+C64*9% | E64: =+D64 | F64: =IF(D64>0," ",C64*18%)
A65: PL 3751 | B65: INCIDENTAL LAW CHARGES (EXCLUSIVE) | C65: 0 | D65: =+C65*9% | E65: =+D65 | F65: =IF(D65>0," ",C65*18%)
A66: SUMMARY
G67: =+C62*9% | H67: =13%/2 | I67: =+G67-H67
A68: (1) INCOME
A69: PARTICULARS | D69: GGST | E69: CGST | F69: IGST
H70: =8.1+8.1+32.4+8.1+8.1+2.7+16.2+8.1+64.8+8.1+32.4+16.2+16.2+48.6+16.2+8.1+16.2+4.5+16.2+8.1+8.1+32.4+16.2+8.1+8.1+48.6 | I70: =+H70/9%
A71: (1) INCOME AS PER LEDGERWISE CALCULATION | D71: =+D62 | E71: =+E62 | F71: =+F62
A72: (2) REFUND GIVEN BUT GST REFUND NOT GIVEN | C72: =G62 | D72: =+C72*0.09 | E72: =+C72*0.09 | F72: 0
D73: =+D71+D72 | E73: =+E71+E72 | F73: 0 | H73: =+C62+C72
A74: (3) PAYABLE AS PER LEDGER | E74: =+D74 | F74: 0 | H74: =+H73*0.18
A75: DIFFERENCE | D75: =+D73-D74 | E75: =+E73-E74 | F75: =IF(F71>F74,F71,F74) | G75: =+E75/9*100
A78: (2) INPUT TAX CREDIT
A79: PARTICULARS | D79: GL 8546 GGST | E79: GL 8547 CGST | F79: GL 8548 IGST
A82: CURRENT MONTH INPUT TAX CREDIT AVAILABLE | E82: =+D82 | F82: 0 | G82: =+D82/2 | H82: =+E82/2 | I82: =+F82/2
A83: LESS : CREDIT CANNOT BE UTILISED (BCUZ GST NO NOT AVAILABLE IN BILL) | D83: =+C92 | E83: =+D83 | F83: 0 | G83: =+D83/2 | H83: =+E83/2 | I83: =+F83/2
A84: ELIGIBLE CREDIT | D84: =+D82-D83 | E84: =+E82-E83 | F84: =+F82-F83 | G84: =+D84/2 | H84: =+E84/2 | I84: =+F84/2
B87: OUR GST NO. NOT REFLECTED ON CENVAT BILLS
B88: PARTY NAME | C88: GGST | D88: CGST | E88: IGST
B89: BSNL | D89: =+C89 | E89: 0
B90: ROHAN AGENCY | D90: =+C90
B91: BSNL | C91: 0 | D91: =+C91 | E91: 0
B92: TOTAL | C92: =SUM(C89:C91) | D92: =SUM(D89:D91) | E92: =SUM(E89:E91) | G92: =+C92/2

Sheet DRIVE IN
A1: NUTAN NAGARIK SAHAKARI BANK LTD (GUJARAT BRANCHES & HEAD OFFICE)
A3: BRANCH NAME :DRIVE IN BRANCH
A4: BRANCH CODE: 09
A5: =+'ODHAV '!$A$5
A7: CODE NO. | B7: PARTICULARS | D7: GGST | E7: CGST | F7: IGST | I7: LOCKER CLOSED
A8: PL
A9: 3380 | B9: STATMENT CHARGES | D9: =+C9*9% | E9: =+D9 | F9: =IF(D9>0," ",C9*18%) | I9: 0
A10: 3200 | B10: COMMISION ON BILLS | D10: =+C10*9% | E10: =+D10 | F10: =IF(D10>0," ",C10*18%) | I10: 0
A11: 3215 | B11: COMMISION ON PAYORDER | D11: =+C11*9% | E11: =+D11 | F11: =IF(D11>0," ",C11*18%) | I11: 0
A12: 3220 | B12: COMMISION ON U.B.D. | D12: =+C12*9% | E12: =+D12 | F12: =IF(D12>0," ",C12*18%) | I12: 0
A13: 3225 | B13: COMMISION I.B.C. | D13: =+C13*9% | E13: =+D13 | F13: =IF(D13>0," ",C13*18%) | I13: 0
A14: 3230 | B14: COMMISION ON GUARANTEE | D14: =+C14*9% | E14: =+D14 | F14: =IF(D14>0," ",C14*18%) | I14: 0
A15: 3235 | B15: COMMISION ON DEMAND DRAFT | D15: =+C15*9% | E15: =+D15 | F15: =IF(D15>0," ",C15*18%) | I15: 0
A16: 3240 | B16: COMMISION ON U.B.C. | D16: =+C16*9% | E16: =+D16 | F16: =IF(D16>0," ",C16*18%) | I16: 0
A17: 3245 | B17: COMMISION ON L.C. | D17: =+C17*9% | E17: =+D17 | F17: =IF(D17>0," ",C17*18%) | I17: 0
A18: 3250 | B18: COMMISSION ON GUARANTEE | D18: =+C18*9% | E18: =+D18 | F18: =IF(D18>0," ",C18*18%) | I18: 0
A19: 3270 | B19: PROCESSING CHARGE | D19: =+C19*9% | E19: =+D19 | F19: =IF(D19>0," ",C19*18%) | I19: 0
A20: 3271 | B20: RENEWAL FEES | D20: =+C20*9% | E20: =+D20 | F20: =IF(D20>0," ",C20*18%) | I20: 0
A21: 3274 | B21: INCOME FROM E-STAMPING | D21: =+C21*9% | E21: =+D21 | F21: =IF(D21>0," ",C21*18%) | I21: 0
A22: 3276 | B22: COMMISION ON PAN | D22: =+C22*9% | E22: =+D22 | F22: =IF(D22>0," ",C22*18%) | I22: 0
A23: 3280 | B23: INSURANCE PREMIUM | D23: =+C23*9% | E23: =+D23 | F23: =IF(D23>0," ",C23*18%) | I23: 0
A24: 3281 | B24: ATM CHARGES | D24: =+C24*9% | E24: =+D24 | F24: =IF(D24>0," ",C24*18%) | I24: 0
A25: 3285 | B25: COMMISION ON RTGS | D25: =+C25*9% | E25: =+D25 | F25: =IF(D25>0," ",C25*18%) | I25: 0
A26: 3286 | B26: COMMISION ON PMJJBY LIC | D26: =+C26*9% | E26: =+D26 | F26: =IF(D26>0," ",C26*18%) | I26: 0
A27: 3287 | B27: COMM. ON PMSBY NEW INDIA ASSURANCE | D27: =+C27*9% | E27: =+D27 | F27: =IF(D27>0," ",C27*18%) | I27: 0
A28: 3291 | B28: CIBIL CHARGES | D28: =+C28*9% | E28: =+D28 | F28: =IF(D28>0," ",C28*18%) | I28: 0
A29: 3296 | B29: RTGS/NEFT MANUAL CHARGES | D29: =+C29*9% | E29: =+D29 | F29: =IF(D29>0," ",C29*18%) | I29: 0
A30: 3297 | B30: ASBA FORM PRINT CHARGES | D30: =+C30*9% | E30: =+D30 | F30: =IF(D30>0," ",C30*18%) | I30: 0
A31: 3298 | B31: MANDATE HANDLING CHARGES | D31: =+C31*9% | E31: =+D31 | F31: =IF(D31>0," ",C31*18%) | I31: 0
A32: 3299 | B32: SI EXECUTION FAILED CHARGES | D32: =+C32*9% | E32: =+D32 | F32: =IF(D32>0," ",C32*18%) | I32: 0
A33: 3300 | B33: INCIDENTAL CHARGES | D33: =+C33*9% | E33: =+D33 | F33: 0 | I33: 0
A34: 3301 | B34: INOPERATIVE CHARGES | D34: =+C34*9% | E34: =+D34 | F34: =IF(D34>0," ",C34*18%) | I34: 0
A35: 3302 | B35: PO CANCEL CHARGES | D35: =+C35*9% | E35: =+D35 | F35: =IF(D35>0," ",C35*18%) | I35: 0
A36: 3305 | B36: A/C SHARE TRANSFER FEES | D36: =+C36*9% | E36: =+D36 | F36: =IF(D36>0," ",C36*18%) | I36: 0
A37: 3309 | B37: MIS. INCOME WITH GST | D37: =+C37*9% | E37: =+D37 | F37: =IF(D37>0," ",C37*18%) | I37: 0
A38: 3310 | B38: MIS. INCOME | D38: =+C38*9% | E38: =+D38 | F38: =IF(D38>0," ",C38*18%) | I38: 0
A39: 3311 | B39: I/W CHQ. RET. CHARGES | D39: =+C39*9% | E39: =+D39 | F39: =IF(D39>0," ",C39*18%) | I39: 0
A40: 3312 | B40: O/W CHQ. RET. CHARGES | D40: =+C40*9% | E40: =+D40 | F40: =IF(D40>0," ",C40*18%) | I40: 0
A41: 3313 | B41: ECS RETD. CHARGES | D41: =+C41*9% | E41: =+D41 | F41: =IF(D41>0," ",C41*18%) | I41: 0
A42: 3314 | B42: CHQ. BOOK ISSUE CHARGES | D42: =+C42*9% | E42: =+D42 | F42: =IF(D42>0," ",C42*18%) | I42: 0
A43: 3315 | B43: CHARGES ON GODOWNS | D43: =+C43*9% | E43: =+D43 | F43: =IF(D43>0," ",C43*18%) | I43: 0
A44: 3316 | B44: CASH CHARGES | D44: =+C44*9% | E44: =+D44 | F44: =IF(D44>0," ",C44*18%) | I44: 0
A45: 3317 | B45: THE P&T CHARGES FOR LC/BG | D45: =+C45*9% | E45: =+D45 | F45: =IF(D45>0," ",C45*18%) | I45: 0
A46: 3318 | B46: OBC POSTAGE CHARGES | D46: =+C46*9% | E46: =+D46 | F46: =IF(D46>0," ",C46*18%) | I46: 0
A47: 3320 | B47: RENT ON LOCKER | D47: =+C47*9% | E47: =+D47 | F47: =IF(D47>0," ",C47*18%) | I47: 0
A48: 3321 | B48: ADHOC LIMIT CHARGES | D48: =+C48*9% | E48: =+D48 | F48: =IF(D48>0," ",C48*18%) | I48: 0
A49: 3322 | B49: INCOME FROM SALE OF OLD NEWS PAPERS | D49: =+C49*9% | E49: =+D49 | F49: =IF(D49>0," ",C49*18%) | I49: 0
A50: 3324 | B50: PENALTY ON OVERDUE LOCKER RENT | D50: =+C50*9% | E50: =+D50 | F50: =IF(D50>0," ",C50*18%) | I50: 0
A51: 3325 | B51: MICR CHARGES | D51: =+C51*2.5% | E51: =+D51 | F51: =IF(D51>0," ",C51*18%) | I51: 0
A52: 3380 | B52: STATMENT CHARGES | D52: =+C52*9% | E52: =+D52 | I52: 0
A53: 3391 | B53: SMS CHARGES INCOME RECEIVED | D53: =+C53*9% | E53: =+D53 | F53: =IF(D53>0," ",C53*18%) | I53: 0
A54: 3359 | B54: COMMITMENT CHARGES | D54: =+C54*9% | E54: =+D54 | F54: =IF(D54>0," ",C54*18%) | I54: 0
A55: 3825 | B55: EXTERNAL AUDIT FEES | D55: =+C55*9% | E55: =+D55 | I55: 0
A56: 3362 | B56: FORECLOSURE CHARGES | D56: =+C56*9% | E56: =+D56 | I56: 0
A57: 3340 | B57: LOAN PROCESSING FEES | D57: =+C57*9% | E57: =+D57 | F57: =IF(D57>0," ",C57*18%) | I57: 0
A58: GL | D58: =+C58*9% | E58: =+D58 | F58: =IF(D58>0," ",C58*18%) | I58: 0
A59: 1720 | B59: COMM. RECD. BUT NOT ACCRUED | D59: =+C59*9% | E59: =+D59 | F59: 0 | I59: 0
A60: 1836 | B60: RENT ON LOCKER RECEIVED BUT | D60: =+C60*9% | E60: =+D60 | F60: =IF(D60>0," ",C60*18%) | I60: 0
B61: NOT ACCRUED | D61: =+C61*9% | E61: =+D61 | F61: =IF(D61>0," ",C61*18%) | I61: 0
B62: SALE OF ASSET ( CASH COUNTING MACHINE) | D62: =+C62*9% | E62: =+D62 | F62: =IF(D62>0," ",C62*18%) | I62: 0
B63: TOTAL : | C63: =SUM(C9:C62) | D63: =SUM(D9:D62) | E63: =SUM(E9:E62) | F63: =SUM(F9:F62) | G63: =SUM(G9:G62) | H63: =SUM(H9:H60)
A64: RCM
A65: PL 3750 | B65: LAW CHARGES (EXCLUSIVE) | C65: 0 | D65: =+C65*9% | E65: =+D65 | F65: 0
A66: PL 3751 | B66: INCIDENTAL LAW CHARGES (EXCLUSIVE) | C66: 0 | D66: =+C66*9% | E66: =+D66 | F66: =IF(D66>0," ",C66*18%) | G66: =+C63*0.09
A67: SUMMARY
A68: (1) INCOME
A69: PARTICULARS | D69: GGST | E69: CGST | F69: IGST
A71: (1) INCOME AS PER LEDGERWISE CALCULATION | D71: =+D63 | E71: =+E63 | F71: =+F63
A72: (2) REFUND GIVEN BUT GST REFUND NOT GIVEN | C72: =G63 | D72: =+C72*0.09 | E72: =+C72*0.09 | F72: 0
D73: =+D71+D72 | E73: =+E71+E72 | F73: =+F71+F72
A74: (3) PAYABLE AS PER LEDGER | D74: 30035.78 | E74: =+D74 | F74: =+F73
A75: DIFFERENCE | D75: =+D73-D74 | E75: =+E73-E74 | F75: =IF(F71>F74,F71,F74) | G75: =+D75/9%
A77: (2) INPUT TAX CREDIT
A78: PARTICULARS | D78: GL 8546 GGST | E78: GL 8547 CGST | F78: GL 8548 IGST
A81: CURRENT MONTH INPUT TAX CREDIT AVAILABLE | D81: 15183.72 | E81: =+D81 | F81: 0 | G81: =+D81/2 | H81: =+E81/2 | I81: =+F81/2
A82: LESS : CREDIT CANNOT BE UTILISED (BCUZ GST NO NOT AVAILABLE IN BILL) | D82: =+C93 | E82: =+D82 | F82: =+E93 | G82: =+D82/2 | H82: =+E82/2 | I82: =+F82/2
A83: ELIGIBLE CREDIT | D83: =+D81-D82 | E83: =+E81-E82 | F83: =+F81-F82 | G83: =+D83/2 | H83: =+E83/2 | I83: =+F83/2
B87: OUR GST NO. NOT REFLECTED ON CENVAT BILLS
B88: PARTY NAME | C88: GGST | D88: CGST | E88: IGST
B89: BSNL | D89: =C89 | E89: 0
B90: ROHAN AGENCY | D90: =C90 | F90: BLOCK CREDIT
B91: BSNL | D91: =C91
B92: ROHAN AGENCY | D92: =+C92 | E92: 0
C93: =SUM(C89:C92) | D93: =SUM(D89:D92) | E93: =SUM(E89:E92)

Sheet VASANA 
A1: NUTAN NAGARIK SAHAKARI BANK LTD (GUJARAT BRANCHES & HEAD OFFICE)
A3: BRANCH NAME : VASNA BRANCH
A4: BRANCH CODE: 8
A5: =+'ODHAV '!$A$5
A7: CODE NO. | B7: PARTICULARS | D7: GGST | E7: CGST | F7: IGST | I7: LOCKER CLOSED CREDIT
A8: PL
A9: 3303 | B9: DD CANCEL CHARGES | D9: =+C9*9% | E9: =+D9 | F9: =IF(D9>0," ",C9*18%) | I9: 0
A10: 3200 | B10: COMMISION ON BILLS | D10: =+C10*9% | E10: =+D10 | F10: =IF(D10>0," ",C10*18%) | I10: 0
A11: 3215 | B11: COMMISION ON PAYORDER | D11: =+C11*9% | E11: =+D11 | F11: =IF(D11>0," ",C11*18%) | I11: 0
A12: 3220 | B12: COMMISION ON U.B.D. | D12: =+C12*9% | E12: =+D12 | F12: =IF(D12>0," ",C12*18%) | I12: 0
A13: 3225 | B13: COMMISION I.B.C. | D13: =+C13*9% | E13: =+D13 | F13: =IF(D13>0," ",C13*18%) | I13: 0
A14: 3230 | B14: COMMISION ON GUARANTEE | D14: =+C14*9% | E14: =+D14 | F14: =IF(D14>0," ",C14*18%) | I14: 0
A15: 3235 | B15: COMMISION ON DEMAND DRAFT | D15: =+C15*9% | E15: =+D15 | F15: =IF(D15>0," ",C15*18%) | I15: 0
A16: 3240 | B16: COMMISION ON U.B.C. | D16: =+C16*9% | F16: =IF(D16>0," ",C16*18%) | I16: 0
A17: 3245 | B17: COMMISION ON L.C. | D17: =+C17*9% | E17: =+D17 | F17: =IF(D17>0," ",C17*18%) | I17: 0
A18: 3250 | B18: COMMISSION ON GUARANTEE | D18: =+C18*9% | E18: =+D18 | F18: =IF(D18>0," ",C18*18%) | I18: 0
A19: 3270 | B19: PROCESSING CHARGE | D19: =+C19*9% | E19: =+D19 | F19: =IF(D19>0," ",C19*18%) | I19: 0
A20: 3271 | B20: RENEWAL FEES | D20: =+C20*9% | E20: =+D20 | F20: =IF(D20>0," ",C20*18%) | I20: 0
A21: 3274 | B21: INCOME FROM E-STAMPING | D21: =+C21*9% | E21: =+D21 | I21: 0
A22: 3276 | B22: COMMISION ON PAN | D22: =+C22*9% | E22: =+D22 | F22: =IF(D22>0," ",C22*18%) | I22: 0
A23: 3280 | B23: INSURANCE PREMIUM | D23: =+C23*9% | E23: =+D23 | F23: =IF(D23>0," ",C23*18%) | I23: 0
A24: 3281 | B24: ATM CHARGES | D24: =+C24*9% | E24: =+D24 | F24: 0 | I24: 0
A25: 3285 | B25: COMMISION ON RTGS | D25: =+C25*9% | E25: =+D25 | F25: =IF(D25>0," ",C25*18%) | I25: 0
A26: 3286 | B26: COMMISION ON PMJJBY LIC | D26: =+C26*9% | E26: =+D26 | F26: =IF(D26>0," ",C26*18%) | I26: 0
A27: 3287 | B27: COMM. ON PMSBY NEW INDIA ASSURANCE | D27: =+C27*9% | E27: =+D27 | F27: =IF(D27>0," ",C27*18%) | I27: 0
A28: 3291 | B28: CIBIL CHARGES | D28: =+C28*9% | E28: =+D28 | F28: =IF(D28>0," ",C28*18%) | I28: 0
A29: 3296 | B29: RTGS/NEFT MANUAL CHARGES | D29: =+C29*9% | E29: =+D29 | F29: =IF(D29>0," ",C29*18%) | I29: 0
A30: 3297 | B30: ASBA FORM PRINT CHARGES | D30: =+C30*9% | E30: =+D30 | F30: =IF(D30>0," ",C30*18%) | I30: 0
A31: 3298 | B31: MANDATE HANDLING CHARGES | D31: =+C31*9% | E31: =+D31 | F31: =IF(D31>0," ",C31*18%) | I31: 0
A32: 3299 | B32: SI EXECUTION FAILED CHARGES | D32: =+C32*9% | E32: =+D32 | F32: =IF(D32>0," ",C32*18%) | I32: 0
A33: 3300 | B33: INCIDENTAL CHARGES | D33: =+C33*9% | E33: =+D33 | I33: 0
A34: 3301 | B34: INOPERATIVE CHARGES | D34: =+C34*9% | E34: =+D34 | F34: =IF(D34>0," ",C34*18%) | I34: 0
A35: 3302 | B35: PO CANCEL CHARGES | D35: =+C35*9% | E35: =+D35 | F35: =IF(D35>0," ",C35*18%) | I35: 0
A36: 3305 | B36: A/C SHARE TRANSFER FEES | D36: =+C36*9% | E36: =+D36 | F36: =IF(D36>0," ",C36*18%) | I36: 0
A37: 3309 | B37: MIS. INCOME WITH GST | D37: =+C37*2.5% | E37: =+D37 | F37: =IF(D37>0," ",C37*18%) | I37: 0
A38: 3310 | B38: MIS. INCOME | D38: =+C38*9% | E38: =+D38 | F38: =IF(D38>0," ",C38*18%) | I38: 0
A39: 3311 | B39: I/W CHQ. RET. CHARGES | D39: =+C39*9% | E39: =+D39 | F39: =IF(D39>0," ",C39*18%) | I39: 0
A40: 3312 | B40: O/W CHQ. RET. CHARGES | D40: =+C40*9% | E40: =+D40 | F40: =IF(D40>0," ",C40*18%) | I40: 0
A41: 3313 | B41: ECS RETD. CHARGES | D41: =+C41*9% | E41: =+D41 | F41: =IF(D41>0," ",C41*18%) | I41: 0
A42: 3314 | B42: CHQ. BOOK ISSUE CHARGES | D42: =+C42*9% | E42: =+D42 | F42: =IF(D42>0," ",C42*18%) | I42: 0
A43: 3315 | B43: CHARGES ON GODOWNS | D43: =+C43*9% | E43: =+D43 | F43: =IF(D43>0," ",C43*18%) | I43: 0
A44: 3316 | B44: CASH CHARGES | D44: =+C44*9% | E44: =+D44 | F44: =IF(D44>0," ",C44*18%) | I44: 0
A45: 3317 | B45: THE P&T CHARGES FOR LC/BG | D45: =+C45*9% | E45: =+D45 | F45: =IF(D45>0," ",C45*18%) | I45: 0
A46: 3318 | B46: OBC POSTAGE CHARGES | D46: =+C46*9% | E46: =+D46 | F46: =IF(D46>0," ",C46*18%) | I46: 0
A47: 3320 | B47: RENT ON LOCKER | D47: =+C47*9% | E47: =+D47 | F47: =IF(D47>0," ",C47*18%) | I47: 0
A48: 3321 | B48: ADHOC LIMIT CHARGES | D48: =+C48*9% | E48: =+D48 | F48: =IF(D48>0," ",C48*18%) | I48: 0
A49: 3322 | B49: INCOME FROM SALE OF OLD NEWS PAPERS | D49: =+C49*5% | E49: =+D49 | I49: 0
A50: 3324 | B50: PENALTY ON OVERDUE LOCKER RENT | D50: =+C50*9% | E50: =+D50 | I50: 0
A51: 3325 | B51: MICR CHARGES | D51: =+C51*2.5% | E51: =+D51 | F51: =IF(D51>0," ",C51*18%) | I51: 0
A52: 3391 | B52: SMS CHARGES INCOME RECEIVED | D52: =+C52*9% | E52: =+D52 | F52: =IF(D52>0," ",C52*18%) | I52: 0
A53: 3359 | B53: COMMITMENT CHARGES | D53: =+C53*9% | E53: =+D53 | I53: 0
A54: 3825 | B54: EXTERNAL AUDIT FEES | D54: =+C54*9% | E54: =+D54 | I54: 0
A55: 3362 | B55: FORECLOSURE CHARGES | D55: =+C55*9% | E55: =+D55 | I55: 0
A56: 3340 | B56: LOAN PROCESSING FEES | D56: =+C56*9% | E56: =+D56 | F56: =IF(D56>0," ",C56*18%) | I56: 0
A57: GL | D57: =+C57*9% | E57: =+D57 | I57: 0
A58: 1720 | B58: COMM. RECD. BUT NOT ACCRUED | D58: =+C58*9% | E58: =+D58 | F58: =IF(D58>0," ",C58*18%) | I58: 0
A59: 1836 | B59: RENT ON LOCKER RECEIVED BUT | D59: =+C59*9% | E59: =+D59 | F59: 0 | I59: 0
B60: NOT ACCRUED | D60: =+C60*9% | E60: =+D60 | I60: 0
B61: SALE OF ASSET ( CASH COUNTING MACHINE) | D61: =+C61*9% | E61: =+D61 | I61: 0
B62: TOTAL : | C62: =SUM(C9:C61) | D62: =SUM(D9:D61) | E62: =SUM(E9:E61) | F62: =SUM(F9:F59) | G62: =SUM(G9:G59) | H62: =SUM(H9:H59)
A63: RCM
A64: PL 3750 | B64: LAW CHARGES (EXCLUSIVE) | C64: 0 | D64: =+C64*9% | E64: =+D64 | F64: =IF(D64>0," ",C64*18%)
A65: PL 3751 | B65: INCIDENTAL LAW CHARGES (EXCLUSIVE) | C65: 0 | D65: =+C65*9% | E65: =+D65 | F65: =IF(D65>0," ",C65*18%) | G65: =+C62*0.09
A66: SUMMARY
A68: (1) INCOME | G68: =+C62+C72
A69: PARTICULARS | D69: GGST | E69: CGST | F69: IGST | G69: =+G68*0.09
A71: (1) INCOME AS PER LEDGERWISE CALCULATION | D71: =+D62 | E71: =+E62 | F71: =+F62
A72: (2) REFUND GIVEN BUT GST REFUND NOT GIVEN | C72: =G62 | D72: =+C72*0.09 | E72: =+C72*0.09 | F72: 0
D73: =+D71+D72 | E73: =+E71+E72 | F73: 0
A74: (3) PAYABLE AS PER LEDGER | D74: 35950.57 | E74: =+D74 | F74: 0 | I74: 31.59 | J74: =+I74/9*100
A75: DIFFERENCE | D75: =+D73-D74 | E75: =+E73-E74 | F75: =IF(F71>F74,F71,F74) | G75: =+E75/0.09 | J75: =685-J74
A77: (2) INPUT TAX CREDIT
A78: PARTICULARS | D78: GL 8546 GGST | E78: GL 8547 CGST | F78: GL 8548 IGST
A81: CURRENT MONTH INPUT TAX CREDIT AVAILABLE | D81: 2024.01 | E81: =+D81 | F81: 0 | G81: =+D81/2 | H81: =+E81/2 | I81: =+F81/2
A82: LESS : CREDIT CANNOT BE UTILISED (BCUZ GST NO NOT AVAILABLE IN BILL) | D82: =+C95 | E82: =D82 | F82: =+E95 | G82: =+D82/2 | H82: =+E82/2 | I82: =+F82/2
A83: ELIGIBLE CREDIT | D83: =+D81-D82 | E83: =+E81-E82 | F83: =+F81-F82 | G83: =+D83/2 | H83: =+E83/2 | I83: =+F83/2
B85: OUR GST NO. NOT REFLECTED ON CENVAT BILLS & BLOCKED CREDIT
B86: PARTY NAME | C86: CGST | D86: SGST | E86: IGST
B87: BSNL | D87: =+C87 | E87: 0
B88: ADITYA SOLSURF PRIVATE LIMITED | D88: =+C88
B89: KABIR TECHNOLOGIES PVT LTD | D89: =+C89
B90: UMIYA PLY & HARDWARE | D90: =+C90
B91: UMIYA PLY & HARDWARE | D91: =+C91
B92: UMIYA PLY & HARDWARE | D92: =+C92
B93: UMIYA PLY & HARDWARE | D93: =+C93
B94: RINKU CORPORATION | D94: =+C94
B95: TOTAL | C95: =SUM(C87:C94) | D95: =SUM(D87:D94) | E95: =SUM(E87:E87)

Sheet SURAT
A1: NUTAN NAGARIK SAHAKARI BANK LTD (GUJARAT BRANCHES & HEAD OFFICE)
A3: BRANCH NAME : SURAT BRANCH
A4: BRANCH CODE: 41
A5: =+'ODHAV '!$A$5
A7: CODE NO. | B7: PARTICULARS | D7: GGST | E7: CGST | F7: IGST | I7: LOCKER CLOSED CREDIT
A8: PL
A9: 3303 | B9: DD CANCEL CHARGES | D9: =+C9*9% | E9: =+D9 | F9: =IF(D9>0," ",C9*18%) | I9: 0
A10: 3200 | B10: COMMISION ON BILLS | D10: =+C10*9% | E10: =+D10 | F10: =IF(D10>0," ",C10*18%) | I10: 0
A11: 3215 | B11: COMMISION ON PAYORDER | D11: =+C11*9% | E11: =+D11 | F11: =IF(D11>0," ",C11*18%) | I11: 0
A12: 3220 | B12: COMMISION ON U.B.D. | D12: =+C12*9% | E12: =+D12 | F12: =IF(D12>0," ",C12*18%) | I12: 0
A13: 3225 | B13: COMMISION I.B.C. | D13: =+C13*9% | E13: =+D13 | F13: =IF(D13>0," ",C13*18%) | I13: 0
A14: 3230 | B14: COMMISION ON GUARANTEE | D14: =+C14*9% | E14: =+D14 | F14: =IF(D14>0," ",C14*18%) | I14: 0
A15: 3235 | B15: COMMISION ON DEMAND DRAFT | D15: =+C15*9% | E15: =+D15 | F15: =IF(D15>0," ",C15*18%) | I15: 0
A16: 3240 | B16: COMMISION ON U.B.C. | D16: =+C16*9% | E16: =+D16 | F16: =IF(D16>0," ",C16*18%) | I16: 0
A17: 3245 | B17: COMMISION ON L.C. | D17: =+C17*9% | E17: =+D17 | F17: =IF(D17>0," ",C17*18%) | I17: 0
A18: 3250 | B18: COMMISSION ON GUARANTEE | D18: =+C18*9% | E18: =+D18 | F18: =IF(D18>0," ",C18*18%) | I18: 0
A19: 3270 | B19: PROCESSING CHARGE | D19: =+C19*9% | E19: =+D19 | F19: =IF(D19>0," ",C19*18%) | I19: 0
A20: 3271 | B20: RENEWAL FEES | D20: =+C20*9% | E20: =+D20 | F20: =IF(D20>0," ",C20*18%) | I20: 0
A21: 3274 | B21: INCOME FROM E-STAMPING | I21: 0
A22: 3276 | B22: COMMISION ON PAN | D22: =+C22*9% | E22: =+D22 | F22: =IF(D22>0," ",C22*18%) | I22: 0
A23: 3280 | B23: INSURANCE PREMIUM | D23: =+C23*9% | E23: =+D23 | F23: =IF(D23>0," ",C23*18%) | I23: 0
A24: 3281 | B24: ATM CHARGES | D24: =+C24*9% | E24: =+D24 | F24: =IF(D24>0," ",C24*18%) | I24: 0
A25: 3285 | B25: COMMISION ON RTGS | D25: =+C25*9% | E25: =+D25 | F25: =IF(D25>0," ",C25*18%) | I25: 0
A26: 3286 | B26: COMMISION ON PMJJBY LIC | D26: =+C26*9% | E26: =+D26 | F26: =IF(D26>0," ",C26*18%) | I26: 0
A27: 3287 | B27: COMM. ON PMSBY NEW INDIA ASSURANCE | D27: =+C27*9% | E27: =+D27 | F27: =IF(D27>0," ",C27*18%) | I27: 0
A28: 3291 | B28: CIBIL CHARGES | D28: =+C28*9% | E28: =+D28 | F28: =IF(D28>0," ",C28*18%) | I28: 0
A29: 3296 | B29: RTGS/NEFT MANUAL CHARGES | D29: =+C29*9% | E29: =+D29 | F29: =IF(D29>0," ",C29*18%) | I29: 0
A30: 3297 | B30: ASBA FORM PRINT CHARGES | D30: =+C30*9% | E30: =+D30 | F30: =IF(D30>0," ",C30*18%) | I30: 0
A31: 3298 | B31: MANDATE HANDLING CHARGES | D31: =+C31*9% | E31: =+D31 | F31: =IF(D31>0," ",C31*18%) | I31: 0
A32: 3299 | B32: SI EXECUTION FAILED CHARGES | D32: =+C32*9% | E32: =+D32 | F32: =IF(D32>0," ",C32*18%) | I32: 0
A33: 3300 | B33: INCIDENTAL CHARGES | D33: =+C33*9% | E33: =+D33 | F33: 0 | I33: 0
A34: 3301 | B34: INOPERATIVE CHARGES | D34: =+C34*9% | E34: =+D34 | F34: =IF(D34>0," ",C34*18%) | I34: 0
A35: 3302 | B35: PO CANCEL CHARGES | D35: =+C35*9% | E35: =+D35 | F35: =IF(D35>0," ",C35*18%) | I35: 0
A36: 3305 | B36: A/C SHARE TRANSFER FEES | D36: =+C36*9% | E36: =+D36 | F36: =IF(D36>0," ",C36*18%) | I36: 0
A37: 3309 | B37: MIS. INCOME WITH GST | D37: =+C37*9% | E37: =+D37 | F37: =IF(D37>0," ",C37*18%) | I37: 0
A38: 3310 | B38: MIS. INCOME | D38: =+C38*9% | E38: =+D38 | F38: =IF(D38>0," ",C38*18%) | I38: 0
A39: 3311 | B39: I/W CHQ. RET. CHARGES | D39: =+C39*9% | E39: =+D39 | F39: =IF(D39>0," ",C39*18%) | I39: 0
A40: 3312 | B40: O/W CHQ. RET. CHARGES | D40: =+C40*9% | E40: =+D40 | F40: =IF(D40>0," ",C40*18%) | I40: 0
A41: 3313 | B41: ECS RETD. CHARGES | D41: =+C41*9% | E41: =+D41 | F41: =IF(D41>0," ",C41*18%) | I41: 0
A42: 3314 | B42: CHQ. BOOK ISSUE CHARGES | D42: =+C42*9% | E42: =+D42 | F42: =IF(D42>0," ",C42*18%) | I42: 0
A43: 3315 | B43: CHARGES ON GODOWNS | D43: =+C43*9% | E43: =+D43 | F43: 0 | I43: 0
A44: 3316 | B44: CASH CHARGES | D44: =+C44*9% | E44: =+D44 | F44: =IF(D44>0," ",C44*18%) | I44: 0
A45: 3317 | B45: THE P&T CHARGES FOR LC/BG | D45: =+C45*9% | E45: =+D45 | F45: =IF(D45>0," ",C45*18%) | I45: 0
A46: 3318 | B46: OBC POSTAGE CHARGES | D46: =+C46*9% | E46: =+D46 | F46: =IF(D46>0," ",C46*18%) | I46: 0
A47: 3320 | B47: RENT ON LOCKER | D47: =+C47*9% | E47: =+D47 | F47: =IF(D47>0," ",C47*18%) | I47: 0
A48: 3321 | B48: ADHOC LIMIT CHARGES | D48: =+C48*9% | E48: =+D48 | F48: =IF(D48>0," ",C48*18%) | I48: 0
A49: 3322 | B49: INCOME FROM SALE OF OLD NEWS PAPERS | D49: =+C49*9% | E49: =+D49 | I49: 0
A50: 3324 | B50: PENALTY ON OVERDUE LOCKER RENT | D50: =+C50*9% | E50: =+D50 | I50: 0
A51: 3325 | B51: MICR CHARGES | D51: =+C51*2.5% | E51: =+D51 | F51: =IF(D51>0," ",C51*18%) | I51: 0
A52: 3391 | B52: SMS CHARGES INCOME RECEIVED | D52: =+C52*9% | E52: =+D52 | F52: =IF(D52>0," ",C52*18%) | I52: 0
A53: 3359 | B53: COMMITMENT CHARGES | D53: =+C53*9% | E53: =+D53 | F53: =IF(D53>0," ",C53*18%) | I53: 0
A54: 3825 | B54: EXTERNAL AUDIT FEES | D54: =+C54*9% | E54: =+D54 | F54: =IF(D54>0," ",C54*18%) | I54: 0
A55: 3362 | B55: FORECLOSURE CHARGES | D55: =+C55*9% | E55: =+D55 | F55: =IF(D55>0," ",C55*18%) | I55: 0
A56: 3340 | B56: LOAN PROCESSING FEES | D56: =+C56*9% | E56: =+D56 | F56: =IF(D56>0," ",C56*18%) | I56: 0
A57: GL | I57: 0
A58: 1720 | B58: COMM. RECD. BUT NOT ACCRUED | D58: =+C58*9% | E58: =+D58 | F58: =IF(D58>0," ",C58*18%) | I58: 0
A59: 1836 | B59: RENT ON LOCKER RECEIVED BUT | D59: =+C59*9% | E59: =+D59 | F59: =IF(D59>0," ",C59*18%) | I59: 0
B60: NOT ACCRUED | I60: 0
B61: SALE OF ASSET ( CASH COUNTING MACHINE) | D61: =+C61*0.09 | E61: =+D61 | I61: 0
B62: TOTAL : | C62: =SUM(C9:C61) | D62: =SUM(D9:D61) | E62: =SUM(E9:E61) | F62: =SUM(F9:F61) | G62: =SUM(G9:G59) | H62: =SUM(H9:H59)
A63: RCM
A64: PL 3750 | B64: LAW CHARGES (EXCLUSIVE) | C64: 0 | D64: =+C64*9% | E64: =+D64 | F64: =IF(D64>0," ",C64*18%) | I64: 0
A65: PL 3751 | B65: INCIDENTAL LAW CHARGES (EXCLUSIVE) | C65: 0 | D65: =+C65*9% | E65: =+D65 | F65: =IF(D65>0," ",C65*18%) | G65: =+C62*0.09 | I65: 0
A66: SUMMARY
A68: (1) INCOME
A69: PARTICULARS | D69: GGST | E69: CGST | F69: IGST
G70: 45 | H70: =+G70/9%
A71: (1) INCOME AS PER LEDGERWISE CALCULATION | D71: =+D62 | E71: =+E62 | F71: =+F62 | G71: =6.75+6.75 | H71: =+G71/9%
A72: (2) REFUND GIVEN BUT GST REFUND NOT GIVEN | C72: =+G62 | D72: =+C72*0.09 | E72: =+C72*0.09 | F72: 0 | G72: =171.63+27.45 | H72: =+G72/9%
D73: =+D71+D72 | E73: =+E71+E72 | F73: 0
A74: (3) PAYABLE AS PER LEDGER | E74: =+D74 | F74: 0
A75: DIFFERENCE | D75: =+D73-D74 | E75: =+E73-E74 | F75: =IF(F71>F74,F71,F74) | G75: =+E75/0.09
A77: (2) INPUT TAX CREDIT
A78: PARTICULARS | D78: GL 8546 GGST | E78: GL 8547 CGST | F78: GL 8548 IGST
A81: CURRENT MONTH INPUT TAX CREDIT AVAILABLE | E81: =+D81 | F81: 0 | G81: =+D81/2 | H81: =+E81/2 | I81: =+F81/2
A82: LESS : CREDIT CANNOT BE UTILISED (BCUZ GST NO NOT AVAILABLE IN BILL) | D82: =C92 | E82: =D92 | F82: 0 | G82: =+D82/2 | H82: =+E82/2 | I82: =+F82/2
A83: ELIGIBLE CREDIT | D83: =+D81-D82 | E83: =+E81-E82 | F83: =+F81-F82 | G83: =+D83/2 | H83: =+E83/2 | I83: =+F83/2
B86: OUR GST NO. NOT REFLECTED ON CENVAT BILLS
B87: PARTY NAME | C87: GGST | D87: CGST | E87: IGST
B88: SHIV SHAKTI SWEETS & SNACKS | D88: =+C88 | E88: 0
B89: AIRTEL | C89: 0 | D89: =+C89 | E89: 0
B90: BSNL | D90: =+C90 | E90: 0
B91: BSNL | C91: 0 | D91: =+C91 | E91: 0
B92: TOTAL | C92: =+SUM(C88:C91) | D92: =+SUM(D88:D91) | E92: =+SUM(E88:E91)

Sheet LAW GARDEN
A1: NUTAN NAGARIK SAHAKARI BANK LTD (GUJARAT BRANCHES & HEAD OFFICE)
A3: BRANCH NAME : LAW GARDEN BRANCH
A4: BRANCH CODE:12
A5: =+'ODHAV '!$A$5
A7: CODE NO. | B7: PARTICULARS | D7: GGST | E7: CGST | F7: IGST
A8: PL
A9: 3303 | B9: DD CANCEL CHARGES | D9: =+C9*9% | E9: =+D9 | F9: =IF(D9>0," ",C9*18%)
A10: 3200 | B10: COMMISION ON BILLS | D10: =+C10*9% | E10: =+D10 | F10: =IF(D10>0," ",C10*18%)
A11: 3215 | B11: COMMISION ON PAYORDER | D11: =+C11*9% | E11: =+D11 | F11: =IF(D11>0," ",C11*18%)
A12: 3220 | B12: COMMISION ON U.B.D. | D12: =+C12*9% | E12: =+D12 | F12: =IF(D12>0," ",C12*18%)
A13: 3225 | B13: COMMISION I.B.C. | D13: =+C13*9% | E13: =+D13 | F13: =IF(D13>0," ",C13*18%)
A14: 3230 | B14: COMMISION ON GUARANTEE | D14: =+C14*9% | E14: =+D14 | F14: =IF(D14>0," ",C14*18%)
A15: 3235 | B15: COMMISION ON DEMAND DRAFT | D15: =+C15*9% | E15: =+D15 | F15: =IF(D15>0," ",C15*18%)
A16: 3240 | B16: COMMISION ON U.B.C. | D16: =+C16*9% | E16: =+D16 | F16: =IF(D16>0," ",C16*18%)
A17: 3245 | B17: COMMISION ON L.C. | D17: =+C17*9% | E17: =+D17 | F17: =IF(D17>0," ",C17*18%)
A18: 3250 | B18: COMMISSION ON GUARANTEE | D18: =+C18*9% | E18: =+D18 | F18: =IF(D18>0," ",C18*18%)
A19: 3270 | B19: PROCESSING CHARGE | D19: =+C19*9% | E19: =+D19
A20: 3271 | B20: RENEWAL FEES | D20: =+C20*9% | E20: =+D20
A21: 3274 | B21: INCOME FROM E-STAMPING | D21: =+C21*9% | E21: =+D21
A22: 3276 | B22: COMMISION ON PAN | D22: =+C22*9% | E22: =+D22 | F22: =IF(D22>0," ",C22*18%)
A23: 3280 | B23: INSURANCE PREMIUM | D23: =+C23*9% | E23: =+D23 | F23: =IF(D23>0," ",C23*18%)
A24: 3281 | B24: ATM CHARGES | D24: =+C24*9% | E24: =+D24 | F24: 0
A25: 3285 | B25: COMMISION ON RTGS | D25: =+C25*9% | E25: =+D25 | F25: =IF(D25>0," ",C25*18%)
A26: 3286 | B26: COMMISION ON PMJJBY LIC | D26: =+C26*9% | E26: =+D26 | F26: =IF(D26>0," ",C26*18%)
A27: 3287 | B27: COMM. ON PMSBY NEW INDIA ASSURANCE | D27: =+C27*9% | E27: =+D27 | F27: =IF(D27>0," ",C27*18%)
A28: 3291 | B28: CIBIL CHARGES | D28: =+C28*9% | E28: =+D28 | F28: =IF(D28>0," ",C28*18%)
A29: 3296 | B29: RTGS/NEFT MANUAL CHARGES | D29: =+C29*9% | E29: =+D29 | F29: =IF(D29>0," ",C29*18%)
A30: 3297 | B30: ASBA FORM PRINT CHARGES | D30: =+C30*9% | E30: =+D30 | F30: 0
A31: 3298 | B31: MANDATE HANDLING CHARGES | D31: =+C31*9% | E31: =+D31 | F31: =IF(D31>0," ",C31*18%)
A32: 3299 | B32: SI EXECUTION FAILED CHARGES | D32: =+C32*9% | E32: =+D32 | F32: =IF(D32>0," ",C32*18%)
A33: 3300 | B33: INCIDENTAL CHARGES | D33: =+C33*9% | E33: =+D33
A34: 3301 | B34: INOPERATIVE CHARGES | D34: =+C34*9% | E34: =+D34 | F34: =IF(D34>0," ",C34*18%)
A35: 3302 | B35: PO CANCEL CHARGES | D35: =+C35*9% | E35: =+D35 | F35: =IF(D35>0," ",C35*18%)
A36: 3305 | B36: A/C SHARE TRANSFER FEES | D36: =+C36*9% | E36: =+D36 | F36: =IF(D36>0," ",C36*18%)
A37: 3309 | B37: MIS. INCOME WITH GST | D37: =+C37*9% | E37: =+D37
A38: 3310 | B38: MIS. INCOME | D38: =+C38*9% | E38: =+D38 | F38: 0
A39: 3311 | B39: I/W CHQ. RET. CHARGES | D39: =+C39*9% | E39: =+D39 | F39: 0
A40: 3312 | B40: O/W CHQ. RET. CHARGES | D40: =+C40*9% | E40: =+D40 | F40: 0
A41: 3313 | B41: ECS RETD. CHARGES | D41: =+C41*9% | E41: =+D41 | F41: 0
A42: 3314 | B42: CHQ. BOOK ISSUE CHARGES | D42: =+C42*9% | E42: =+D42 | F42: 0
A43: 3315 | B43: CHARGES ON GODOWNS | D43: =+C43*9% | E43: =+D43 | F43: 0
A44: 3316 | B44: CASH CHARGES | D44: =+C44*9% | E44: =+D44 | F44: 0
A45: 3317 | B45: THE P&T CHARGES FOR LC/BG | D45: =+C45*9% | E45: =+D45 | F45: 0
A46: 3318 | B46: OBC POSTAGE CHARGES | D46: =+C46*9% | E46: =+D46 | F46: =IF(D46>0," ",C46*18%)
A47: 3320 | B47: RENT ON LOCKER | D47: =+C47*9% | E47: =+D47 | F47: 0
A48: 3321 | B48: ADHOC LIMIT CHARGES | D48: =+C48*9% | E48: =+D48 | F48: =IF(D48>0," ",C48*18%)
A49: 3322 | B49: INCOME FROM SALE OF OLD NEWS PAPERS | D49: =+C49*9% | E49: =+D49
A50: 3324 | B50: PENALTY ON OVERDUE LOCKER RENT | D50: =+C50*9% | E50: =+D50
A51: 3325 | B51: MICR CHARGES | D51: =+C51*9% | E51: =+D51 | F51: =IF(D51>0," ",C51*18%)
A52: 3391 | B52: SMS CHARGES INCOME RECEIVED | D52: =+C52*9% | E52: =+D52 | F52: 0
A53: 3359 | B53: COMMITMENT CHARGES | D53: =+C53*9% | E53: =+D53 | F53: 0
A54: 3825 | B54: EXTERNAL AUDIT FEES | D54: =+C54*9% | E54: =+D54
A55: 3362 | B55: FORECLOSURE CHARGES | D55: =+C55*9% | E55: =+D55
A56: 3340 | B56: LOAN PROCESSING FEES | D56: =+C56*9% | E56: =+D56 | F56: =IF(D56>0," ",C56*18%)
A57: GL | D57: 0
A58: 1720 | B58: COMM. RECD. BUT NOT ACCRUED | D58: =+C58*9% | E58: =+D58 | F58: 0
A59: 1836 | B59: RENT ON LOCKER RECEIVED BUT | D59: =+C59*9% | E59: =+D59 | F59: =IF(D59>0," ",C59*18%)
B60: NOT ACCRUED
B61: SALE OF ASSET ( CASH COUNTING MACHINE) | D61: =+C61*9% | E61: =+D61
B62: TOTAL : | C62: =SUM(C9:C61) | D62: =SUM(D9:D61) | E62: =SUM(E9:E61) | F62: =SUM(F9:F61) | G62: =+SUM(G9:G60) | H62: =+SUM(H9:H60)
A63: RCM
A64: PL 3750 | B64: LAW CHARGES (EXCLUSIVE) | D64: =+C64*9% | E64: =+D64 | F64: =IF(D64>0," ",C64*18%)
A65: PL 3751 | B65: INCIDENTAL LAW CHARGES (EXCLUSIVE) | C65: 0 | D65: =+C65*9% | E65: =+D65 | F65: =IF(D65>0," ",C65*18%) | G65: =+C62*0.09
A66: SUMMARY
A68: (1) INCOME
A69: PARTICULARS | D69: GGST | E69: CGST | F69: IGST
A71: (1) INCOME AS PER LEDGERWISE CALCULATION | D71: =+D62 | E71: =+E62 | F71: 0
A72: (2) REFUND GIVEN BUT GST REFUND NOT GIVEN | C72: =+G62 | D72: =+C72*0.09 | E72: =+C72*0.09 | F72: 0
D73: =SUM(D71:D72) | E73: =+D73 | F73: =SUM(F71:F72)
A74: (3) PAYABLE AS PER LEDGER | D74: 82565.32 | E74: =+D74 | F74: 0
A75: DIFFERENCE | D75: =+D73-D74 | E75: =+E73-E74 | F75: =IF(F71>F74,F71,F74) | G75: =+D75/9%
A77: (2) INPUT TAX CREDIT
A78: PARTICULARS | D78: GL 8546 GGST | E78: GL 8547 CGST | F78: GL 8548 IGST
A81: CURRENT MONTH INPUT TAX CREDIT AVAILABLE | D81: 2935.71 | E81: =+D81 | F81: 0 | G81: =+D81/2 | H81: =+E81/2 | I81: =+F81/2
A82: LESS : CREDIT CANNOT BE UTILISED (BCUZ GST NO NOT AVAILABLE IN BILL) | D82: =+C96 | E82: =D82 | F82: 0 | G82: =+D82/2 | H82: =+E82/2 | I82: =+F82/2
A83: ELIGIBLE CREDIT | D83: =+D81-D82 | E83: =+E81-E82 | F83: =+F81-F82 | G83: =+D83/2 | H83: =+E83/2 | I83: =+F83/2
B85: OUR GST NO. NOT REFLECTED ON CENVAT BILLS & BLOCKED CREDIT
C86: CGST | D86: SGST | E86: IGST
A87: GSTIN MISSING | B87: BSNL | C87: 0 | D87: =+C87 | E87: 0
B88: BSNL | C88: 0 | D88: =+C88
B89: DALIA MOTOR PVT.LTD. | C89: 0 | D89: =+C89
B90: DALIA MOTOR PVT.LTD. | C90: 0 | D90: =+C90
B91: DALIA MOTOR PVT.LTD. | C91: 0 | D91: =+C91
A92: GSTIN MISSING | B92: TRISHUL MARKETING | C92: 0 | D92: =+C92
B93: VENUS MOTORS | C93: 0 | D93: =+C93
B94: VENUS MOTORS | C94: 0 | D94: =+C94
A95: GSTIN MISSING | B95: UNION BANK OF INDIA | C95: 0 | D95: =+C95 | E95: 0
B96: TOTAL | C96: =+SUM(C87:C95) | D96: =+SUM(D87:D95) | E96: =+SUM(E87:E95) | G96: =+C96/2 | H96: =+D96/2

Sheet NEW CLOTH
A1: NUTAN NAGARIK SAHAKARI BANK LTD (GUJARAT BRANCHES & HEAD OFFICE)
A3: BRANCH NAME : NEW CLOTH MARKET BRANCH
A4: BRANCH NAME : 03
A5: =+'ODHAV '!$A$5
A7: CODE NO. | B7: PARTICULARS | D7: GGST | E7: CGST | F7: IGST | I7: LOCKER CLOSED CREDIT
A8: PL
A9: 3303 | B9: DD CANCEL CHARGES | D9: =+C9*9% | E9: =+D9 | F9: =IF(D9>0," ",C9*18%) | I9: 0
A10: 3200 | B10: COMMISION ON BILLS | D10: =+C10*9% | E10: =+D10 | F10: =IF(D10>0," ",C10*18%) | I10: 0
A11: 3215 | B11: COMMISION ON PAYORDER | D11: =+C11*9% | E11: =+D11 | I11: 0
A12: 3220 | B12: COMMISION ON U.B.D. | D12: =+C12*9% | E12: =+D12 | F12: =IF(D12>0," ",C12*18%) | I12: 0
A13: 3225 | B13: COMMISION I.B.C. | D13: =+C13*9% | E13: =+D13 | F13: =IF(D13>0," ",C13*18%) | I13: 0
A14: 3230 | B14: COMMISION ON GUARANTEE | D14: =+C14*9% | E14: =+D14 | F14: 0 | I14: 0
A15: 3235 | B15: COMMISION ON DEMAND DRAFT | D15: =+C15*9% | E15: =+D15 | F15: 0 | I15: 0
A16: 3240 | B16: COMMISION ON U.B.C. | D16: =+C16*9% | E16: =+D16 | F16: =IF(D16>0," ",C16*18%) | I16: 0
A17: 3245 | B17: COMMISION ON L.C. | D17: =+C17*9% | E17: =+D17 | F17: =IF(D17>0," ",C17*18%) | I17: 0
A18: 3250 | B18: COMMISSION ON GUARANTEE | D18: =+C18*9% | E18: =+D18 | F18: =IF(D18>0," ",C18*18%) | I18: 0
A19: 3270 | B19: PROCESSING CHARGE | D19: =+C19*9% | E19: =+D19 | F19: 0 | I19: 0
A20: 3271 | B20: RENEWAL FEES | D20: =+C20*9% | E20: =+D20 | I20: 0
A21: 3274 | B21: INCOME FROM E-STAMPING | D21: =+C21*9% | E21: =+D21 | I21: 0
A22: 3276 | B22: COMMISION ON PAN | D22: =+C22*9% | E22: =+D22 | F22: =IF(D22>0," ",C22*18%) | I22: 0
A23: 3280 | B23: INSURANCE PREMIUM | D23: =+C23*9% | E23: =+D23 | F23: =IF(D23>0," ",C23*18%) | I23: 0
A24: 3281 | B24: ATM CHARGES | D24: =+C24*9% | E24: =+D24 | I24: 0
A25: 3285 | B25: COMMISION ON RTGS | D25: =+C25*9% | E25: =+D25 | I25: 0
A26: 3286 | B26: COMMISION ON PMJJBY LIC | D26: =+C26*9% | E26: =+D26 | I26: 0
A27: 3287 | B27: COMM. ON PMSBY NEW INDIA ASSURANCE | D27: =+C27*9% | E27: =+D27 | F27: =IF(D27>0," ",C27*18%) | I27: 0
A28: 3291 | B28: CIBIL CHARGES | D28: =+C28*9% | E28: =+D28 | F28: =IF(D28>0," ",C28*18%) | I28: 0
A29: 3296 | B29: RTGS/NEFT MANUAL CHARGES | D29: =+C29*9% | E29: =+D29 | F29: =IF(D29>0," ",C29*18%) | I29: 0
A30: 3297 | B30: ASBA FORM PRINT CHARGES | D30: =+C30*9% | E30: =+D30 | F30: =IF(D30>0," ",C30*18%) | I30: 0
A31: 3298 | B31: MANDATE HANDLING CHARGES | D31: =+C31*9% | E31: =+D31 | F31: =IF(D31>0," ",C31*18%) | I31: 0
A32: 3299 | B32: SI EXECUTION FAILED CHARGES | D32: =+C32*9% | E32: =+D32 | F32: =IF(D32>0," ",C32*18%) | I32: 0
A33: 3300 | B33: INCIDENTAL CHARGES | D33: =+C33*9% | E33: =+D33 | F33: 0 | I33: 0
A34: 3301 | B34: INOPERATIVE CHARGES | D34: =+C34*9% | E34: =+D34 | F34: =IF(D34>0," ",C34*18%) | I34: 0
A35: 3302 | B35: PO CANCEL CHARGES | D35: =+C35*9% | E35: =+D35 | F35: =IF(D35>0," ",C35*18%) | I35: 0
A36: 3305 | B36: A/C SHARE TRANSFER FEES | D36: =+C36*9% | E36: =+D36 | F36: =IF(D36>0," ",C36*18%) | I36: 0
A37: 3309 | B37: MIS. INCOME WITH GST | D37: =+C37*9% | E37: =+D37 | F37: =IF(D37>0," ",C37*18%) | I37: 0
A38: 3310 | B38: MIS. INCOME | D38: =+C38*9% | E38: =+D38 | F38: =IF(D38>0," ",C38*18%) | I38: 0
A39: 3311 | B39: I/W CHQ. RET. CHARGES | D39: =+C39*9% | E39: =+D39 | F39: =IF(D39>0," ",C39*18%) | I39: 0
A40: 3312 | B40: O/W CHQ. RET. CHARGES | D40: =+C40*9% | E40: =+D40 | F40: =IF(D40>0," ",C40*18%) | I40: 0
A41: 3313 | B41: ECS RETD. CHARGES | D41: =+C41*9% | E41: =+D41 | F41: =IF(D41>0," ",C41*18%) | I41: 0
A42: 3314 | B42: CHQ. BOOK ISSUE CHARGES | D42: =+C42*9% | E42: =+D42 | F42: =IF(D42>0," ",C42*18%) | I42: 0
A43: 3315 | B43: CHARGES ON GODOWNS | D43: =+C43*9% | E43: =+D43 | F43: 0 | I43: 0
A44: 3316 | B44: CASH CHARGES | D44: =+C44*9% | E44: =+D44 | F44: =IF(D44>0," ",C44*18%) | I44: 0
A45: 3317 | B45: THE P&T CHARGES FOR LC/BG | D45: =+C45*9% | E45: =+D45 | F45: =IF(D45>0," ",C45*18%) | I45: 0
A46: 3318 | B46: OBC POSTAGE CHARGES | D46: =+C46*9% | E46: =+D46 | F46: =IF(D46>0," ",C46*18%) | I46: 0
A47: 3320 | B47: RENT ON LOCKER | D47: =+C47*9% | E47: =+D47 | F47: =IF(D47>0," ",C47*18%) | I47: 0
A48: 3321 | B48: ADHOC LIMIT CHARGES | D48: =+C48*9% | E48: =+D48 | F48: =IF(D48>0," ",C48*18%) | I48: 0
A49: 3322 | B49: INCOME FROM SALE OF OLD NEWS PAPERS | D49: =+C49*9% | E49: =+D49 | I49: 0
A50: 3324 | B50: PENALTY ON OVERDUE LOCKER RENT | D50: =+C50*9% | E50: =+D50 | I50: 0
A51: 3325 | B51: MICR CHARGES | D51: =+C51*2.5% | E51: =+D51 | F51: =IF(D51>0," ",C51*18%) | I51: 0
A52: 3391 | B52: SMS CHARGES INCOME RECEIVED | D52: =+C52*9% | E52: =+D52 | I52: 0
A53: 3359 | B53: COMMITMENT CHARGES | D53: =+C53*9% | E53: =+D53 | I53: 0
A54: 3825 | B54: EXTERNAL AUDIT FEES | D54: =+C54*9% | E54: =+D54 | I54: 0
A55: 3362 | B55: FORECLOSURE CHARGES | D55: =+C55*9% | E55: =+D55 | I55: 0
A56: 3340 | B56: LOAN PROCESSING FEES | D56: =+C56*9% | E56: =+D56 | F56: =IF(D56>0," ",C56*18%) | I56: 0
A57: GL | I57: 0
A58: 1720 | B58: COMM. RECD. BUT NOT ACCRUED | D58: =+C58*9% | E58: =+D58 | F58: 0 | I58: 0
A59: 1836 | B59: RENT ON LOCKER RECEIVED BUT | D59: =+C59*9% | E59: =+D59 | F59: =IF(D59>0," ",C59*18%) | I59: 0
B60: NOT ACCRUED | I60: 0
B61: SALE OF ASSET ( CASH COUNTING MACHINE) | D61: =+C61*9% | E61: =+D61 | I61: 0
B62: TOTAL : | C62: =SUM(C9:C61) | D62: =SUM(D9:D61) | E62: =SUM(E9:E61) | F62: =SUM(F9:F61) | G62: =SUM(G9:G59) | H62: =SUM(H9:H59) | I62: =SUM(I9:I59)
A63: RCM
A64: PL 3750 | B64: LAW CHARGES (EXCLUSIVE) | C64: 0 | D64: =+C64*9% | E64: =+D64 | F64: =IF(D64>0," ",C64*18%) | K64: .
A65: PL 3751 | B65: INCIDENTAL LAW CHARGES (EXCLUSIVE) | D65: =+C65*9% | E65: =+D65 | F65: =IF(D65>0," ",C65*18%) | G65: =+C62*0.09
A66: SUMMARY
A68: (1) INCOME
A69: PARTICULARS | D69: GGST | E69: CGST | F69: IGST
A71: (1) INCOME AS PER LEDGERWISE CALCULATION | D71: =+D62 | E71: =+E62 | F71: =+F62
A72: (2) REFUND GIVEN BUT GST REFUND NOT GIVEN | C72: =G62 | D72: =+C72*0.09 | E72: =+C72*0.09 | F72: 0
D73: =+D71+D72 | E73: =+E71+E72 | F73: =+F71+F72
A74: (2) PAYABLE AS PER LEDGER | E74: =+D74 | F74: 0
A75: DIFFERENCE | D75: =+D73-D74 | E75: =+E73-E74 | F75: =+F73-F74 | G75: =+E75/9%
A77: (2) INPUT TAX CREDIT
A78: PARTICULARS | D78: GL 8546 GGST | E78: GL 8547 CGST | F78: GL 8548 IGST
A81: CURRENT MONTH INPUT TAX CREDIT AVAILABLE | E81: =+D81 | F81: 0 | G81: =+D81/2 | H81: =+E81/2 | I81: =+F81/2
A82: LESS : CREDIT CANNOT BE UTILISED (BCUZ GST NO NOT AVAILABLE IN BILL) | D82: =+C95 | E82: =+D82 | F82: 0 | G82: =+D82/2 | H82: =+E82/2 | I82: =+F82/2
A83: ELIGIBLE CREDIT | D83: =SUM(D81-D82) | E83: =SUM(E81-E82) | F83: 0 | G83: =+D83/2 | H83: =+E83/2 | I83: =+F83/2
B86: OUR GST NO. NOT REFLECTED ON GST BILLS
B87: PARTY NAME | C87: CGST | D87: SGST | E87: IGST
B88: BSNL | D88: =+C88 | E88: 0
B89: BSNL | C89: 0 | D89: =+C89 | E89: 0
B90: BSNL | C90: 0 | D90: =+C90 | E90: 0
B91: BSNL | C91: 0 | D91: =+C91 | E91: 0
B92: BSNL | C92: 0 | D92: =+C92 | E92: 0
B93: KRISHNA IMPEX | C93: 0 | D93: =+C93 | E93: 0
B94: ROHAN AGENCY | C94: 0 | D94: =+C94 | E94: 0
C95: =SUM(C88:C94) | D95: =SUM(D88:D94) | E95: =SUM(E88:E94)

Sheet BAPUNAGAR
A1: NUTAN NAGARIK SAHAKARI BANK LTD (GUJARAT BRANCHES & HEAD OFFICE)
A3: BRANCH NAME : BAPUNAGAR BRANCH
A4: BRANCH CODE: 07
A5: =+'ODHAV '!$A$5
A7: CODE NO. | B7: PARTICULARS | D7: GGST | E7: CGST | F7: IGST | I7: LOCKER CLOSED CREDIT
A8: PL
A9: 3303 | B9: DD CANCEL CHARGES | D9: =+C9*9% | E9: =+D9 | F9: =IF(D9>0," ",C9*18%) | I9: 0
A10: 3200 | B10: COMMISION ON BILLS | D10: =+C10*9% | E10: =+D10 | F10: =IF(D10>0," ",C10*18%) | I10: 0
A11: 3215 | B11: COMMISION ON PAYORDER | D11: =+C11*9% | E11: =+D11 | F11: =IF(D11>0," ",C11*18%) | I11: 0
A12: 3220 | B12: COMMISION ON U.B.D. | D12: =+C12*9% | E12: =+D12 | F12: =IF(D12>0," ",C12*18%) | I12: 0
A13: 3225 | B13: COMMISION I.B.C. | D13: =+C13*9% | E13: =+D13 | F13: =IF(D13>0," ",C13*18%) | I13: 0
A14: 3230 | B14: COMMISION ON GUARANTEE | D14: =+C14*9% | E14: =+D14 | F14: =IF(D14>0," ",C14*18%) | I14: 0
A15: 3235 | B15: COMMISION ON DEMAND DRAFT | D15: =+C15*9% | E15: =+D15 | F15: =IF(D15>0," ",C15*18%) | I15: 0
A16: 3240 | B16: COMMISION ON U.B.C. | D16: =+C16*9% | E16: =+D16 | F16: =IF(D16>0," ",C16*18%) | I16: 0
A17: 3245 | B17: COMMISION ON L.C. | D17: =+C17*9% | E17: =+D17 | F17: =IF(D17>0," ",C17*18%) | I17: 0
A18: 3250 | B18: COMMISSION ON GUARANTEE | D18: =+C18*9% | E18: =+D18 | F18: =IF(D18>0," ",C18*18%) | I18: 0
A19: 3270 | B19: PROCESSING CHARGE | D19: =+C19*9% | E19: =+D19 | F19: =IF(D19>0," ",C19*18%) | I19: 0
A20: 3271 | B20: RENEWAL FEES | D20: =+C20*9% | E20: =+D20 | F20: =IF(D20>0," ",C20*18%) | I20: 0
A21: 3274 | B21: INCOME FROM E-STAMPING | I21: 0
A22: 3276 | B22: COMMISION ON PAN | D22: =+C22*9% | E22: =+D22 | F22: =IF(D22>0," ",C22*18%) | I22: 0
A23: 3280 | B23: INSURANCE PREMIUM | D23: =+C23*9% | E23: =+D23 | F23: =IF(D23>0," ",C23*18%) | I23: 0
A24: 3281 | B24: ATM CHARGES | D24: =+C24*9% | E24: =+D24 | F24: =IF(D24>0," ",C24*18%) | I24: 0
A25: 3285 | B25: COMMISION ON RTGS | D25: =+C25*9% | E25: =+D25 | F25: =IF(D25>0," ",C25*18%) | I25: 0
A26: 3286 | B26: COMMISION ON PMJJBY LIC | D26: =+C26*9% | E26: =+D26 | F26: =IF(D26>0," ",C26*18%) | I26: 0
A27: 3287 | B27: COMM. ON PMSBY NEW INDIA ASSURANCE | D27: =+C27*9% | E27: =+D27 | F27: =IF(D27>0," ",C27*18%) | I27: 0
A28: 3291 | B28: CIBIL CHARGES | D28: =+C28*9% | E28: =+D28 | F28: =IF(D28>0," ",C28*18%) | I28: 0
A29: 3296 | B29: RTGS/NEFT MANUAL CHARGES | D29: =+C29*9% | E29: =+D29 | F29: =IF(D29>0," ",C29*18%) | I29: 0
A30: 3297 | B30: ASBA FORM PRINT CHARGES | D30: =+C30*9% | E30: =+D30 | F30: =IF(D30>0," ",C30*18%) | I30: 0
A31: 3298 | B31: MANDATE HANDLING CHARGES | D31: =+C31*9% | E31: =+D31 | F31: =IF(D31>0," ",C31*18%) | I31: 0
A32: 3299 | B32: SI EXECUTION FAILED CHARGES | D32: =+C32*9% | E32: =+D32 | F32: =IF(D32>0," ",C32*18%) | I32: 0
A33: 3300 | B33: INCIDENTAL CHARGES | D33: =+C33*9% | E33: =+D33 | F33: 0 | I33: 0
A34: 3301 | B34: INOPERATIVE CHARGES | D34: =+C34*9% | E34: =+D34 | F34: =IF(D34>0," ",C34*18%) | I34: 0
A35: 3302 | B35: PO CANCEL CHARGES | D35: =+C35*9% | E35: =+D35 | F35: =IF(D35>0," ",C35*18%) | I35: 0
A36: 3305 | B36: A/C SHARE TRANSFER FEES | D36: =+C36*9% | E36: =+D36 | F36: =IF(D36>0," ",C36*18%) | I36: 0
A37: 3309 | B37: MIS. INCOME WITH GST | D37: =+C37*9% | E37: =+D37 | F37: =IF(D37>0," ",C37*18%) | I37: 0
A38: 3310 | B38: MIS. INCOME | D38: =+C38*9% | E38: =+D38 | F38: =IF(D38>0," ",C38*18%) | I38: 0
A39: 3311 | B39: I/W CHQ. RET. CHARGES | D39: =+C39*9% | E39: =+D39 | F39: =IF(D39>0," ",C39*18%) | I39: 0
A40: 3312 | B40: O/W CHQ. RET. CHARGES | D40: =+C40*9% | E40: =+D40 | F40: =IF(D40>0," ",C40*18%) | I40: 0
A41: 3313 | B41: ECS RETD. CHARGES | D41: =+C41*9% | E41: =+D41 | F41: =IF(D41>0," ",C41*18%) | I41: 0
A42: 3314 | B42: CHQ. BOOK ISSUE CHARGES | D42: =+C42*9% | E42: =+D42 | F42: =IF(D42>0," ",C42*18%) | I42: 0
A43: 3315 | B43: CHARGES ON GODOWNS | D43: =+C43*9% | E43: =+D43 | F43: =IF(D43>0," ",C43*18%) | I43: 0
A44: 3316 | B44: CASH CHARGES | D44: =+C44*9% | E44: =+D44 | F44: =IF(D44>0," ",C44*18%) | I44: 0
A45: 3317 | B45: THE P&T CHARGES FOR LC/BG | D45: =+C45*9% | E45: =+D45 | F45: =IF(D45>0," ",C45*18%) | I45: 0
A46: 3318 | B46: OBC POSTAGE CHARGES | D46: =+C46*9% | E46: =+D46 | F46: =IF(D46>0," ",C46*18%) | I46: 0
A47: 3320 | B47: RENT ON LOCKER | D47: =+C47*9% | E47: =+D47 | F47: =IF(D47>0," ",C47*18%) | I47: 0
A48: 3321 | B48: ADHOC LIMIT CHARGES | D48: =+C48*9% | E48: =+D48 | F48: =IF(D48>0," ",C48*18%) | I48: 0
A49: 3322 | B49: INCOME FROM SALE OF OLD NEWS PAPERS | D49: =+C49*5% | E49: =+D49 | F49: =IF(D49>0," ",C49*18%) | I49: 0
A50: 3324 | B50: PENALTY ON OVERDUE LOCKER RENT | D50: =+C50*5% | E50: =+D50 | F50: =IF(D50>0," ",C50*18%) | I50: 0
A51: 3325 | B51: MICR CHARGES | D51: =+C51*2.5% | E51: =+D51 | F51: =IF(D51>0," ",C51*18%) | I51: 0
A52: 3391 | B52: SMS CHARGES INCOME RECEIVED | D52: =+C52*9% | E52: =+D52 | F52: =IF(D52>0," ",C52*18%) | I52: 0
A53: 3359 | B53: COMMITMENT CHARGES | D53: =+C53*9% | E53: =+D53 | F53: 0 | I53: 0
A54: 3825 | B54: EXTERNAL AUDIT FEES | D54: =+C54*9% | E54: =+D54 | I54: 0
A55: 3362 | B55: FORECLOSURE CHARGES | I55: 0
A56: 3340 | B56: LOAN PROCESSING FEES | D56: =+C56*9% | E56: =+D56 | F56: =IF(D56>0," ",C56*18%) | I56: 0
A57: GL | I57: 0
A58: 1720 | B58: COMM. RECD. BUT NOT ACCRUED | D58: =+C58*9% | E58: =+D58 | F58: =IF(D58>0," ",C58*18%) | I58: 0
A59: 1836 | B59: RENT ON LOCKER RECEIVED BUT | D59: =+C59*9% | E59: =+D59 | F59: =IF(D59>0," ",C59*18%) | I59: 0
B60: NOT ACCRUED | I60: 0
B61: SALE OF ASSET ( CASH COUNTING MACHINE) | D61: =+C61*9% | E61: =+D61 | I61: 0
B62: TOTAL : | C62: =SUM(C9:C61) | D62: =SUM(D9:D61) | E62: =SUM(E9:E61) | F62: =SUM(F9:F61) | G62: =SUM(G9:G59) | H62: =SUM(H9:H59) | K62: =3853.29-D62
A63: RCM
A64: PL 3750 | B64: LAW CHARGES (EXCLUSIVE) | C64: 0 | D64: =+C64*9% | E64: =+D64 | F64: =IF(D64>0," ",C64*18%)
A65: PL 3751 | B65: INCIDENTAL LAW CHARGES (EXCLUSIVE) | C65: 0 | D65: =+C65*9% | E65: =+D65 | F65: =IF(D65>0," ",C65*18%) | G65: =+C62*0.09
A66: SUMMARY
A68: (1) INCOME
A69: PARTICULARS | D69: GGST | E69: CGST | F69: IGST
A71: (1) INCOME AS PER LEDGERWISE CALCULATION | D71: =+D62 | E71: =+E62 | F71: =+F62
A72: (2) REFUND GIVEN BUT GST REFUND NOT GIVEN | C72: =G62 | D72: =+C72*9% | E72: =+D72 | F72: 0
D73: =+D71+D72 | E73: =+E71+E72 | F73: 0
A74: (3) PAYABLE AS PER LEDGER | E74: =+D74 | F74: 0
A75: DIFFERENCE | D75: =D73-D74 | E75: =+E73-E74 | F75: =IF(F71>F74,F71,F74) | G75: =+E75/9%
A77: (2) INPUT TAX CREDIT
A78: PARTICULARS | D78: GL 8546 GGST | E78: GL 8547 CGST | F78: GL 8548 IGST
A81: CURRENT MONTH INPUT TAX CREDIT AVAILABLE | E81: =+D81 | F81: 0 | G81: =+D81/2 | H81: =+E81/2 | I81: =+F81/2
A82: LESS : CREDIT CANNOT BE UTILISED (BCUZ GST NO NOT AVAILABLE IN BILL) | D82: =+C91 | E82: =D82 | F82: 0 | G82: =+D82/2 | H82: =+E82/2 | I82: =+F82/2
A83: ELIGIBLE CREDIT | D83: =+D81-D82 | E83: =+E81-E82 | F83: =+F81-F82 | G83: =+D83/2 | H83: =+E83/2 | I83: =+F83/2
B86: OUR GST NO. NOT REFLECTED ON CENVAT BILLS
B87: PARTY | C87: CGST | D87: SGST | E87: IGST
B88: BSNL | C88: 0 | D88: =+C88 | E88: 0
B89: ROHAN AGENCY | C89: 0 | D89: =+C89
B90: MAA BEVERAGES | C90: 0 | D90: =+C90
B91: TOTAL | C91: =SUM(C88:C90) | D91: =SUM(D88:D90) | E91: =+SUM(E88:E88)

Sheet BOPAL
A1: NUTAN NAGARIK SAHAKARI BANK LTD (GUJARAT BRANCHES & HEAD OFFICE)
A3: BRANCH NAME : BOPAL BRANCH
A4: BRANCH CODE: 22
A5: =+'ODHAV '!$A$5
A7: CODE NO. | B7: PARTICULARS | D7: GGST | E7: CGST | F7: IGST | I7: LOCKER CLOSED CREDIT
A8: PL
A9: 3303 | B9: DD CANCEL CHARGES | D9: =+C9*9% | E9: =+D9 | F9: 0 | I9: 0
A10: 3200 | B10: COMMISION ON BILLS | D10: =+C10*9% | E10: =+D10 | F10: =IF(D10>0," ",C10*18%) | I10: 0
A11: 3215 | B11: COMMISION ON PAYORDER | D11: =+C11*9% | E11: =+D11 | F11: =IF(D11>0," ",C11*18%) | I11: 0
A12: 3220 | B12: COMMISION ON U.B.D. | D12: =+C12*9% | E12: =+D12 | F12: =IF(D12>0," ",C12*18%) | I12: 0
A13: 3225 | B13: COMMISION I.B.C. | D13: =+C13*9% | E13: =+D13 | F13: =IF(D13>0," ",C13*18%) | I13: 0
A14: 3230 | B14: COMMISION ON GUARANTEE | D14: =+C14*9% | E14: =+D14 | F14: =IF(D14>0," ",C14*18%) | I14: 0
A15: 3235 | B15: COMMISION ON DEMAND DRAFT | D15: =+C15*9% | E15: =+D15 | F15: =IF(D15>0," ",C15*18%) | I15: 0
A16: 3240 | B16: COMMISION ON U.B.C. | D16: =+C16*9% | E16: =+D16 | F16: =IF(D16>0," ",C16*18%) | I16: 0
A17: 3245 | B17: COMMISION ON L.C. | D17: =+C17*9% | E17: =+D17 | F17: =IF(D17>0," ",C17*18%) | I17: 0
A18: 3250 | B18: COMMISSION ON GUARANTEE | D18: =+C18*9% | E18: =+D18 | F18: =IF(D18>0," ",C18*18%) | I18: 0
A19: 3270 | B19: PROCESSING CHARGE | D19: =+C19*9% | E19: =+D19 | F19: 0 | I19: 0
A20: 3271 | B20: RENEWAL FEES | D20: =+C20*9% | E20: =+D20 | I20: 0
A21: 3274 | B21: INCOME FROM E-STAMPING | I21: 0
A22: 3276 | B22: COMMISION ON PAN | D22: =+C22*9% | E22: =+D22 | F22: =IF(D22>0," ",C22*18%) | I22: 0
A23: 3280 | B23: INSURANCE PREMIUM | D23: =+C23*9% | E23: =+D23 | F23: =IF(D23>0," ",C23*18%) | I23: 0
A24: 3281 | B24: ATM CHARGES | D24: =+C24*9% | E24: =+D24 | F24: =IF(D24>0," ",C24*18%) | I24: 0
A25: 3285 | B25: COMMISION ON RTGS | D25: =+C25*9% | E25: =+D25 | F25: =IF(D25>0," ",C25*18%) | I25: 0
A26: 3286 | B26: COMMISION ON PMJJBY LIC | D26: =+C26*9% | E26: =+D26 | F26: =IF(D26>0," ",C26*18%) | I26: 0
A27: 3287 | B27: COMM. ON PMSBY NEW INDIA ASSURANCE | D27: =+C27*9% | E27: =+D27 | F27: =IF(D27>0," ",C27*18%) | I27: 0
A28: 3291 | B28: CIBIL CHARGES | D28: =+C28*9% | E28: =+D28 | F28: =IF(D28>0," ",C28*18%) | I28: 0
A29: 3296 | B29: RTGS/NEFT MANUAL CHARGES | D29: =+C29*9% | E29: =+D29 | F29: =IF(D29>0," ",C29*18%) | I29: 0
A30: 3297 | B30: ASBA FORM PRINT CHARGES | D30: =+C30*9% | E30: =+D30 | F30: =IF(D30>0," ",C30*18%) | I30: 0
A31: 3298 | B31: MANDATE HANDLING CHARGES | D31: =+C31*9% | E31: =+D31 | F31: =IF(D31>0," ",C31*18%) | I31: 0
A32: 3299 | B32: SI EXECUTION FAILED CHARGES | D32: =+C32*9% | E32: =+D32 | F32: =IF(D32>0," ",C32*18%) | I32: 0
A33: 3300 | B33: INCIDENTAL CHARGES | D33: =+C33*9% | E33: =+D33 | F33: =IF(D33>0," ",C33*18%) | I33: 0
A34: 3301 | B34: INOPERATIVE CHARGES | D34: =+C34*9% | E34: =+D34 | F34: =IF(D34>0," ",C34*18%) | I34: 0
A35: 3302 | B35: PO CANCEL CHARGES | D35: =+C35*9% | E35: =+D35 | F35: =IF(D35>0," ",C35*18%) | I35: 0
A36: 3305 | B36: A/C SHARE TRANSFER FEES | D36: =+C36*9% | E36: =+D36 | F36: =IF(D36>0," ",C36*18%) | I36: 0
A37: 3309 | B37: MIS. INCOME WITH GST | D37: =+C37*9% | E37: =+D37 | F37: =IF(D37>0," ",C37*18%) | I37: 0
A38: 3310 | B38: MIS. INCOME | D38: =+C38*9% | E38: =+D38 | F38: 0 | I38: 0
A39: 3311 | B39: I/W CHQ. RET. CHARGES | D39: =+C39*9% | E39: =+D39 | F39: =IF(D39>0," ",C39*18%) | I39: 0
A40: 3312 | B40: O/W CHQ. RET. CHARGES | D40: =+C40*9% | E40: =+D40 | F40: =IF(D40>0," ",C40*18%) | I40: 0
A41: 3313 | B41: ECS RETD. CHARGES | D41: =+C41*9% | E41: =+D41 | F41: =IF(D41>0," ",C41*18%) | I41: 0
A42: 3314 | B42: CHQ. BOOK ISSUE CHARGES | D42: =+C42*9% | E42: =+D42 | F42: =IF(D42>0," ",C42*18%) | I42: 0
A43: 3315 | B43: CHARGES ON GODOWNS | D43: =+C43*9% | E43: =+D43 | F43: =IF(D43>0," ",C43*18%) | I43: 0
A44: 3316 | B44: CASH CHARGES | D44: =+C44*9% | E44: =+D44 | F44: =IF(D44>0," ",C44*18%) | I44: 0
A45: 3317 | B45: THE P&T CHARGES FOR LC/BG | D45: =+C45*9% | E45: =+D45 | F45: =IF(D45>0," ",C45*18%) | I45: 0
A46: 3318 | B46: OBC POSTAGE CHARGES | D46: =+C46*9% | E46: =+D46 | F46: =IF(D46>0," ",C46*18%) | I46: 0
A47: 3320 | B47: RENT ON LOCKER | D47: =+C47*9% | E47: =+D47 | F47: =IF(D47>0," ",C47*18%) | I47: 0
A48: 3321 | B48: ADHOC LIMIT CHARGES | D48: =+C48*9% | E48: =+D48 | F48: =IF(D48>0," ",C48*18%) | I48: 0
A49: 3322 | B49: INCOME FROM SALE OF OLD NEWS PAPERS | D49: =+C49*5% | E49: =+D49 | I49: 0
A50: 3324 | B50: PENALTY ON OVERDUE LOCKER RENT | D50: =+C50*9% | E50: =+D50 | I50: 0
A51: 3325 | B51: MICR CLEARING CHARGES | D51: =+C51*9% | E51: =+D51 | I51: 0
A52: 3380 | B52: STATEMENT CHARGES | D52: =+C52*9% | E52: =+D52 | I52: 0
A53: 3391 | B53: SMS CHARGES INCOME RECEIVED | D53: =+C53*9% | E53: =+D53 | F53: =IF(D53>0," ",C53*18%) | I53: 0
A54: 3359 | B54: COMMITMENT CHARGES | D54: =+C54*9% | E54: =+D54 | F54: 0 | I54: 0
A55: 3825 | B55: EXTERNAL AUDIT FEES | D55: =+C55*9% | E55: =+D55 | I55: 0
A56: 3362 | B56: FORECLOSURE CHARGES | D56: =+C56*9% | E56: =+D56 | I56: 0
A57: 3340 | B57: LOAN PROCESSING FEES | D57: =+C57*9% | E57: =+D57 | F57: =IF(D57>0," ",C57*18%) | I57: 0
A58: GL | D58: =+C58*9% | E58: =+D58 | I58: 0
A59: 1720 | B59: COMM. RECD. BUT NOT ACCRUED | D59: =+C59*9% | E59: =+D59 | I59: 0
A60: 1836 | B60: RENT ON LOCKER RECEIVED BUT | D60: =+C60*9% | E60: =+D60 | F60: =IF(D60>0," ",C60*18%) | I60: 0
B61: NOT ACCRUED | D61: =+C61*9% | E61: =+D61 | I61: 0
B62: SALE OF ASSET ( CASH COUNTING MACHINE) | D62: =+C62*9% | E62: =+D62 | I62: 0
B63: TOTAL : | C63: =SUM(C9:C62) | D63: =SUM(D9:D62) | E63: =SUM(E9:E62) | F63: =SUM(F9:F62) | G63: =+SUM(G9:G61) | H63: =+SUM(H9:H61) | I63: =+SUM(I9:I61)
A64: RCM
A65: PL 3750 | B65: LAW CHARGES (EXCLUSIVE) | C65: 0 | D65: =+C65*9% | E65: =+D65 | F65: =IF(D65>0," ",C65*18%)
A66: PL 3751 | B66: INCIDENTAL LAW CHARGES (EXCLUSIVE) | C66: 0 | D66: =+C66*9% | E66: =+D66 | F66: =IF(D66>0," ",C66*18%) | G66: =+C63*0.09 | H66: =+C63*0.09
A67: SUMMARY
G68: =C59*9%
A69: (1) INCOME
A70: PARTICULARS | D70: GGST | E70: CGST | F70: IGST
A72: (1) INCOME AS PER LEDGERWISE CALCULATION | D72: =+D63 | E72: =+E63 | F72: 0
A73: (2) REFUND GIVEN BUT GST REFUND NOT GIVEN | C73: =G63 | D73: =+C73*9% | E73: =+D73 | F73: 0
D74: =+D72+D73 | E74: =+E72+E73 | F74: 0
A75: (3) PAYABLE AS PER LEDGER | E75: =+D75 | F75: 0
A76: DIFFERENCE | D76: =D74-D75 | E76: =+E74-E75 | F76: =IF(F72>F75,F72,F75) | G76: =+D76/9%
A78: (2) INPUT TAX CREDIT
A79: PARTICULARS | D79: GL 8546 GGST | E79: GL 8547 CGST | F79: GL 8548 IGST
A82: CURRENT MONTH INPUT TAX CREDIT AVAILABLE | E82: =+D82 | F82: 0 | G82: =+E82/2 | H82: =+G82 | I82: =+F82/2
A83: LESS : CREDIT CANNOT BE UTILISED (BCUZ GST NO NOT AVAILABLE IN BILL) | D83: =+C93 | E83: =D83 | F83: =+E93 | G83: =+E83/2 | H83: =+G83 | I83: =+F83/2
A84: ELIGIBLE CREDIT | D84: =+D82-D83 | E84: =+E82-E83 | F84: =+F82-F83 | G84: =+E84/2 | H84: =+G84 | I84: =+F84/2
B88: OUR GST NO. NOT REFLECTED ON CENVAT BILLS
B89: PARTY NAME | C89: CGST | D89: SGST | E89: IGST
B90: BSNL | D90: =+C90 | E90: 0
B91: ROHAN AGENCY | C91: 0 | D91: =+C91
B92: ORCHID CENTER COMM CO-OP SER SOC LTO | C92: 0 | D92: =+C92 | E92: 0
C93: =+SUM(C90:C92) | D93: =+SUM(D90:D92) | E93: =+SUM(E90:E92) | G93: =+C93/2 | H93: =+E93/2

Sheet THALTEJ
A1: NUTAN NAGARIK SAHAKARI BANK LTD (GUJARAT BRANCHES & HEAD OFFICE)
A3: BRANCH NAME : THALTEJ BRANCH
A4: BRANCH CODE: 18
A5: =+BOPAL!A5
A7: CODE NO. | B7: PARTICULARS | D7: GGST | E7: CGST | F7: IGST | I7: LOCKER CLOSED CREDIT
A8: PL
A9: 3303 | B9: DD CANCEL CHARGES | D9: =+C9*9% | E9: =+D9 | F9: =IF(D9>0," ",C9*18%) | I9: 0
A10: 3200 | B10: COMMISION ON BILLS | D10: =+C10*9% | E10: =+D10 | F10: =IF(D10>0," ",C10*18%) | I10: 0
A11: 3215 | B11: COMMISION ON PAYORDER | D11: =+C11*9% | E11: =+D11 | F11: 0 | I11: 0
A12: 3220 | B12: COMMISION ON U.B.D. | D12: =+C12*9% | E12: =+D12 | F12: =IF(D12>0," ",C12*18%) | I12: 0
A13: 3225 | B13: COMMISION I.B.C. | D13: =+C13*9% | E13: =+D13 | F13: =IF(D13>0," ",C13*18%) | I13: 0
A14: 3230 | B14: COMMISION ON GUARANTEE | D14: =+C14*9% | E14: =+D14 | F14: =IF(D14>0," ",C14*18%) | I14: 0
A15: 3235 | B15: COMMISION ON DEMAND DRAFT | D15: =+C15*9% | E15: =+D15 | F15: =IF(D15>0," ",C15*18%) | I15: 0
A16: 3240 | B16: COMMISION ON U.B.C. | D16: =+C16*9% | E16: =+D16 | F16: =IF(D16>0," ",C16*18%) | I16: 0
A17: 3245 | B17: COMMISION ON L.C. | D17: =+C17*9% | E17: =+D17 | F17: =IF(D17>0," ",C17*18%) | I17: 0
A18: 3250 | B18: COMMISSION ON GUARANTEE | D18: =+C18*9% | E18: =+D18 | F18: =IF(D18>0," ",C18*18%) | I18: 0
A19: 3270 | B19: PROCESSING CHARGE | D19: =+C19*9% | E19: =+D19 | F19: 0 | I19: 0
A20: 3271 | B20: RENEWAL FEES | D20: =+C20*9% | E20: =+D20 | I20: 0
A21: 3274 | B21: INCOME FROM E-STAMPING | I21: 0
A22: 3276 | B22: COMMISION ON PAN | D22: =+C22*9% | E22: =+D22 | F22: =IF(D22>0," ",C22*18%) | I22: 0
A23: 3280 | B23: INSURANCE PREMIUM | D23: =+C23*9% | E23: =+D23 | F23: =IF(D23>0," ",C23*18%) | I23: 0
A24: 3281 | B24: ATM CHARGES | D24: =+C24*9% | E24: =+D24 | F24: =IF(D24>0," ",C24*18%) | I24: 0
A25: 3285 | B25: COMMISION ON RTGS | D25: =+C25*9% | E25: =+D25 | F25: =IF(D25>0," ",C25*18%) | I25: 0
A26: 3286 | B26: COMMISION ON PMJJBY LIC | D26: =+C26*9% | E26: =+D26 | F26: =IF(D26>0," ",C26*18%) | I26: 0
A27: 3287 | B27: COMM. ON PMSBY NEW INDIA ASSURANCE | D27: =+C27*9% | E27: =+D27 | F27: =IF(D27>0," ",C27*18%) | I27: 0
A28: 3291 | B28: CIBIL CHARGES | D28: =+C28*9% | E28: =+D28 | F28: =IF(D28>0," ",C28*18%) | I28: 0
A29: 3296 | B29: RTGS/NEFT MANUAL CHARGES | D29: =+C29*9% | E29: =+D29 | F29: =IF(D29>0," ",C29*18%) | I29: 0
A30: 3297 | B30: ASBA FORM PRINT CHARGES | D30: =+C30*9% | E30: =+D30 | F30: =IF(D30>0," ",C30*18%) | I30: 0
A31: 3298 | B31: MANDATE HANDLING CHARGES | D31: =+C31*9% | E31: =+D31 | F31: =IF(D31>0," ",C31*18%) | I31: 0
A32: 3299 | B32: SI EXECUTION FAILED CHARGES | D32: =+C32*9% | E32: =+D32 | F32: =IF(D32>0," ",C32*18%) | I32: 0
A33: 3300 | B33: INCIDENTAL CHARGES | D33: =+C33*9% | E33: =+D33 | F33: 0 | I33: 0
A34: 3301 | B34: INOPERATIVE CHARGES | D34: =+C34*9% | E34: =+D34 | F34: =IF(D34>0," ",C34*18%) | I34: 0
A35: 3302 | B35: PO CANCEL CHARGES | D35: =+C35*9% | E35: =+D35 | F35: =IF(D35>0," ",C35*18%) | I35: 0
A36: 3305 | B36: A/C SHARE TRANSFER FEES | D36: =+C36*9% | E36: =+D36 | F36: =IF(D36>0," ",C36*18%) | I36: 0
A37: 3309 | B37: MIS. INCOME WITH GST | D37: =+C37*9% | E37: =+D37 | F37: =IF(D37>0," ",C37*18%) | I37: 0
A38: 3310 | B38: MIS. INCOME | D38: =+C38*9% | E38: =+D38 | F38: =IF(D38>0," ",C38*18%) | I38: 0
A39: 3311 | B39: I/W CHQ. RET. CHARGES | D39: =+C39*9% | E39: =+D39 | F39: =IF(D39>0," ",C39*18%) | I39: 0
A40: 3312 | B40: O/W CHQ. RET. CHARGES | D40: =+C40*9% | E40: =+D40 | F40: =IF(D40>0," ",C40*18%) | I40: 0
A41: 3313 | B41: ECS RETD. CHARGES | D41: =+C41*9% | E41: =+D41 | F41: =IF(D41>0," ",C41*18%) | I41: 0
A42: 3314 | B42: CHQ. BOOK ISSUE CHARGES | D42: =+C42*9% | E42: =+D42 | F42: =IF(D42>0," ",C42*18%) | I42: 0
A43: 3315 | B43: CHARGES ON GODOWNS | D43: =+C43*9% | E43: =+D43 | F43: =IF(D43>0," ",C43*18%) | I43: 0
A44: 3316 | B44: CASH CHARGES | D44: =+C44*9% | E44: =+D44 | F44: 0 | I44: 0
A45: 3317 | B45: THE P&T CHARGES FOR LC/BG | D45: =+C45*9% | E45: =+D45 | F45: =IF(D45>0," ",C45*18%) | I45: 0
A46: 3318 | B46: OBC POSTAGE CHARGES | D46: =+C46*9% | E46: =+D46 | F46: =IF(D46>0," ",C46*18%) | I46: 0
A47: 3320 | B47: RENT ON LOCKER | D47: =+C47*9% | E47: =+D47 | F47: =IF(D47>0," ",C47*18%) | I47: 0
A48: 3321 | B48: ADHOC LIMIT CHARGES | D48: =+C48*9% | E48: =+D48 | F48: =IF(D48>0," ",C48*18%) | I48: 0
A49: 3322 | B49: INCOME FROM SALE OF OLD NEWS PAPERS | D49: =+C49*9% | E49: =+D49 | I49: 0
A50: 3324 | B50: PENALTY ON OVERDUE LOCKER RENT | D50: =+C50*9% | E50: =+D50 | I50: 0 | L50: 0
A51: 3325 | B51: MICR CLEARING CHARGES | D51: =+C51*9% | E51: =+D51 | I51: 0
A52: 3391 | B52: SMS CHARGES INCOME RECEIVED | D52: =+C52*9% | E52: =+D52 | F52: 0 | I52: 0 | L52: 0
A53: 3359 | B53: COMMITMENT CHARGES | D53: =+C53*9% | E53: =+D53 | F53: 0 | I53: 0
A54: 3825 | B54: EXTERNAL AUDIT FEES | D54: =+C54*9% | E54: =+D54 | F54: 0 | I54: 0
A55: 3362 | B55: FORECLOSURE CHARGES | I55: 0
A56: 3340 | B56: LOAN PROCESSING FEES | D56: =+C56*9% | E56: =+D56 | F56: =IF(D56>0," ",C56*18%) | I56: 0
A57: GL | I57: 0
A58: 1720 | B58: COMM. RECD. BUT NOT ACCRUED | D58: =+C58*9% | E58: =+D58 | F58: =IF(D58>0," ",C58*18%) | I58: 0
A59: 1836 | B59: RENT ON LOCKER RECEIVED BUT | D59: =+C59*9% | E59: =+D59 | F59: 0 | I59: 0
B60: NOT ACCRUED | I60: 0
B61: SALE OF ASSET ( CASH COUNTING MACHINE) | D61: =+C61*9% | E61: =+D61 | I61: 0
B62: TOTAL : | C62: =SUM(C9:C61) | D62: =SUM(D9:D61) | E62: =SUM(E9:E61) | F62: =SUM(F9:F61) | G62: =SUM(G9:G59) | H62: =SUM(H9:H59) | I62: =SUM(I9:I59)
A63: RCM | C63: 0
A64: PL 4112 | B64: DSA MARKETING EXPENSES | C64: 0 | D64: =+C64*0.09 | E64: =+D64
A65: PL 3750 | B65: LAW CHARGES (EXCLUSIVE) | D65: =+C65*9% | E65: =+D65 | F65: =IF(D65>0," ",C65*18%)
A66: PL 3751 | B66: INCIDENTAL LAW CHARGES (EXCLUSIVE) | C66: 0 | D66: =+C66*9% | E66: =+D66 | F66: =IF(D66>0," ",C66*18%)
A67: SUMMARY | G67: =+C62*0.09
A69: (1) INCOME
A70: PARTICULARS | D70: GGST | E70: CGST | F70: IGST
A72: (1) INCOME AS PER LEDGERWISE CALCULATION | D72: =+D62+D64 | E72: =+D72 | F72: =+F62
A73: (2) REFUND GIVEN BUT GST REFUND NOT GIVEN | C73: =G62 | D73: =+C73*0.09 | E73: =+D73 | F73: 0
D74: =+D72+D73 | E74: =+E72+E73 | F74: 0
A75: (3) PAYABLE AS PER LEDGER | E75: =+D75 | F75: 0
A76: DIFFERENCE | D76: =+D74-D75 | E76: =+E74-E75 | F76: =IF(F72>F75,F72,F75) | G76: =D76/9%
A78: (2) INPUT TAX CREDIT
A79: PARTICULARS | D79: GL 8546 GGST | E79: GL 8547 CGST | F79: GL 8548 IGST
A82: CURRENT MONTH INPUT TAX CREDIT AVAILABLE | E82: =+D82 | F82: 0 | G82: =++D82/2 | H82: =++E82/2 | I82: =++F82/2
A83: LESS : CREDIT CANNOT BE UTILISED (BCUZ GST NO NOT AVAILABLE IN BILL) | D83: =+C94 | E83: =+D83 | F83: 0 | G83: =++D83/2 | H83: =++E83/2 | I83: =++F83/2
A84: ELIGIBLE CREDIT | D84: =+D82-D83 | E84: =+E82-E810 | F84: =+F82-F83 | G84: =++D84/2 | H84: =++E84/2 | I84: =++F84/2
B90: INELLIGBLE CREDIT
B91: PARTY NAME | C91: GGST | D91: CGST | E91: IGST
B92: ROHAN AGENCY | C92: 0 | D92: =+C92 | E92: 0
B93: SATELIITE ELECTRONICS AND CONTROLS | C93: 0 | D93: 0
B94: TOTAL | C94: =+SUM(C92:C93) | D94: =+SUM(D92:D93) | E94: =+SUM(E92:E93)
G96: =+C94/2

Sheet CHANDKHEDA
A1: NUTAN NAGARIK SAHAKARI BANK LTD (GUJARAT BRANCHES & HEAD OFFICE)
A3: BRANCH NAME : CHANDKHEDA BRANCH
A4: BRANCH CODE: 23
A5: =+BOPAL!A5
A7: CODE NO. | B7: PARTICULARS | D7: GGST | E7: CGST | F7: IGST | I7: LOCKER CLOSED CREDIT
A8: PL
A9: 3303 | B9: DD CANCEL CHARGES | D9: =+C9*9% | E9: =+D9 | F9: =IF(D9>0," ",C9*18%) | I9: 0
A10: 3200 | B10: COMMISION ON BILLS | D10: =+C10*9% | E10: =+D10 | F10: =IF(D10>0," ",C10*18%) | I10: 0
A11: 3215 | B11: COMMISION ON PAYORDER | D11: =+C11*9% | E11: =+D11 | F11: 0 | I11: 0
A12: 3220 | B12: COMMISION ON U.B.D. | D12: =+C12*9% | E12: =+D12 | F12: =IF(D12>0," ",C12*18%) | I12: 0
A13: 3225 | B13: COMMISION I.B.C. | D13: =+C13*9% | E13: =+D13 | F13: =IF(D13>0," ",C13*18%) | I13: 0
A14: 3230 | B14: COMMISION ON GUARANTEE | D14: =+C14*9% | E14: =+D14 | F14: =IF(D14>0," ",C14*18%) | I14: 0
A15: 3235 | B15: COMMISION ON DEMAND DRAFT | D15: =+C15*9% | E15: =+D15 | F15: =IF(D15>0," ",C15*18%) | I15: 0
A16: 3240 | B16: COMMISION ON U.B.C. | D16: =+C16*9% | E16: =+D16 | F16: =IF(D16>0," ",C16*18%) | I16: 0
A17: 3245 | B17: COMMISION ON L.C. | D17: =+C17*9% | E17: =+D17 | F17: =IF(D17>0," ",C17*18%) | I17: 0
A18: 3250 | B18: COMMISSION ON GUARANTEE | D18: =+C18*9% | E18: =+D18 | F18: =IF(D18>0," ",C18*18%) | I18: 0
A19: 3270 | B19: PROCESSING CHARGE | D19: =+C19*9% | E19: =+D19 | F19: 0 | I19: 0 | J19: 0
A20: 3271 | B20: RENEWAL FEES | D20: =+C20*9% | E20: =+D20 | I20: 0
A21: 3274 | B21: INCOME FROM E-STAMPING | I21: 0
A22: 3276 | B22: COMMISION ON PAN | D22: =+C22*9% | E22: =+D22 | F22: =IF(D22>0," ",C22*18%) | I22: 0
A23: 3280 | B23: INSURANCE PREMIUM | D23: =+C23*9% | E23: =+D23 | F23: =IF(D23>0," ",C23*18%) | I23: 0
A24: 3281 | B24: ATM CHARGES | D24: =+C24*9% | E24: =+D24 | F24: =IF(D24>0," ",C24*18%) | I24: 0
A25: 3285 | B25: COMMISION ON RTGS | D25: =+C25*9% | E25: =+D25 | F25: =IF(D25>0," ",C25*18%) | I25: 0
A26: 3286 | B26: COMMISION ON PMJJBY LIC | D26: =+C26*9% | E26: =+D26 | F26: =IF(D26>0," ",C26*18%) | I26: 0
A27: 3287 | B27: COMM. ON PMSBY NEW INDIA ASSURANCE | D27: =+C27*9% | E27: =+D27 | F27: =IF(D27>0," ",C27*18%) | I27: 0
A28: 3291 | B28: CIBIL CHARGES | D28: =+C28*9% | E28: =+D28 | F28: =IF(D28>0," ",C28*18%) | I28: 0
A29: 3296 | B29: RTGS/NEFT MANUAL CHARGES | D29: =+C29*9% | E29: =+D29 | F29: =IF(D29>0," ",C29*18%) | I29: 0
A30: 3297 | B30: ASBA FORM PRINT CHARGES | D30: =+C30*9% | E30: =+D30 | F30: =IF(D30>0," ",C30*18%) | I30: 0
A31: 3298 | B31: MANDATE HANDLING CHARGES | D31: =+C31*9% | E31: =+D31 | F31: =IF(D31>0," ",C31*18%) | I31: 0
A32: 3299 | B32: SI EXECUTION FAILED CHARGES | D32: =+C32*9% | E32: =+D32 | F32: =IF(D32>0," ",C32*18%) | I32: 0
A33: 3300 | B33: INCIDENTAL CHARGES | D33: =+C33*9% | E33: =+D33 | F33: 0 | I33: 0
A34: 3301 | B34: INOPERATIVE CHARGES | D34: =+C34*9% | E34: =+D34 | F34: =IF(D34>0," ",C34*18%) | I34: 0
A35: 3302 | B35: PO CANCEL CHARGES | D35: =+C35*9% | E35: =+D35 | F35: =IF(D35>0," ",C35*18%) | I35: 0
A36: 3305 | B36: A/C SHARE TRANSFER FEES | D36: =+C36*9% | E36: =+D36 | F36: =IF(D36>0," ",C36*18%) | I36: 0
A37: 3309 | B37: MIS. INCOME WITH GST | D37: =+C37*9% | E37: =+D37 | F37: =IF(D37>0," ",C37*18%) | I37: 0
A38: 3310 | B38: MIS. INCOME | D38: =+C38*9% | E38: =+D38 | F38: =IF(D38>0," ",C38*18%) | I38: 0
A39: 3311 | B39: I/W CHQ. RET. CHARGES | D39: =+C39*9% | E39: =+D39 | F39: =IF(D39>0," ",C39*18%) | I39: 0
A40: 3312 | B40: O/W CHQ. RET. CHARGES | D40: =+C40*9% | E40: =+D40 | F40: =IF(D40>0," ",C40*18%) | I40: 0
A41: 3313 | B41: ECS RETD. CHARGES | D41: =+C41*9% | E41: =+D41 | F41: =IF(D41>0," ",C41*18%) | I41: 0
A42: 3314 | B42: CHQ. BOOK ISSUE CHARGES | D42: =+C42*9% | E42: =+D42 | F42: =IF(D42>0," ",C42*18%) | I42: 0
A43: 3315 | B43: CHARGES ON GODOWNS | D43: =+C43*9% | E43: =+D43 | F43: =IF(D43>0," ",C43*18%) | I43: 0
A44: 3316 | B44: CASH CHARGES | D44: =+C44*9% | E44: =+D44 | F44: 0 | I44: 0
A45: 3317 | B45: THE P&T CHARGES FOR LC/BG | D45: =+C45*9% | E45: =+D45 | F45: =IF(D45>0," ",C45*18%) | I45: 0
A46: 3318 | B46: OBC POSTAGE CHARGES | D46: =+C46*9% | E46: =+D46 | F46: =IF(D46>0," ",C46*18%) | I46: 0
A47: 3320 | B47: RENT ON LOCKER | D47: =+C47*9% | E47: =+D47 | F47: =IF(D47>0," ",C47*18%) | I47: 0
A48: 3321 | B48: ADHOC LIMIT CHARGES | D48: =+C48*9% | E48: =+D48 | F48: =IF(D48>0," ",C48*18%) | I48: 0
A49: 3322 | B49: INCOME FROM SALE OF OLD NEWS PAPERS | D49: =+C49*9% | E49: =+D49 | I49: 0
A50: 3324 | B50: PENALTY ON OVERDUE LOCKER RENT | D50: =+C50*9% | E50: =+D50 | I50: 0 | L50: 0
A51: 3325 | B51: MICR CLEARING CHARGES | D51: =+C51*9% | E51: =+D51 | I51: 0
A52: 3391 | B52: SMS CHARGES INCOME RECEIVED | D52: =+C52*9% | E52: =+D52 | F52: 0 | I52: 0 | L52: 0
A53: 3359 | B53: COMMITMENT CHARGES | D53: =+C53*9% | E53: =+D53 | F53: 0 | I53: 0
A54: 3825 | B54: EXTERNAL AUDIT FEES | D54: =+C54*9% | E54: =+D54 | F54: 0 | I54: 0
A55: 3362 | B55: FORECLOSURE CHARGES | I55: 0
A56: 3340 | B56: LOAN PROCESSING FEES | D56: =+C56*9% | E56: =+D56 | F56: =IF(D56>0," ",C56*18%) | I56: 0
A57: GL | I57: 0
A58: 1720 | B58: COMM. RECD. BUT NOT ACCRUED | D58: =+C58*9% | E58: =+D58 | F58: =IF(D58>0," ",C58*18%) | I58: 0
A59: 1836 | B59: RENT ON LOCKER RECEIVED BUT | D59: =+C59*9% | E59: =+D59 | F59: 0 | I59: 0 | K59: 0 | L59: =+K59*11.1111111111111
B60: NOT ACCRUED | I60: 0
B61: SALE OF ASSET ( CASH COUNTING MACHINE) | D61: =+C61*9% | E61: =+D61 | I61: 0
B62: TOTAL : | C62: =SUM(C9:C61) | D62: =SUM(D9:D61) | E62: =SUM(E9:E61) | F62: =SUM(F9:F61) | G62: =SUM(G9:G59) | H62: =SUM(H9:H59) | I62: =SUM(I9:I59)
A63: RCM | C63: 0
A64: PL 3750 | B64: LAW CHARGES (EXCLUSIVE) | C64: 0 | D64: =+C64*9% | E64: =+D64 | F64: =IF(D64>0," ",C64*18%) | G64: =+C62*0.09
A65: PL 3751 | B65: INCIDENTAL LAW CHARGES (EXCLUSIVE) | C65: 0 | D65: =+C65*9% | E65: =+D65 | F65: =IF(D65>0," ",C65*18%)
A66: SUMMARY
A68: (1) INCOME
A69: PARTICULARS | D69: GGST | E69: CGST | F69: IGST
A71: (1) INCOME AS PER LEDGERWISE CALCULATION | D71: =+D62 | E71: =+E62 | F71: =+F62
A72: (2) REFUND GIVEN BUT GST REFUND NOT GIVEN | C72: =G62 | D72: =+C72*0.09 | E72: =+D72 | F72: 0
D73: =+D71+D72 | E73: =+E71+E72 | F73: 0
A74: (3) PAYABLE AS PER LEDGER | D74: 5832.3 | E74: =+D74 | F74: 0
A75: DIFFERENCE | D75: =+D73-D74 | E75: =+E73-E74 | F75: =IF(F71>F74,F71,F74) | G75: =D75/9%
A77: (2) INPUT TAX CREDIT
A78: PARTICULARS | D78: GL 8546 GGST | E78: GL 8547 CGST | F78: GL 8548 IGST
A81: CURRENT MONTH INPUT TAX CREDIT AVAILABLE | D81: 89446.5 | E81: =+D81 | F81: 0 | G81: =++D81/2 | H81: =++E81/2 | I81: =++F81/2
A82: LESS : CREDIT CANNOT BE UTILISED (BCUZ GST NO NOT AVAILABLE IN BILL) | D82: =+C93 | E82: =+D82 | F82: 0 | G82: =++D82/2 | H82: =++E82/2 | I82: =++F82/2
A83: ELIGIBLE CREDIT | D83: =+D81-D82 | E83: =+E81-E809 | F83: =+F81-F82 | G83: =++D83/2 | H83: =++E83/2 | I83: =++F83/2
B89: INELLIGBLE CREDIT
B90: PARTY NAME | C90: GGST | D90: CGST | E90: IGST
B91: JAYSINGHS ICECREAM AND COLDDRINKS | C91: 0 | D91: =+C91 | E91: 0
B92: SATELIITE ELECTRONICS AND CONTROLS | C92: 0 | D92: 0
B93: TOTAL | C93: =+SUM(C91:C92) | D93: =+SUM(D91:D92) | E93: =+SUM(E91:E92)
G95: =+C93/2

Sheet VASTRAL
A1: NUTAN NAGARIK SAHAKARI BANK LTD (GUJARAT BRANCHES & HEAD OFFICE)
A3: BRANCH NAME : VASTRAL BRANCH
A4: BRANCH CODE: 24
A5: =+BOPAL!A5
A7: CODE NO. | B7: PARTICULARS | D7: GGST | E7: CGST | F7: IGST | I7: LOCKER CLOSED CREDIT
A8: PL
A9: 3303 | B9: DD CANCEL CHARGES | D9: =+C9*9% | E9: =+D9 | F9: =IF(D9>0," ",C9*18%) | I9: 0
A10: 3200 | B10: COMMISION ON BILLS | D10: =+C10*9% | E10: =+D10 | F10: =IF(D10>0," ",C10*18%) | I10: 0
A11: 3215 | B11: COMMISION ON PAYORDER | D11: =+C11*9% | E11: =+D11 | F11: 0 | I11: 0
A12: 3220 | B12: COMMISION ON U.B.D. | D12: =+C12*9% | E12: =+D12 | F12: =IF(D12>0," ",C12*18%) | I12: 0
A13: 3225 | B13: COMMISION I.B.C. | D13: =+C13*9% | E13: =+D13 | F13: =IF(D13>0," ",C13*18%) | I13: 0
A14: 3230 | B14: COMMISION ON GUARANTEE | D14: =+C14*9% | E14: =+D14 | F14: =IF(D14>0," ",C14*18%) | I14: 0
A15: 3235 | B15: COMMISION ON DEMAND DRAFT | D15: =+C15*9% | E15: =+D15 | F15: =IF(D15>0," ",C15*18%) | I15: 0
A16: 3240 | B16: COMMISION ON U.B.C. | D16: =+C16*9% | E16: =+D16 | F16: =IF(D16>0," ",C16*18%) | I16: 0
A17: 3245 | B17: COMMISION ON L.C. | D17: =+C17*9% | E17: =+D17 | F17: =IF(D17>0," ",C17*18%) | I17: 0
A18: 3250 | B18: COMMISSION ON GUARANTEE | D18: =+C18*9% | E18: =+D18 | F18: =IF(D18>0," ",C18*18%) | I18: 0
A19: 3270 | B19: PROCESSING CHARGE | D19: =+C19*9% | E19: =+D19 | F19: 0 | I19: 0 | J19: 0
A20: 3271 | B20: RENEWAL FEES | D20: =+C20*9% | E20: =+D20 | I20: 0
A21: 3274 | B21: INCOME FROM E-STAMPING | I21: 0
A22: 3276 | B22: COMMISION ON PAN | D22: =+C22*9% | E22: =+D22 | F22: =IF(D22>0," ",C22*18%) | I22: 0
A23: 3280 | B23: INSURANCE PREMIUM | D23: =+C23*9% | E23: =+D23 | F23: =IF(D23>0," ",C23*18%) | I23: 0
A24: 3281 | B24: ATM CHARGES | D24: =+C24*9% | E24: =+D24 | F24: =IF(D24>0," ",C24*18%) | I24: 0
A25: 3285 | B25: COMMISION ON RTGS | D25: =+C25*9% | E25: =+D25 | F25: =IF(D25>0," ",C25*18%) | I25: 0
A26: 3286 | B26: COMMISION ON PMJJBY LIC | D26: =+C26*9% | E26: =+D26 | F26: =IF(D26>0," ",C26*18%) | I26: 0
A27: 3287 | B27: COMM. ON PMSBY NEW INDIA ASSURANCE | D27: =+C27*9% | E27: =+D27 | F27: =IF(D27>0," ",C27*18%) | I27: 0
A28: 3291 | B28: CIBIL CHARGES | D28: =+C28*9% | E28: =+D28 | F28: =IF(D28>0," ",C28*18%) | I28: 0
A29: 3296 | B29: RTGS/NEFT MANUAL CHARGES | D29: =+C29*9% | E29: =+D29 | F29: =IF(D29>0," ",C29*18%) | I29: 0
A30: 3297 | B30: ASBA FORM PRINT CHARGES | D30: =+C30*9% | E30: =+D30 | F30: =IF(D30>0," ",C30*18%) | I30: 0
A31: 3298 | B31: MANDATE HANDLING CHARGES | D31: =+C31*9% | E31: =+D31 | F31: =IF(D31>0," ",C31*18%) | I31: 0
A32: 3299 | B32: SI EXECUTION FAILED CHARGES | D32: =+C32*9% | E32: =+D32 | F32: =IF(D32>0," ",C32*18%) | I32: 0
A33: 3300 | B33: INCIDENTAL CHARGES | D33: =+C33*9% | E33: =+D33 | F33: 0 | I33: 0
A34: 3301 | B34: INOPERATIVE CHARGES | D34: =+C34*9% | E34: =+D34 | F34: =IF(D34>0," ",C34*18%) | I34: 0
A35: 3302 | B35: PO CANCEL CHARGES | D35: =+C35*9% | E35: =+D35 | F35: =IF(D35>0," ",C35*18%) | I35: 0
A36: 3305 | B36: A/C SHARE TRANSFER FEES | D36: =+C36*9% | E36: =+D36 | F36: =IF(D36>0," ",C36*18%) | I36: 0
A37: 3309 | B37: MIS. INCOME WITH GST | D37: =+C37*9% | E37: =+D37 | F37: =IF(D37>0," ",C37*18%) | I37: 0
A38: 3310 | B38: MIS. INCOME | D38: =+C38*9% | E38: =+D38 | F38: =IF(D38>0," ",C38*18%) | I38: 0
A39: 3311 | B39: I/W CHQ. RET. CHARGES | D39: =+C39*9% | E39: =+D39 | F39: =IF(D39>0," ",C39*18%) | I39: 0
A40: 3312 | B40: O/W CHQ. RET. CHARGES | D40: =+C40*9% | E40: =+D40 | F40: =IF(D40>0," ",C40*18%) | I40: 0
A41: 3313 | B41: ECS RETD. CHARGES | D41: =+C41*9% | E41: =+D41 | F41: =IF(D41>0," ",C41*18%) | I41: 0
A42: 3314 | B42: CHQ. BOOK ISSUE CHARGES | D42: =+C42*9% | E42: =+D42 | F42: =IF(D42>0," ",C42*18%) | I42: 0
A43: 3315 | B43: CHARGES ON GODOWNS | D43: =+C43*9% | E43: =+D43 | F43: =IF(D43>0," ",C43*18%) | I43: 0
A44: 3316 | B44: CASH CHARGES | D44: =+C44*9% | E44: =+D44 | F44: 0 | I44: 0
A45: 3317 | B45: THE P&T CHARGES FOR LC/BG | D45: =+C45*9% | E45: =+D45 | F45: =IF(D45>0," ",C45*18%) | I45: 0
A46: 3318 | B46: OBC POSTAGE CHARGES | D46: =+C46*9% | E46: =+D46 | F46: =IF(D46>0," ",C46*18%) | I46: 0
A47: 3320 | B47: RENT ON LOCKER | D47: =+C47*9% | E47: =+D47 | F47: =IF(D47>0," ",C47*18%) | I47: 0
A48: 3321 | B48: ADHOC LIMIT CHARGES | D48: =+C48*9% | E48: =+D48 | F48: =IF(D48>0," ",C48*18%) | I48: 0
A49: 3322 | B49: INCOME FROM SALE OF OLD NEWS PAPERS | D49: =+C49*9% | E49: =+D49 | I49: 0
A50: 3324 | B50: PENALTY ON OVERDUE LOCKER RENT | D50: =+C50*9% | E50: =+D50 | I50: 0 | L50: 0
A51: 3325 | B51: MICR CLEARING CHARGES | D51: =+C51*9% | E51: =+D51 | I51: 0
A52: 3391 | B52: SMS CHARGES INCOME RECEIVED | D52: =+C52*9% | E52: =+D52 | F52: 0 | I52: 0 | L52: 0
A53: 3359 | B53: COMMITMENT CHARGES | D53: =+C53*9% | E53: =+D53 | F53: 0 | I53: 0
A54: 3825 | B54: EXTERNAL AUDIT FEES | D54: =+C54*9% | E54: =+D54 | F54: 0 | I54: 0
A55: 3362 | B55: FORECLOSURE CHARGES | I55: 0
A56: 3340 | B56: LOAN PROCESSING FEES | D56: =+C56*9% | E56: =+D56 | F56: =IF(D56>0," ",C56*18%) | I56: 0
A57: GL | I57: 0
A58: 1720 | B58: COMM. RECD. BUT NOT ACCRUED | D58: =+C58*9% | E58: =+D58 | F58: =IF(D58>0," ",C58*18%) | I58: 0
A59: 1836 | B59: RENT ON LOCKER RECEIVED BUT | D59: =+C59*9% | E59: =+D59 | F59: 0 | I59: 0 | K59: 0 | L59: =+K59*11.1111111111111
B60: NOT ACCRUED | I60: 0
B61: SALE OF ASSET ( CASH COUNTING MACHINE) | D61: =+C61*9% | E61: =+D61 | I61: 0
B62: TOTAL : | C62: =SUM(C9:C61) | D62: =SUM(D9:D61) | E62: =SUM(E9:E61) | F62: =SUM(F9:F61) | G62: =SUM(G9:G59) | H62: =SUM(H9:H59) | I62: =SUM(I9:I59)
A63: RCM | C63: 0
A64: PL 3750 | B64: LAW CHARGES (EXCLUSIVE) | C64: 0 | D64: =+C64*9% | E64: =+D64 | F64: =IF(D64>0," ",C64*18%) | G64: =+C62*0.09
A65: PL 3751 | B65: INCIDENTAL LAW CHARGES (EXCLUSIVE) | C65: 0 | D65: =+C65*9% | E65: =+D65 | F65: =IF(D65>0," ",C65*18%)
A66: SUMMARY
A68: (1) INCOME
A69: PARTICULARS | D69: GGST | E69: CGST | F69: IGST
A71: (1) INCOME AS PER LEDGERWISE CALCULATION | D71: =+D62 | E71: =+E62 | F71: =+F62
A72: (2) REFUND GIVEN BUT GST REFUND NOT GIVEN | C72: =G62 | D72: =+C72*0.09 | E72: =+D72 | F72: 0
D73: =+D71+D72 | E73: =+E71+E72 | F73: 0
A74: (3) PAYABLE AS PER LEDGER | E74: =+D74 | F74: 0
A75: DIFFERENCE | D75: =+D73-D74 | E75: =+E73-E74 | F75: =IF(F71>F74,F71,F74) | G75: =D75/9%
A77: (2) INPUT TAX CREDIT
A78: PARTICULARS | D78: GL 8546 GGST | E78: GL 8547 CGST | F78: GL 8548 IGST
A81: CURRENT MONTH INPUT TAX CREDIT AVAILABLE | E81: =+D81 | G81: =++D81/2 | H81: =++E81/2 | I81: =++F81/2
A82: LESS : CREDIT CANNOT BE UTILISED (BCUZ GST NO NOT AVAILABLE IN BILL) | D82: =+C93 | E82: =+D82 | F82: 0 | G82: =++D82/2 | H82: =++E82/2 | I82: =++F82/2
A83: ELIGIBLE CREDIT | D83: =+D81-D82 | E83: =+E81-E809 | F83: =+F81-F82 | G83: =++D83/2 | H83: =++E83/2 | I83: =++F83/2
B89: INELLIGBLE CREDIT
B90: PARTY NAME | C90: GGST | D90: CGST | E90: IGST
B91: JAYSINGHS ICECREAM AND COLDDRINKS | C91: 0 | D91: =+C91 | E91: 0
B92: SATELIITE ELECTRONICS AND CONTROLS | C92: 0 | D92: 0
B93: TOTAL | C93: =+SUM(C91:C92) | D93: =+SUM(D91:D92) | E93: =+SUM(E91:E92)
G95: =+C93/2

Sheet Sheet1
A1: NUTAN NAGARIK SAHAKARI BANK LTD (GUJARAT BRANCHES & HEAD OFFICE)
A3: ALL BRANCHES EXCEPT HO AND DEMAT
A5: =+THALTEJ!A5
A7: PL CODE NO. | B7: PARTICULARS | C7: INCOME | D7: GGST | E7: CGST | F7: IGST | G7: REFUND WITHOUT GST | H7: REFUND WITH GST | I7: TOTAL INCOME AS PER CAL
J8: INCOME AS ON 31-08-2026 (A) | K8: INCOME AS ON 31-07-2026 (A) | L8: INCOME FOR JULY 26 (A)-(B) | M8: DIFFERENCE | N8: PL CODE | O8: INCOME ASPER CAL | P8: INCOME AS ON 31-07-2026 (A) | Q8: INCOME AS ON 30-06-2026 (A) | R8: INCOM FOR JULY-26 (A)-(B) | S8: DIFF
A9: =+'LAW GARDEN'!A9 | B9: =+'LAW GARDEN'!B9 | C9: =+'ODHAV '!C9+RAKHIAL!C9+CHANGODAR!C9+'NEW SHARDA'!C9+ISANPUR!C9+MANINAGAR!C9+'SHANTI COMM'!C9+MASKATI!C9+VEJALPUR!C9+'JODHPUR-SATELLITE'!C9+PANJRAPOLE!C9+'ASHRAM ROAD'!C9+NARAYANNAGAR!C9+NARANPURA!C9+'DRIVE IN'!C9+'VASANA '!C9+SURAT!C9+'LAW GARDEN'!C9+'NEW CLOTH'!C9+BAPUNAGAR!C9+BOPAL!C9+THALTEJ!C9+CHANDKHEDA!C9+VASTRAL!C9 | D9: =+C9*0.09 | E9: =+D9 | F9: 0 | G9: =+'ODHAV '!G9+RAKHIAL!G9+CHANGODAR!G9+'NEW SHARDA'!G9+ISANPUR!G9+MANINAGAR!G9+'SHANTI COMM'!G9+MASKATI!G9+VEJALPUR!G9+'JODHPUR-SATELLITE'!G9+PANJRAPOLE!G9+'ASHRAM ROAD'!G9+NARAYANNAGAR!G9+NARANPURA!G9+'DRIVE IN'!G9+'VASANA '!G9+SURAT!G9+'LAW GARDEN'!G9+'NEW CLOTH'!G9+BAPUNAGAR!G9+BOPAL!G9+THALTEJ!G9 | H9: =+'ODHAV '!H9+RAKHIAL!H9+CHANGODAR!H9+'NEW SHARDA'!H9+ISANPUR!H9+MANINAGAR!H9+'SHANTI COMM'!H9+MASKATI!H9+VEJALPUR!H9+'JODHPUR-SATELLITE'!H9+PANJRAPOLE!H9+'ASHRAM ROAD'!H9+NARAYANNAGAR!H9+NARANPURA!H9+'DRIVE IN'!H9+'VASANA '!H9+SURAT!H9+'LAW GARDEN'!H9+'NEW CLOTH'!H9+BAPUNAGAR!H9+BOPAL!H9+THALTEJ!H9 | I9: =+C9 | J9: 540 | K9: 420 | L9: =+J9-K9 | M9: =+I9-L9 | N9: 3282 | O9: =+HO!C17 | P9: 0 | Q9: 0 | R9: =12690-12690.22 | S9: =+O9-R9
A10: 3200 | B10: COMMISION ON BILLS | C10: =+'ODHAV '!C10+RAKHIAL!C10+CHANGODAR!C10+'NEW SHARDA'!C10+ISANPUR!C10+MANINAGAR!C10+'SHANTI COMM'!C10+MASKATI!C10+VEJALPUR!C10+'JODHPUR-SATELLITE'!C10+PANJRAPOLE!C10+'ASHRAM ROAD'!C10+NARAYANNAGAR!C10+NARANPURA!C10+'DRIVE IN'!C10+'VASANA '!C10+SURAT!C10+'LAW GARDEN'!C10+'NEW CLOTH'!C10+BAPUNAGAR!C10+BOPAL!C10+THALTEJ!C10+CHANDKHEDA!C10+VASTRAL!C10 | D10: =+C10*9% | E10: =+D10 | G10: 0 | H10: =+'ODHAV '!H10+RAKHIAL!H10+CHANGODAR!H10+'NEW SHARDA'!H10+ISANPUR!H10+MANINAGAR!H10+'SHANTI COMM'!H10+MASKATI!H10+VEJALPUR!H10+'JODHPUR-SATELLITE'!H10+PANJRAPOLE!H10+'ASHRAM ROAD'!H10+NARAYANNAGAR!H10+NARANPURA!H10+'DRIVE IN'!H10+'VASANA '!H10+SURAT!H10+'LAW GARDEN'!H10+'NEW CLOTH'!H10+BAPUNAGAR!H10+BOPAL!H10+THALTEJ!H10 | I10: =+C10 | L10: =+J10-K10 | M10: =+I10-L10 | N10: 3284 | O10: =+HO!C18 | P10: 29746.31 | Q10: 22192.81 | R10: =+P10-Q10 | S10: =+O10-R10
A11: 3215 | B11: COMMISION ON PAYORDER | C11: =+'ODHAV '!C11+RAKHIAL!C11+CHANGODAR!C11+'NEW SHARDA'!C11+ISANPUR!C11+MANINAGAR!C11+'SHANTI COMM'!C11+MASKATI!C11+VEJALPUR!C11+'JODHPUR-SATELLITE'!C11+PANJRAPOLE!C11+'ASHRAM ROAD'!C11+NARAYANNAGAR!C11+NARANPURA!C11+'DRIVE IN'!C11+'VASANA '!C11+SURAT!C11+'LAW GARDEN'!C11+'NEW CLOTH'!C11+BAPUNAGAR!C11+BOPAL!C11+THALTEJ!C11+CHANDKHEDA!C11+VASTRAL!C11 | D11: =+C11*9% | E11: =+D11 | F11: =IF(D11>0," ",C11*18%) | G11: =+'ODHAV '!G11+RAKHIAL!G11+CHANGODAR!G11+'NEW SHARDA'!G11+ISANPUR!G11+MANINAGAR!G11+'SHANTI COMM'!G11+MASKATI!G11+VEJALPUR!G11+'JODHPUR-SATELLITE'!G11+PANJRAPOLE!G11+'ASHRAM ROAD'!G11+NARAYANNAGAR!G11+NARANPURA!G11+'DRIVE IN'!G11+'VASANA '!G11+SURAT!G11+'LAW GARDEN'!G11+'NEW CLOTH'!G11+BAPUNAGAR!G11+BOPAL!G11+THALTEJ!G11 | H11: =+'ODHAV '!H11+RAKHIAL!H11+CHANGODAR!H11+'NEW SHARDA'!H11+ISANPUR!H11+MANINAGAR!H11+'SHANTI COMM'!H11+MASKATI!H11+VEJALPUR!H11+'JODHPUR-SATELLITE'!H11+PANJRAPOLE!H11+'ASHRAM ROAD'!H11+NARAYANNAGAR!H11+NARANPURA!H11+'DRIVE IN'!H11+'VASANA '!H11+SURAT!H11+'LAW GARDEN'!H11+'NEW CLOTH'!H11+BAPUNAGAR!H11+BOPAL!H11+THALTEJ!H11 | I11: =+C11 | J11: 17225 | K11: 14275 | L11: =+J11-K11 | M11: =+I11-L11 | N11: 3290 | O11: =+HO!C44 | P11: 190462.36 | Q11: 137358.2 | R11: =+P11-Q11 | S11: =+O11-R11
A12: 3220 | B12: COMMISION ON U.B.D. | C12: =+'ODHAV '!C12+RAKHIAL!C12+CHANGODAR!C12+'NEW SHARDA'!C12+ISANPUR!C12+MANINAGAR!C12+'SHANTI COMM'!C12+MASKATI!C12+VEJALPUR!C12+'JODHPUR-SATELLITE'!C12+PANJRAPOLE!C12+'ASHRAM ROAD'!C12+NARAYANNAGAR!C12+NARANPURA!C12+'DRIVE IN'!C12+'VASANA '!C12+SURAT!C12+'LAW GARDEN'!C12+'NEW CLOTH'!C12+BAPUNAGAR!C12+BOPAL!C12+THALTEJ!C12+CHANDKHEDA!C12+VASTRAL!C12 | D12: =+C12*9% | E12: =+D12 | G12: =+'ODHAV '!G12+RAKHIAL!G12+CHANGODAR!G12+'NEW SHARDA'!G12+ISANPUR!G12+MANINAGAR!G12+'SHANTI COMM'!G12+MASKATI!G12+VEJALPUR!G12+'JODHPUR-SATELLITE'!G12+PANJRAPOLE!G12+'ASHRAM ROAD'!G12+NARAYANNAGAR!G12+NARANPURA!G12+'DRIVE IN'!G12+'VASANA '!G12+SURAT!G12+'LAW GARDEN'!G12+'NEW CLOTH'!G12+BAPUNAGAR!G12+BOPAL!G12+THALTEJ!G12 | H12: =+'ODHAV '!H12+RAKHIAL!H12+CHANGODAR!H12+'NEW SHARDA'!H12+ISANPUR!H12+MANINAGAR!H12+'SHANTI COMM'!H12+MASKATI!H12+VEJALPUR!H12+'JODHPUR-SATELLITE'!H12+PANJRAPOLE!H12+'ASHRAM ROAD'!H12+NARAYANNAGAR!H12+NARANPURA!H12+'DRIVE IN'!H12+'VASANA '!H12+SURAT!H12+'LAW GARDEN'!H12+'NEW CLOTH'!H12+BAPUNAGAR!H12+BOPAL!H12+THALTEJ!H12 | I12: =+C12 | J12: 428111 | K12: 263983 | L12: =+J12-K12 | M12: =+I12-L12 | N12: 3292 | O12: =+HO!C24 | P12: 322 | Q12: 322 | R12: =+P12-Q12 | S12: =+O12-R12
A13: 3225 | B13: COMMISION I.B.C. | C13: =+'ODHAV '!C13+RAKHIAL!C13+CHANGODAR!C13+'NEW SHARDA'!C13+ISANPUR!C13+MANINAGAR!C13+'SHANTI COMM'!C13+MASKATI!C13+VEJALPUR!C13+'JODHPUR-SATELLITE'!C13+PANJRAPOLE!C13+'ASHRAM ROAD'!C13+NARAYANNAGAR!C13+NARANPURA!C13+'DRIVE IN'!C13+'VASANA '!C13+SURAT!C13+'LAW GARDEN'!C13+'NEW CLOTH'!C13+BAPUNAGAR!C13+BOPAL!C13+THALTEJ!C13+CHANDKHEDA!C13+VASTRAL!C13 | D13: =+C13*9% | E13: =+D13 | F13: =IF(D13>0," ",C13*18%) | G13: =+'ODHAV '!G13+RAKHIAL!G13+CHANGODAR!G13+'NEW SHARDA'!G13+ISANPUR!G13+MANINAGAR!G13+'SHANTI COMM'!G13+MASKATI!G13+VEJALPUR!G13+'JODHPUR-SATELLITE'!G13+PANJRAPOLE!G13+'ASHRAM ROAD'!G13+NARAYANNAGAR!G13+NARANPURA!G13+'DRIVE IN'!G13+'VASANA '!G13+SURAT!G13+'LAW GARDEN'!G13+'NEW CLOTH'!G13+BAPUNAGAR!G13+BOPAL!G13+THALTEJ!G13 | H13: =+'ODHAV '!H13+RAKHIAL!H13+CHANGODAR!H13+'NEW SHARDA'!H13+ISANPUR!H13+MANINAGAR!H13+'SHANTI COMM'!H13+MASKATI!H13+VEJALPUR!H13+'JODHPUR-SATELLITE'!H13+PANJRAPOLE!H13+'ASHRAM ROAD'!H13+NARAYANNAGAR!H13+NARANPURA!H13+'DRIVE IN'!H13+'VASANA '!H13+SURAT!H13+'LAW GARDEN'!H13+'NEW CLOTH'!H13+BAPUNAGAR!H13+BOPAL!H13+THALTEJ!H13 | I13: =+C13 | L13: =+J13-K13 | M13: =+I13-L13 | N13: 3338 | O13: =+HO!C40 | P13: 0 | Q13: 0 | R13: =+P13-Q13 | S13: =+O13-R13
A14: 3230 | B14: COMMISION ON GUARANTEE | C14: =+'ODHAV '!C14+RAKHIAL!C14+CHANGODAR!C14+'NEW SHARDA'!C14+ISANPUR!C14+MANINAGAR!C14+'SHANTI COMM'!C14+MASKATI!C14+VEJALPUR!C14+'JODHPUR-SATELLITE'!C14+PANJRAPOLE!C14+'ASHRAM ROAD'!C14+NARAYANNAGAR!C14+NARANPURA!C14+'DRIVE IN'!C14+'VASANA '!C14+SURAT!C14+'LAW GARDEN'!C14+'NEW CLOTH'!C14+BAPUNAGAR!C14+BOPAL!C14+THALTEJ!C14+CHANDKHEDA!C14+VASTRAL!C14 | D14: =+C14*9% | E14: =+D14 | F14: 0 | G14: =+'ODHAV '!G14+RAKHIAL!G14+CHANGODAR!G14+'NEW SHARDA'!G14+ISANPUR!G14+MANINAGAR!G14+'SHANTI COMM'!G14+MASKATI!G14+VEJALPUR!G14+'JODHPUR-SATELLITE'!G14+PANJRAPOLE!G14+'ASHRAM ROAD'!G14+NARAYANNAGAR!G14+NARANPURA!G14+'DRIVE IN'!G14+'VASANA '!G14+SURAT!G14+'LAW GARDEN'!G14+'NEW CLOTH'!G14+BAPUNAGAR!G14+BOPAL!G14+THALTEJ!G14 | H14: =+'ODHAV '!H14+RAKHIAL!H14+CHANGODAR!H14+'NEW SHARDA'!H14+ISANPUR!H14+MANINAGAR!H14+'SHANTI COMM'!H14+MASKATI!H14+VEJALPUR!H14+'JODHPUR-SATELLITE'!H14+PANJRAPOLE!H14+'ASHRAM ROAD'!H14+NARAYANNAGAR!H14+NARANPURA!H14+'DRIVE IN'!H14+'VASANA '!H14+SURAT!H14+'LAW GARDEN'!H14+'NEW CLOTH'!H14+BAPUNAGAR!H14+BOPAL!H14+THALTEJ!H14 | I14: =+C14 | J14: 938590 | K14: 700251 | L14: =+J14-K14 | M14: =+I14-L14 | N14: 3293 | O14: =+HO!C25 | P14: 1963 | Q14: 1491 | R14: =+P14-Q14 | S14: =+O14-R14
A15: 3235 | B15: COMMISION ON DEMAND DRAFT | C15: =+'ODHAV '!C15+RAKHIAL!C15+CHANGODAR!C15+'NEW SHARDA'!C15+ISANPUR!C15+MANINAGAR!C15+'SHANTI COMM'!C15+MASKATI!C15+VEJALPUR!C15+'JODHPUR-SATELLITE'!C15+PANJRAPOLE!C15+'ASHRAM ROAD'!C15+NARAYANNAGAR!C15+NARANPURA!C15+'DRIVE IN'!C15+'VASANA '!C15+SURAT!C15+'LAW GARDEN'!C15+'NEW CLOTH'!C15+BAPUNAGAR!C15+BOPAL!C15+THALTEJ!C15+CHANDKHEDA!C15+VASTRAL!C15 | D15: =+C15*9% | E15: =+D15 | G15: =+'ODHAV '!G15+RAKHIAL!G15+CHANGODAR!G15+'NEW SHARDA'!G15+ISANPUR!G15+MANINAGAR!G15+'SHANTI COMM'!G15+MASKATI!G15+VEJALPUR!G15+'JODHPUR-SATELLITE'!G15+PANJRAPOLE!G15+'ASHRAM ROAD'!G15+NARAYANNAGAR!G15+NARANPURA!G15+'DRIVE IN'!G15+'VASANA '!G15+SURAT!G15+'LAW GARDEN'!G15+'NEW CLOTH'!G15+BAPUNAGAR!G15+BOPAL!G15+THALTEJ!G15 | H15: =+'ODHAV '!H15+RAKHIAL!H15+CHANGODAR!H15+'NEW SHARDA'!H15+ISANPUR!H15+MANINAGAR!H15+'SHANTI COMM'!H15+MASKATI!H15+VEJALPUR!H15+'JODHPUR-SATELLITE'!H15+PANJRAPOLE!H15+'ASHRAM ROAD'!H15+NARAYANNAGAR!H15+NARANPURA!H15+'DRIVE IN'!H15+'VASANA '!H15+SURAT!H15+'LAW GARDEN'!H15+'NEW CLOTH'!H15+BAPUNAGAR!H15+BOPAL!H15+THALTEJ!H15 | I15: =+C15 | J15: 9540 | K15: 6910 | L15: =+J15-K15 | M15: =+I15-L15 | N15: 3294 | P15: 0 | Q15: 133492.05 | R15: =+P15-Q15
A16: 3240 | B16: COMMISION ON U.B.C. | C16: =+'ODHAV '!C16+RAKHIAL!C16+CHANGODAR!C16+'NEW SHARDA'!C16+ISANPUR!C16+MANINAGAR!C16+'SHANTI COMM'!C16+MASKATI!C16+VEJALPUR!C16+'JODHPUR-SATELLITE'!C16+PANJRAPOLE!C16+'ASHRAM ROAD'!C16+NARAYANNAGAR!C16+NARANPURA!C16+'DRIVE IN'!C16+'VASANA '!C16+SURAT!C16+'LAW GARDEN'!C16+'NEW CLOTH'!C16+BAPUNAGAR!C16+BOPAL!C16+THALTEJ!C16+CHANDKHEDA!C16+VASTRAL!C16 | D16: =+C16*9% | E16: =+D16 | F16: =IF(D16>0," ",C16*18%) | G16: =+'ODHAV '!G16+RAKHIAL!G16+CHANGODAR!G16+'NEW SHARDA'!G16+ISANPUR!G16+MANINAGAR!G16+'SHANTI COMM'!G16+MASKATI!G16+VEJALPUR!G16+'JODHPUR-SATELLITE'!G16+PANJRAPOLE!G16+'ASHRAM ROAD'!G16+NARAYANNAGAR!G16+NARANPURA!G16+'DRIVE IN'!G16+'VASANA '!G16+SURAT!G16+'LAW GARDEN'!G16+'NEW CLOTH'!G16+BAPUNAGAR!G16+BOPAL!G16+THALTEJ!G16 | H16: =+'ODHAV '!H16+RAKHIAL!H16+CHANGODAR!H16+'NEW SHARDA'!H16+ISANPUR!H16+MANINAGAR!H16+'SHANTI COMM'!H16+MASKATI!H16+VEJALPUR!H16+'JODHPUR-SATELLITE'!H16+PANJRAPOLE!H16+'ASHRAM ROAD'!H16+NARAYANNAGAR!H16+NARANPURA!H16+'DRIVE IN'!H16+'VASANA '!H16+SURAT!H16+'LAW GARDEN'!H16+'NEW CLOTH'!H16+BAPUNAGAR!H16+BOPAL!H16+THALTEJ!H16 | I16: =+C16 | J16: 6000 | K16: 6000 | L16: =+J16-K16 | M16: =+I16-L16
A17: 3245 | B17: COMMISION ON L.C. | C17: =+'ODHAV '!C17+RAKHIAL!C17+CHANGODAR!C17+'NEW SHARDA'!C17+ISANPUR!C17+MANINAGAR!C17+'SHANTI COMM'!C17+MASKATI!C17+VEJALPUR!C17+'JODHPUR-SATELLITE'!C17+PANJRAPOLE!C17+'ASHRAM ROAD'!C17+NARAYANNAGAR!C17+NARANPURA!C17+'DRIVE IN'!C17+'VASANA '!C17+SURAT!C17+'LAW GARDEN'!C17+'NEW CLOTH'!C17+BAPUNAGAR!C17+BOPAL!C17+THALTEJ!C17+CHANDKHEDA!C17+VASTRAL!C17 | D17: =+C17*9% | E17: =+D17 | F17: =IF(D17>0," ",C17*18%) | G17: =+'ODHAV '!G17+RAKHIAL!G17+CHANGODAR!G17+'NEW SHARDA'!G17+ISANPUR!G17+MANINAGAR!G17+'SHANTI COMM'!G17+MASKATI!G17+VEJALPUR!G17+'JODHPUR-SATELLITE'!G17+PANJRAPOLE!G17+'ASHRAM ROAD'!G17+NARAYANNAGAR!G17+NARANPURA!G17+'DRIVE IN'!G17+'VASANA '!G17+SURAT!G17+'LAW GARDEN'!G17+'NEW CLOTH'!G17+BAPUNAGAR!G17+BOPAL!G17+THALTEJ!G17 | H17: =+'ODHAV '!H17+RAKHIAL!H17+CHANGODAR!H17+'NEW SHARDA'!H17+ISANPUR!H17+MANINAGAR!H17+'SHANTI COMM'!H17+MASKATI!H17+VEJALPUR!H17+'JODHPUR-SATELLITE'!H17+PANJRAPOLE!H17+'ASHRAM ROAD'!H17+NARAYANNAGAR!H17+NARANPURA!H17+'DRIVE IN'!H17+'VASANA '!H17+SURAT!H17+'LAW GARDEN'!H17+'NEW CLOTH'!H17+BAPUNAGAR!H17+BOPAL!H17+THALTEJ!H17 | I17: =+C17 | J17: 4500 | K17: 3500 | L17: =+J17-K17 | M17: =+I17-L17
A18: 3250 | B18: COMMISSION ON GUARANTEE | C18: =+'ODHAV '!C18+RAKHIAL!C18+CHANGODAR!C18+'NEW SHARDA'!C18+ISANPUR!C18+MANINAGAR!C18+'SHANTI COMM'!C18+MASKATI!C18+VEJALPUR!C18+'JODHPUR-SATELLITE'!C18+PANJRAPOLE!C18+'ASHRAM ROAD'!C18+NARAYANNAGAR!C18+NARANPURA!C18+'DRIVE IN'!C18+'VASANA '!C18+SURAT!C18+'LAW GARDEN'!C18+'NEW CLOTH'!C18+BAPUNAGAR!C18+BOPAL!C18+THALTEJ!C18+CHANDKHEDA!C18+VASTRAL!C18 | D18: =+C18*9% | E18: =+D18 | F18: =IF(D18>0," ",C18*18%) | G18: =+'ODHAV '!G18+RAKHIAL!G18+CHANGODAR!G18+'NEW SHARDA'!G18+ISANPUR!G18+MANINAGAR!G18+'SHANTI COMM'!G18+MASKATI!G18+VEJALPUR!G18+'JODHPUR-SATELLITE'!G18+PANJRAPOLE!G18+'ASHRAM ROAD'!G18+NARAYANNAGAR!G18+NARANPURA!G18+'DRIVE IN'!G18+'VASANA '!G18+SURAT!G18+'LAW GARDEN'!G18+'NEW CLOTH'!G18+BAPUNAGAR!G18+BOPAL!G18+THALTEJ!G18 | H18: =+'ODHAV '!H18+RAKHIAL!H18+CHANGODAR!H18+'NEW SHARDA'!H18+ISANPUR!H18+MANINAGAR!H18+'SHANTI COMM'!H18+MASKATI!H18+VEJALPUR!H18+'JODHPUR-SATELLITE'!H18+PANJRAPOLE!H18+'ASHRAM ROAD'!H18+NARAYANNAGAR!H18+NARANPURA!H18+'DRIVE IN'!H18+'VASANA '!H18+SURAT!H18+'LAW GARDEN'!H18+'NEW CLOTH'!H18+BAPUNAGAR!H18+BOPAL!H18+THALTEJ!H18 | I18: =+C18 | L18: =+J18-K18 | M18: =+I18-L18
A19: 3270 | B19: PROCESSING CHARGE | C19: =+'ODHAV '!C19+RAKHIAL!C19+CHANGODAR!C19+'NEW SHARDA'!C19+ISANPUR!C19+MANINAGAR!C19+'SHANTI COMM'!C19+MASKATI!C19+VEJALPUR!C19+'JODHPUR-SATELLITE'!C19+PANJRAPOLE!C19+'ASHRAM ROAD'!C19+NARAYANNAGAR!C19+NARANPURA!C19+'DRIVE IN'!C19+'VASANA '!C19+SURAT!C19+'LAW GARDEN'!C19+'NEW CLOTH'!C19+BAPUNAGAR!C19+BOPAL!C19+THALTEJ!C19+CHANDKHEDA!C19+VASTRAL!C19 | D19: =+C19*9% | E19: =+D19 | F19: =IF(D19>0," ",C19*18%) | G19: =+'ODHAV '!G19+RAKHIAL!G19+CHANGODAR!G19+'NEW SHARDA'!G19+ISANPUR!G19+MANINAGAR!G19+'SHANTI COMM'!G19+MASKATI!G19+VEJALPUR!G19+'JODHPUR-SATELLITE'!G19+PANJRAPOLE!G19+'ASHRAM ROAD'!G19+NARAYANNAGAR!G19+NARANPURA!G19+'DRIVE IN'!G19+'VASANA '!G19+SURAT!G19+'LAW GARDEN'!G19+'NEW CLOTH'!G19+BAPUNAGAR!G19+BOPAL!H19+THALTEJ!G19 | H19: =+'ODHAV '!H19+RAKHIAL!H19+CHANGODAR!H19+'NEW SHARDA'!H19+ISANPUR!H19+MANINAGAR!H19+'SHANTI COMM'!H19+MASKATI!H19+VEJALPUR!H19+'JODHPUR-SATELLITE'!H19+PANJRAPOLE!H19+'ASHRAM ROAD'!H19+NARAYANNAGAR!H19+NARANPURA!H19+'DRIVE IN'!H19+'VASANA '!H19+SURAT!H19+'LAW GARDEN'!H19+'NEW CLOTH'!H19+BAPUNAGAR!H19+BOPAL!I19+THALTEJ!H19 | I19: =+C19 | J19: 5909552.4 | K19: 4868822.4 | L19: =+J19-K19 | M19: =+I19-L19
A20: 3271 | B20: RENEWAL FEES | C20: =+'ODHAV '!C20+RAKHIAL!C20+CHANGODAR!C20+'NEW SHARDA'!C20+ISANPUR!C20+MANINAGAR!C20+'SHANTI COMM'!C20+MASKATI!C20+VEJALPUR!C20+'JODHPUR-SATELLITE'!C20+PANJRAPOLE!C20+'ASHRAM ROAD'!C20+NARAYANNAGAR!C20+NARANPURA!C20+'DRIVE IN'!C20+'VASANA '!C20+SURAT!C20+'LAW GARDEN'!C20+'NEW CLOTH'!C20+BAPUNAGAR!C20+BOPAL!C20+THALTEJ!C20+CHANDKHEDA!C20+VASTRAL!C20 | D20: =+C20*9% | E20: =+D20 | G20: =+'ODHAV '!G20+RAKHIAL!G20+CHANGODAR!G20+'NEW SHARDA'!G20+ISANPUR!G20+MANINAGAR!G20+'SHANTI COMM'!G20+MASKATI!G20+VEJALPUR!G20+'JODHPUR-SATELLITE'!G20+PANJRAPOLE!G20+'ASHRAM ROAD'!G20+NARAYANNAGAR!G20+NARANPURA!G20+'DRIVE IN'!G20+'VASANA '!G20+SURAT!G20+'LAW GARDEN'!G20+'NEW CLOTH'!G20+BAPUNAGAR!G20+BOPAL!G20+THALTEJ!G20 | H20: =+'ODHAV '!H20+RAKHIAL!H20+CHANGODAR!H20+'NEW SHARDA'!H20+ISANPUR!H20+MANINAGAR!H20+'SHANTI COMM'!H20+MASKATI!H20+VEJALPUR!H20+'JODHPUR-SATELLITE'!H20+PANJRAPOLE!H20+'ASHRAM ROAD'!H20+NARAYANNAGAR!H20+NARANPURA!H20+'DRIVE IN'!H20+'VASANA '!H20+SURAT!H20+'LAW GARDEN'!H20+'NEW CLOTH'!H20+BAPUNAGAR!H20+BOPAL!H20+THALTEJ!H20 | I20: =+C20 | J20: 255677 | K20: 190777 | L20: =+J20-K20 | M20: =+I20-L20
A21: 3274 | B21: INCOME FROM E-STAMPING | C21: =+'ODHAV '!C21+RAKHIAL!C21+CHANGODAR!C21+'NEW SHARDA'!C21+ISANPUR!C21+MANINAGAR!C21+'SHANTI COMM'!C21+MASKATI!C21+VEJALPUR!C21+'JODHPUR-SATELLITE'!C21+PANJRAPOLE!C21+'ASHRAM ROAD'!C21+NARAYANNAGAR!C21+NARANPURA!C21+'DRIVE IN'!C21+'VASANA '!C21+SURAT!C21+'LAW GARDEN'!C21+'NEW CLOTH'!C21+BAPUNAGAR!C21+BOPAL!C21+THALTEJ!C21+CHANDKHEDA!C21+VASTRAL!C21 | D21: =+C21*9% | E21: =+D21 | G21: =+'ODHAV '!G21+RAKHIAL!G21+CHANGODAR!G21+'NEW SHARDA'!G21+ISANPUR!G21+MANINAGAR!G21+'SHANTI COMM'!G21+MASKATI!G21+VEJALPUR!G21+'JODHPUR-SATELLITE'!G21+PANJRAPOLE!G21+'ASHRAM ROAD'!G21+NARAYANNAGAR!G21+NARANPURA!G21+'DRIVE IN'!G21+'VASANA '!G21+SURAT!G21+'LAW GARDEN'!G21+'NEW CLOTH'!G21+BAPUNAGAR!G21+BOPAL!G21+THALTEJ!G21 | H21: =+'ODHAV '!H21+RAKHIAL!H21+CHANGODAR!H21+'NEW SHARDA'!H21+ISANPUR!H21+MANINAGAR!H21+'SHANTI COMM'!H21+MASKATI!H21+VEJALPUR!H21+'JODHPUR-SATELLITE'!H21+PANJRAPOLE!H21+'ASHRAM ROAD'!H21+NARAYANNAGAR!H21+NARANPURA!H21+'DRIVE IN'!H21+'VASANA '!H21+SURAT!H21+'LAW GARDEN'!H21+'NEW CLOTH'!H21+BAPUNAGAR!H21+BOPAL!H21+THALTEJ!H21 | I21: =+C21 | J21: 165549.3 | K21: 125019.88 | L21: =+J21-K21 | M21: =+I21-L21
A22: 3276 | B22: COMMISION ON PAN | C22: =+'ODHAV '!C22+RAKHIAL!C22+CHANGODAR!C22+'NEW SHARDA'!C22+ISANPUR!C22+MANINAGAR!C22+'SHANTI COMM'!C22+MASKATI!C22+VEJALPUR!C22+'JODHPUR-SATELLITE'!C22+PANJRAPOLE!C22+'ASHRAM ROAD'!C22+NARAYANNAGAR!C22+NARANPURA!C22+'DRIVE IN'!C22+'VASANA '!C22+SURAT!C22+'LAW GARDEN'!C22+'NEW CLOTH'!C22+BAPUNAGAR!C22+BOPAL!C22+THALTEJ!C22+CHANDKHEDA!C22+VASTRAL!C22 | D22: =+C22*9% | E22: =+D22 | F22: 0 | G22: =+'ODHAV '!G22+RAKHIAL!G22+CHANGODAR!G23+'NEW SHARDA'!G22+ISANPUR!G22+MANINAGAR!G22+'SHANTI COMM'!G22+MASKATI!G22+VEJALPUR!G22+'JODHPUR-SATELLITE'!G22+PANJRAPOLE!G22+'ASHRAM ROAD'!G22+NARAYANNAGAR!G22+NARANPURA!G22+'DRIVE IN'!G22+'VASANA '!G22+SURAT!G22+'LAW GARDEN'!G22+'NEW CLOTH'!G22+BAPUNAGAR!G22+BOPAL!G22+THALTEJ!G22 | H22: =+'ODHAV '!H22+RAKHIAL!H22+CHANGODAR!H23+'NEW SHARDA'!H22+ISANPUR!H22+MANINAGAR!H22+'SHANTI COMM'!H22+MASKATI!H22+VEJALPUR!H22+'JODHPUR-SATELLITE'!H22+PANJRAPOLE!H22+'ASHRAM ROAD'!H22+NARAYANNAGAR!H22+NARANPURA!H22+'DRIVE IN'!H22+'VASANA '!H22+SURAT!H22+'LAW GARDEN'!H22+'NEW CLOTH'!H22+BAPUNAGAR!H22+BOPAL!H22+THALTEJ!H22 | I22: =+C22 | L22: =+J22-K22 | M22: =+I22-L22
A23: 3280 | B23: INSURANCE PREMIUM | C23: =+'ODHAV '!C23+RAKHIAL!C23+CHANGODAR!C23+'NEW SHARDA'!C23+ISANPUR!C23+MANINAGAR!C23+'SHANTI COMM'!C23+MASKATI!C23+VEJALPUR!C23+'JODHPUR-SATELLITE'!C23+PANJRAPOLE!C23+'ASHRAM ROAD'!C23+NARAYANNAGAR!C23+NARANPURA!C23+'DRIVE IN'!C23+'VASANA '!C23+SURAT!C23+'LAW GARDEN'!C23+'NEW CLOTH'!C23+BAPUNAGAR!C23+BOPAL!C23+THALTEJ!C23+CHANDKHEDA!C23+VASTRAL!C23 | D23: =+C23*9% | E23: =+D23 | F23: =IF(D23>0," ",C23*18%) | G23: =+'ODHAV '!G23+RAKHIAL!G23+CHANGODAR!G24+'NEW SHARDA'!G23+ISANPUR!G23+MANINAGAR!G23+'SHANTI COMM'!G23+MASKATI!G23+VEJALPUR!G23+'JODHPUR-SATELLITE'!G23+PANJRAPOLE!G23+'ASHRAM ROAD'!G23+NARAYANNAGAR!G23+NARANPURA!G23+'DRIVE IN'!G23+'VASANA '!G23+SURAT!G23+'LAW GARDEN'!G23+'NEW CLOTH'!G23+BAPUNAGAR!G23+BOPAL!G23+THALTEJ!G23 | H23: =+'ODHAV '!H23+RAKHIAL!H23+CHANGODAR!H24+'NEW SHARDA'!H23+ISANPUR!H23+MANINAGAR!H23+'SHANTI COMM'!H23+MASKATI!H23+VEJALPUR!H23+'JODHPUR-SATELLITE'!H23+PANJRAPOLE!H23+'ASHRAM ROAD'!H23+NARAYANNAGAR!H23+NARANPURA!H23+'DRIVE IN'!H23+'VASANA '!H23+SURAT!H23+'LAW GARDEN'!H23+'NEW CLOTH'!H23+BAPUNAGAR!H23+BOPAL!H23+THALTEJ!H23 | I23: =+C23 | L23: =+J23-K23 | M23: =+I23-L23
A24: 3281 | B24: ATM CHARGES | C24: =+'ODHAV '!C24+RAKHIAL!C24+CHANGODAR!C24+'NEW SHARDA'!C24+ISANPUR!C24+MANINAGAR!C24+'SHANTI COMM'!C24+MASKATI!C24+VEJALPUR!C24+'JODHPUR-SATELLITE'!C24+PANJRAPOLE!C24+'ASHRAM ROAD'!C24+NARAYANNAGAR!C24+NARANPURA!C24+'DRIVE IN'!C24+'VASANA '!C24+SURAT!C24+'LAW GARDEN'!C24+'NEW CLOTH'!C24+BAPUNAGAR!C24+BOPAL!C24+THALTEJ!C24+CHANDKHEDA!C24+VASTRAL!C24 | D24: =+C24*9% | E24: =+D24 | F24: =IF(D24>0," ",C24*18%) | G24: =+'ODHAV '!G24+RAKHIAL!G24+CHANGODAR!G25+'NEW SHARDA'!G24+ISANPUR!G24+MANINAGAR!G24+'SHANTI COMM'!G24+MASKATI!G24+VEJALPUR!G24+'JODHPUR-SATELLITE'!G24+PANJRAPOLE!G24+'ASHRAM ROAD'!G24+NARAYANNAGAR!G24+NARANPURA!G24+'DRIVE IN'!G24+'VASANA '!G24+SURAT!G24+'LAW GARDEN'!G24+'NEW CLOTH'!G24+BAPUNAGAR!G24+BOPAL!G24+THALTEJ!G24 | H24: =+'ODHAV '!H24+RAKHIAL!H24+CHANGODAR!H25+'NEW SHARDA'!H24+ISANPUR!H24+MANINAGAR!H24+'SHANTI COMM'!H24+MASKATI!H24+VEJALPUR!H24+'JODHPUR-SATELLITE'!H24+PANJRAPOLE!H24+'ASHRAM ROAD'!H24+NARAYANNAGAR!H24+NARANPURA!H24+'DRIVE IN'!H24+'VASANA '!H24+SURAT!H24+'LAW GARDEN'!H24+'NEW CLOTH'!H24+BAPUNAGAR!H24+BOPAL!H24+THALTEJ!H24 | I24: =+C24 | J24: 1825 | K24: 1025 | L24: =+J24-K24 | M24: =+I24-L24
A25: 3285 | B25: COMMISION ON RTGS | C25: =+'ODHAV '!C25+RAKHIAL!C25+CHANGODAR!C25+'NEW SHARDA'!C25+ISANPUR!C25+MANINAGAR!C25+'SHANTI COMM'!C25+MASKATI!C25+VEJALPUR!C25+'JODHPUR-SATELLITE'!C25+PANJRAPOLE!C25+'ASHRAM ROAD'!C25+NARAYANNAGAR!C25+NARANPURA!C25+'DRIVE IN'!C25+'VASANA '!C25+SURAT!C25+'LAW GARDEN'!C25+'NEW CLOTH'!C25+BAPUNAGAR!C25+BOPAL!C25+THALTEJ!C25+CHANDKHEDA!C25+VASTRAL!C25 | D25: =+C25*9% | E25: =+D25 | F25: 0 | G25: =+'ODHAV '!G26+RAKHIAL!G26+CHANGODAR!G27+'NEW SHARDA'!G26+ISANPUR!G26+MANINAGAR!G26+'SHANTI COMM'!G26+MASKATI!G26+VEJALPUR!G26+'JODHPUR-SATELLITE'!G26+PANJRAPOLE!G26+'ASHRAM ROAD'!G26+NARAYANNAGAR!G26+NARANPURA!G26+'DRIVE IN'!G26+'VASANA '!G26+SURAT!G26+'LAW GARDEN'!G26+'NEW CLOTH'!G26+BAPUNAGAR!G26+BOPAL!G26+THALTEJ!G26 | H25: =+'ODHAV '!H26+RAKHIAL!H26+CHANGODAR!H27+'NEW SHARDA'!H26+ISANPUR!H26+MANINAGAR!H26+'SHANTI COMM'!H26+MASKATI!H26+VEJALPUR!H26+'JODHPUR-SATELLITE'!H26+PANJRAPOLE!H26+'ASHRAM ROAD'!H26+NARAYANNAGAR!H26+NARANPURA!H26+'DRIVE IN'!H26+'VASANA '!H26+SURAT!H26+'LAW GARDEN'!H26+'NEW CLOTH'!H26+BAPUNAGAR!H26+BOPAL!H26+THALTEJ!H26 | I25: =+C25 | L25: =+J25-K25 | M25: =+I25-L25
A26: 3286 | B26: COMMISION ON PMJJBY LIC | C26: =+'ODHAV '!C26+RAKHIAL!C26+CHANGODAR!C26+'NEW SHARDA'!C26+ISANPUR!C26+MANINAGAR!C26+'SHANTI COMM'!C26+MASKATI!C26+VEJALPUR!C26+'JODHPUR-SATELLITE'!C26+PANJRAPOLE!C26+'ASHRAM ROAD'!C26+NARAYANNAGAR!C26+NARANPURA!C26+'DRIVE IN'!C26+'VASANA '!C26+SURAT!C26+'LAW GARDEN'!C26+'NEW CLOTH'!C26+BAPUNAGAR!C26+BOPAL!C26+THALTEJ!C26+CHANDKHEDA!C26+VASTRAL!C26 | D26: =+C26*9% | E26: =+D26 | G26: =+'ODHAV '!G27+RAKHIAL!G27+CHANGODAR!G28+'NEW SHARDA'!G27+ISANPUR!G27+MANINAGAR!G27+'SHANTI COMM'!G27+MASKATI!G27+VEJALPUR!G27+'JODHPUR-SATELLITE'!G27+PANJRAPOLE!G27+'ASHRAM ROAD'!G27+NARAYANNAGAR!G27+NARANPURA!G27+'DRIVE IN'!G27+'VASANA '!G27+SURAT!G27+'LAW GARDEN'!G27+'NEW CLOTH'!G27+BAPUNAGAR!G27+BOPAL!G27+THALTEJ!G27 | H26: =+'ODHAV '!H27+RAKHIAL!H27+CHANGODAR!H28+'NEW SHARDA'!H27+ISANPUR!H27+MANINAGAR!H27+'SHANTI COMM'!H27+MASKATI!H27+VEJALPUR!H27+'JODHPUR-SATELLITE'!H27+PANJRAPOLE!H27+'ASHRAM ROAD'!H27+NARAYANNAGAR!H27+NARANPURA!H27+'DRIVE IN'!H27+'VASANA '!H27+SURAT!H27+'LAW GARDEN'!H27+'NEW CLOTH'!H27+BAPUNAGAR!H27+BOPAL!H27+THALTEJ!H27 | I26: =+C26 | J26: 17806.32 | K26: 17702.1 | L26: =+J26-K26 | M26: =+I26-L26
A27: 3287 | B27: COMM. ON PMSBY NEW INDIA ASSURANCE | C27: =+'ODHAV '!C27+RAKHIAL!C27+CHANGODAR!C27+'NEW SHARDA'!C27+ISANPUR!C27+MANINAGAR!C27+'SHANTI COMM'!C27+MASKATI!C27+VEJALPUR!C27+'JODHPUR-SATELLITE'!C27+PANJRAPOLE!C27+'ASHRAM ROAD'!C27+NARAYANNAGAR!C27+NARANPURA!C27+'DRIVE IN'!C27+'VASANA '!C27+SURAT!C27+'LAW GARDEN'!C27+'NEW CLOTH'!C27+BAPUNAGAR!C27+BOPAL!C27+THALTEJ!C27+CHANDKHEDA!C27+VASTRAL!C27 | D27: =+C27*9% | E27: =+D27 | F27: =IF(D27>0," ",C27*18%) | G27: =+'ODHAV '!G28+RAKHIAL!G28+CHANGODAR!G29+'NEW SHARDA'!G28+ISANPUR!G28+MANINAGAR!G28+'SHANTI COMM'!G28+MASKATI!G28+VEJALPUR!G28+'JODHPUR-SATELLITE'!G28+PANJRAPOLE!G28+'ASHRAM ROAD'!G28+NARAYANNAGAR!G28+NARANPURA!G28+'DRIVE IN'!G28+'VASANA '!G28+SURAT!G28+'LAW GARDEN'!G28+'NEW CLOTH'!G28+BAPUNAGAR!G28+BOPAL!G28+THALTEJ!G28 | H27: =+'ODHAV '!H28+RAKHIAL!H28+CHANGODAR!H29+'NEW SHARDA'!H28+ISANPUR!H28+MANINAGAR!H28+'SHANTI COMM'!H28+MASKATI!H28+VEJALPUR!H28+'JODHPUR-SATELLITE'!H28+PANJRAPOLE!H28+'ASHRAM ROAD'!H28+NARAYANNAGAR!H28+NARANPURA!H28+'DRIVE IN'!H28+'VASANA '!H28+SURAT!H28+'LAW GARDEN'!H28+'NEW CLOTH'!H28+BAPUNAGAR!H28+BOPAL!H28+THALTEJ!H28 | I27: =+C27 | L27: =+J27-K27 | M27: =+I27-L27
A28: 3291 | B28: CIBIL CHARGES | C28: =+'ODHAV '!C28+RAKHIAL!C28+CHANGODAR!C28+'NEW SHARDA'!C28+ISANPUR!C28+MANINAGAR!C28+'SHANTI COMM'!C28+MASKATI!C28+VEJALPUR!C28+'JODHPUR-SATELLITE'!C28+PANJRAPOLE!C28+'ASHRAM ROAD'!C28+NARAYANNAGAR!C28+NARANPURA!C28+'DRIVE IN'!C28+'VASANA '!C28+SURAT!C28+'LAW GARDEN'!C28+'NEW CLOTH'!C28+BAPUNAGAR!C28+BOPAL!C28+THALTEJ!C28+CHANDKHEDA!C28+VASTRAL!C28 | D28: =+C28*9% | E28: =+D28 | G28: =+'ODHAV '!G29+RAKHIAL!G29+CHANGODAR!G30+'NEW SHARDA'!G29+ISANPUR!G29+MANINAGAR!G29+'SHANTI COMM'!G29+MASKATI!G29+VEJALPUR!G29+'JODHPUR-SATELLITE'!G29+PANJRAPOLE!G29+'ASHRAM ROAD'!G29+NARAYANNAGAR!G29+NARANPURA!G29+'DRIVE IN'!G29+'VASANA '!G29+SURAT!G29+'LAW GARDEN'!G29+'NEW CLOTH'!G29+BAPUNAGAR!G29+BOPAL!G29+THALTEJ!G29 | H28: =+'ODHAV '!H29+RAKHIAL!H29+CHANGODAR!H30+'NEW SHARDA'!H29+ISANPUR!H29+MANINAGAR!H29+'SHANTI COMM'!H29+MASKATI!H29+VEJALPUR!H29+'JODHPUR-SATELLITE'!H29+PANJRAPOLE!H29+'ASHRAM ROAD'!H29+NARAYANNAGAR!H29+NARANPURA!H29+'DRIVE IN'!H29+'VASANA '!H29+SURAT!H29+'LAW GARDEN'!H29+'NEW CLOTH'!H29+BAPUNAGAR!H29+BOPAL!H29+THALTEJ!H29 | I28: =+C28 | L28: =+J28-K28 | M28: =+I28-L28
A29: 3296 | B29: RTGS/NEFT MANUAL CHARGES | C29: =+'ODHAV '!C29+RAKHIAL!C29+CHANGODAR!C29+'NEW SHARDA'!C29+ISANPUR!C29+MANINAGAR!C29+'SHANTI COMM'!C29+MASKATI!C29+VEJALPUR!C29+'JODHPUR-SATELLITE'!C29+PANJRAPOLE!C29+'ASHRAM ROAD'!C29+NARAYANNAGAR!C29+NARANPURA!C29+'DRIVE IN'!C29+'VASANA '!C29+SURAT!C29+'LAW GARDEN'!C29+'NEW CLOTH'!C29+BAPUNAGAR!C29+BOPAL!C29+THALTEJ!C29+CHANDKHEDA!C29+VASTRAL!C29 | D29: =+C29*9% | E29: =+D29 | F29: =IF(D29>0," ",C29*18%) | G29: =+'ODHAV '!G30+RAKHIAL!G30+CHANGODAR!G31+'NEW SHARDA'!G30+ISANPUR!G30+MANINAGAR!G30+'SHANTI COMM'!G30+MASKATI!G30+VEJALPUR!G30+'JODHPUR-SATELLITE'!G30+PANJRAPOLE!G30+'ASHRAM ROAD'!G30+NARAYANNAGAR!G30+NARANPURA!G30+'DRIVE IN'!G30+'VASANA '!G30+SURAT!G30+'LAW GARDEN'!G30+'NEW CLOTH'!G30+BAPUNAGAR!G30+BOPAL!G30+THALTEJ!G30 | H29: =+'ODHAV '!H30+RAKHIAL!H30+CHANGODAR!H31+'NEW SHARDA'!H30+ISANPUR!H30+MANINAGAR!H30+'SHANTI COMM'!H30+MASKATI!H30+VEJALPUR!H30+'JODHPUR-SATELLITE'!H30+PANJRAPOLE!H30+'ASHRAM ROAD'!H30+NARAYANNAGAR!H30+NARANPURA!H30+'DRIVE IN'!H30+'VASANA '!H30+SURAT!H30+'LAW GARDEN'!H30+'NEW CLOTH'!H30+BAPUNAGAR!H30+BOPAL!H30+THALTEJ!H30 | I29: =+C29 | J29: 133202.5 | K29: 104282.5 | L29: =+J29-K29 | M29: =+I29-L29
A30: 3297 | B30: ASBA FORM PRINT CHARGES | C30: =+'ODHAV '!C30+RAKHIAL!C30+CHANGODAR!C30+'NEW SHARDA'!C30+ISANPUR!C30+MANINAGAR!C30+'SHANTI COMM'!C30+MASKATI!C30+VEJALPUR!C30+'JODHPUR-SATELLITE'!C30+PANJRAPOLE!C30+'ASHRAM ROAD'!C30+NARAYANNAGAR!C30+NARANPURA!C30+'DRIVE IN'!C30+'VASANA '!C30+SURAT!C30+'LAW GARDEN'!C30+'NEW CLOTH'!C30+BAPUNAGAR!C30+BOPAL!C30+THALTEJ!C30+CHANDKHEDA!C30+VASTRAL!C30 | D30: =+C30*9% | E30: =+D30 | F30: =IF(D30>0," ",C30*18%) | G30: =+'ODHAV '!G31+RAKHIAL!G31+CHANGODAR!G32+'NEW SHARDA'!G31+ISANPUR!G31+MANINAGAR!G31+'SHANTI COMM'!G31+MASKATI!G31+VEJALPUR!G31+'JODHPUR-SATELLITE'!G31+PANJRAPOLE!G31+'ASHRAM ROAD'!G31+NARAYANNAGAR!G31+NARANPURA!G31+'DRIVE IN'!G31+'VASANA '!G31+SURAT!G31+'LAW GARDEN'!G31+'NEW CLOTH'!G31+BAPUNAGAR!G31+BOPAL!G31+THALTEJ!G31 | H30: =+'ODHAV '!H31+RAKHIAL!H31+CHANGODAR!H32+'NEW SHARDA'!H31+ISANPUR!H31+MANINAGAR!H31+'SHANTI COMM'!H31+MASKATI!H31+VEJALPUR!H31+'JODHPUR-SATELLITE'!H31+PANJRAPOLE!H31+'ASHRAM ROAD'!H31+NARAYANNAGAR!H31+NARANPURA!H31+'DRIVE IN'!H31+'VASANA '!H31+SURAT!H31+'LAW GARDEN'!H31+'NEW CLOTH'!H31+BAPUNAGAR!H31+BOPAL!H31+THALTEJ!H31 | I30: =+C30 | J30: 167800 | K30: 54200 | L30: =+J30-K30 | M30: =+I30-L30
A31: 3298 | B31: MANDATE HANDLING CHARGES | C31: =+'ODHAV '!C31+RAKHIAL!C31+CHANGODAR!C31+'NEW SHARDA'!C31+ISANPUR!C31+MANINAGAR!C31+'SHANTI COMM'!C31+MASKATI!C31+VEJALPUR!C31+'JODHPUR-SATELLITE'!C31+PANJRAPOLE!C31+'ASHRAM ROAD'!C31+NARAYANNAGAR!C31+NARANPURA!C31+'DRIVE IN'!C31+'VASANA '!C31+SURAT!C31+'LAW GARDEN'!C31+'NEW CLOTH'!C31+BAPUNAGAR!C31+BOPAL!C31+THALTEJ!C31+CHANDKHEDA!C31+VASTRAL!C31 | D31: =+C31*9% | E31: =+D31 | F31: =IF(D31>0," ",C31*18%) | G31: =+'ODHAV '!G32+RAKHIAL!G32+CHANGODAR!G33+'NEW SHARDA'!G32+ISANPUR!G32+MANINAGAR!G32+'SHANTI COMM'!G32+MASKATI!G32+VEJALPUR!G32+'JODHPUR-SATELLITE'!G32+PANJRAPOLE!G32+'ASHRAM ROAD'!G32+NARAYANNAGAR!G32+NARANPURA!G32+'DRIVE IN'!G32+'VASANA '!G32+SURAT!G32+'LAW GARDEN'!G32+'NEW CLOTH'!G32+BAPUNAGAR!G32+BOPAL!G32+THALTEJ!G32 | H31: =+'ODHAV '!H32+RAKHIAL!H32+CHANGODAR!H33+'NEW SHARDA'!H32+ISANPUR!H32+MANINAGAR!H32+'SHANTI COMM'!H32+MASKATI!H32+VEJALPUR!H32+'JODHPUR-SATELLITE'!H32+PANJRAPOLE!H32+'ASHRAM ROAD'!H32+NARAYANNAGAR!H32+NARANPURA!H32+'DRIVE IN'!H32+'VASANA '!H32+SURAT!H32+'LAW GARDEN'!H32+'NEW CLOTH'!H32+BAPUNAGAR!H32+BOPAL!H32+THALTEJ!H32 | I31: =+C31 | J31: 62850 | K31: 49550 | L31: =+J31-K31 | M31: =+I31-L31
A32: 3299 | B32: SI EXECUTION FAILED CHARGES | C32: =+'ODHAV '!C32+RAKHIAL!C32+CHANGODAR!C32+'NEW SHARDA'!C32+ISANPUR!C32+MANINAGAR!C32+'SHANTI COMM'!C32+MASKATI!C32+VEJALPUR!C32+'JODHPUR-SATELLITE'!C32+PANJRAPOLE!C32+'ASHRAM ROAD'!C32+NARAYANNAGAR!C32+NARANPURA!C32+'DRIVE IN'!C32+'VASANA '!C32+SURAT!C32+'LAW GARDEN'!C32+'NEW CLOTH'!C32+BAPUNAGAR!C32+BOPAL!C32+THALTEJ!C32+CHANDKHEDA!C32+VASTRAL!C32 | D32: =+C32*9% | E32: =+D32 | F32: =IF(D32>0," ",C32*18%) | G32: =+'ODHAV '!G33+RAKHIAL!G33+CHANGODAR!G34+'NEW SHARDA'!G33+ISANPUR!G33+MANINAGAR!G33+'SHANTI COMM'!G33+MASKATI!G33+VEJALPUR!G33+'JODHPUR-SATELLITE'!G33+PANJRAPOLE!G33+'ASHRAM ROAD'!G33+NARAYANNAGAR!G33+NARANPURA!G33+'DRIVE IN'!G33+'VASANA '!G33+SURAT!G33+'LAW GARDEN'!G33+'NEW CLOTH'!G33+BAPUNAGAR!G33+BOPAL!G33+THALTEJ!G33 | H32: =+'ODHAV '!H33+RAKHIAL!H33+CHANGODAR!H34+'NEW SHARDA'!H33+ISANPUR!H33+MANINAGAR!H33+'SHANTI COMM'!H33+MASKATI!H33+VEJALPUR!H33+'JODHPUR-SATELLITE'!H33+PANJRAPOLE!H33+'ASHRAM ROAD'!H33+NARAYANNAGAR!H33+NARANPURA!H33+'DRIVE IN'!H33+'VASANA '!H33+SURAT!H33+'LAW GARDEN'!H33+'NEW CLOTH'!H33+BAPUNAGAR!H33+BOPAL!H33+THALTEJ!H33 | I32: =+C32 | J32: 1200 | K32: 1050 | L32: =+J32-K32 | M32: =+I32-L32
A33: 3300 | B33: INCIDENTAL CHARGES | C33: =+'ODHAV '!C33+RAKHIAL!C33+CHANGODAR!C33+'NEW SHARDA'!C33+ISANPUR!C33+MANINAGAR!C33+'SHANTI COMM'!C33+MASKATI!C33+VEJALPUR!C33+'JODHPUR-SATELLITE'!C33+PANJRAPOLE!C33+'ASHRAM ROAD'!C33+NARAYANNAGAR!C33+NARANPURA!C33+'DRIVE IN'!C33+'VASANA '!C33+SURAT!C33+'LAW GARDEN'!C33+'NEW CLOTH'!C33+BAPUNAGAR!C33+BOPAL!C33+THALTEJ!C33+CHANDKHEDA!C33+VASTRAL!C33 | D33: =+C33*9% | E33: =+D33 | G33: =+'ODHAV '!G34+RAKHIAL!G34+CHANGODAR!G35+'NEW SHARDA'!G34+ISANPUR!G34+MANINAGAR!G34+'SHANTI COMM'!G34+MASKATI!G34+VEJALPUR!G34+'JODHPUR-SATELLITE'!G34+PANJRAPOLE!G34+'ASHRAM ROAD'!G34+NARAYANNAGAR!G34+NARANPURA!G34+'DRIVE IN'!G34+'VASANA '!G34+SURAT!G34+'LAW GARDEN'!G34+'NEW CLOTH'!G34+BAPUNAGAR!G34+BOPAL!G34+THALTEJ!G34 | H33: =+'ODHAV '!H34+RAKHIAL!H34+CHANGODAR!H35+'NEW SHARDA'!H34+ISANPUR!H34+MANINAGAR!H34+'SHANTI COMM'!H34+MASKATI!H34+VEJALPUR!H34+'JODHPUR-SATELLITE'!H34+PANJRAPOLE!H34+'ASHRAM ROAD'!H34+NARAYANNAGAR!H34+NARANPURA!H34+'DRIVE IN'!H34+'VASANA '!H34+SURAT!H34+'LAW GARDEN'!H34+'NEW CLOTH'!H34+BAPUNAGAR!H34+BOPAL!H34+THALTEJ!H34 | I33: =+C33 | J33: 97267.1 | K33: 79581.92 | L33: =+J33-K33 | M33: =+I33-L33
A34: 3301 | B34: INOPERATIVE CHARGES | C34: =+'ODHAV '!C34+RAKHIAL!C34+CHANGODAR!C34+'NEW SHARDA'!C34+ISANPUR!C34+MANINAGAR!C34+'SHANTI COMM'!C34+MASKATI!C34+VEJALPUR!C34+'JODHPUR-SATELLITE'!C34+PANJRAPOLE!C34+'ASHRAM ROAD'!C34+NARAYANNAGAR!C34+NARANPURA!C34+'DRIVE IN'!C34+'VASANA '!C34+SURAT!C34+'LAW GARDEN'!C34+'NEW CLOTH'!C34+BAPUNAGAR!C34+BOPAL!C34+THALTEJ!C34+CHANDKHEDA!C34+VASTRAL!C34 | D34: =+C34*9% | E34: =+D34 | G34: =+'ODHAV '!G35+RAKHIAL!G35+CHANGODAR!G36+'NEW SHARDA'!G35+ISANPUR!G35+MANINAGAR!G35+'SHANTI COMM'!G35+MASKATI!G35+VEJALPUR!G35+'JODHPUR-SATELLITE'!G35+PANJRAPOLE!G35+'ASHRAM ROAD'!G35+NARAYANNAGAR!G35+NARANPURA!G35+'DRIVE IN'!G35+'VASANA '!G35+SURAT!G35+'LAW GARDEN'!G35+'NEW CLOTH'!G35+BAPUNAGAR!G35+BOPAL!G35+THALTEJ!G35 | H34: =+'ODHAV '!H35+RAKHIAL!H35+CHANGODAR!H36+'NEW SHARDA'!H35+ISANPUR!H35+MANINAGAR!H35+'SHANTI COMM'!H35+MASKATI!H35+VEJALPUR!H35+'JODHPUR-SATELLITE'!H35+PANJRAPOLE!H35+'ASHRAM ROAD'!H35+NARAYANNAGAR!H35+NARANPURA!H35+'DRIVE IN'!H35+'VASANA '!H35+SURAT!H35+'LAW GARDEN'!H35+'NEW CLOTH'!H35+BAPUNAGAR!H35+BOPAL!H35+THALTEJ!H35 | I34: =+C34 | L34: =+J34-K34 | M34: =+I34-L34
A35: 3302 | B35: PO CANCEL CHARGES | C35: =+'ODHAV '!C35+RAKHIAL!C35+CHANGODAR!C35+'NEW SHARDA'!C35+ISANPUR!C35+MANINAGAR!C35+'SHANTI COMM'!C35+MASKATI!C35+VEJALPUR!C35+'JODHPUR-SATELLITE'!C35+PANJRAPOLE!C35+'ASHRAM ROAD'!C35+NARAYANNAGAR!C35+NARANPURA!C35+'DRIVE IN'!C35+'VASANA '!C35+SURAT!C35+'LAW GARDEN'!C35+'NEW CLOTH'!C35+BAPUNAGAR!C35+BOPAL!C35+THALTEJ!C35+CHANDKHEDA!C35+VASTRAL!C35 | D35: =+C35*9% | E35: =+D35 | F35: =+'ODHAV '!F35 | G35: =+'ODHAV '!G36+RAKHIAL!G36+CHANGODAR!G37+'NEW SHARDA'!G36+ISANPUR!G36+MANINAGAR!G36+'SHANTI COMM'!G36+MASKATI!G36+VEJALPUR!G36+'JODHPUR-SATELLITE'!G36+PANJRAPOLE!G36+'ASHRAM ROAD'!G36+NARAYANNAGAR!G36+NARANPURA!G36+'DRIVE IN'!G36+'VASANA '!G36+SURAT!G36+'LAW GARDEN'!G36+'NEW CLOTH'!G36+BAPUNAGAR!G36+BOPAL!G36+THALTEJ!G36 | H35: =+'ODHAV '!H36+RAKHIAL!H36+CHANGODAR!H37+'NEW SHARDA'!H36+ISANPUR!H36+MANINAGAR!H36+'SHANTI COMM'!H36+MASKATI!H36+VEJALPUR!H36+'JODHPUR-SATELLITE'!H36+PANJRAPOLE!H36+'ASHRAM ROAD'!H36+NARAYANNAGAR!H36+NARANPURA!H36+'DRIVE IN'!H36+'VASANA '!H36+SURAT!H36+'LAW GARDEN'!H36+'NEW CLOTH'!H36+BAPUNAGAR!H36+BOPAL!H36+THALTEJ!H36 | I35: =+C35 | J35: 160 | K35: 160 | L35: =+J35-K35 | M35: =+I35-L35
